Workbook

Sheet ENTREGAS DE CAFE
A2: PROVEEDOR:
A3: FECHA DE ENTREGA:
B6: SANTANDER | C6: MEXICO | D6: BRASIL | E6: OTRO
A7: MOLIDO
A8: GRANO
A11: PEDIDOS CAFE
A12: PROVEEDOR:
A13: FECHA DE ENTREGA:
B16: SANTANDER | C16: MEXICO | D16: BRASIL | E16: OTRO
A17: MOLIDO
A18: GRANO
A21: PEDIDOS CAFE
A22: PROVEEDOR:
A23: FECHA DE ENTREGA:
B26: SANTANDER | C26: MEXICO | D26: BRASIL | E26: OTRO
A27: MOLIDO
A28: GRANO
A31: PEDIDOS CAFE
A32: PROVEEDOR:
A33: FECHA DE ENTREGA:
B36: SANTANDER | C36: MEXICO | D36: BRASIL | E36: OTRO
A37: MOLIDO
A38: GRANO

Sheet CIERRE 2023
B1: FECHA | C1: VENTA DIARIA | D1: ZETA | E1: CAJA | F1: CAMBIO | G1: TARJETAS | H1: PEDIDOS YA PAGO-ONLINE | I1: CTA CTE | J1: MERCADO | K1: EFECTIVO DEL DIA | L1: CAJA FUERTE | M1: CAJITA
A2: LUNES | B2: 44928 | C2: 263279 | D2: 121170 | E2: =400+1000+100+240+60+1000 -> 2800 | F2: =500 -> 500 | G2: =15470+36820 -> 52290 | H2: 15790 | J2: 54440 | K2: 118169
A3: MARTES | B3: 44564 | C3: 227225 | D3: 144531 | E3: 2000 | F3: 500 | G3: =21030+29060 -> 50090 | H3: 43890 | J3: 31870 | K3: 82594
A4: MIERCOLES | B4: 44565 | C4: =244984-37200 -> 207784 | D4: 178130 | E4: 1300 | F4: 0 | G4: =27630+12950 -> 40580 | H4: 31260 | J4: 56740 | K4: 68445
A5: JUEVES | B5: 44566 | C5: 270227 | D5: 186310 | E5: =800+500+1800+520+10 -> 3630 | G5: =23710+32120 -> 55830 | H5: 54670 | J5: 41070 | K5: 84107
A6: VIERNES | B6: 44567 | C6: 236390 | D6: 155200 | E6: 2000 | F6: 0 | G6: 41020 | H6: 61930 | J6: 52810 | K6: 78150
A7: SABADO | B7: 44568 | C7: 167077 | D7: 107710 | E7: =700+1300+250+420+90 -> 2760 | F7: 2100 | G7: =41080+4400 -> 45480 | H7: 30680 | J7: 25650 | K7: 52837
A8: DOMINGO | B8: 44569
A9: LUNES | B9: 44570 | C9: 214483 | D9: 129670 | E9: =700+2800+50+400+20 -> 3970 | F9: 1300 | G9: 26020 | H9: 33080 | J9: 58660 | K9: 79693
A10: MARTES | B10: 44571 | C10: 219920 | D10: 129390 | E10: 3400 | F10: 700 | G10: 38220 | H10: 31490 | J10: 53830 | K10: 82530
A11: MIERCOLES | B11: 44572 | C11: 261475 | D11: 150760 | E11: 2200 | F11: 800 | G11: =26760+19880 -> 46640 | H11: 58060 | J11: 49770 | K11: 96685
A12: JUEVES | B12: 44573 | C12: 261596 | D12: 165032 | E12: =500+1900+50+700+60 -> 3210 | F12: 3300 | G12: =20910+34710 -> 55620 | H12: 48810 | J12: 57947 | K12: 74994
A13: VIERNES | B13: 44574 | C13: 206419 | D13: 105590 | E13: 3400 | F13: 300 | G13: =27320+2720 -> 30040 | H13: 29660 | J13: 31650 | K13: 98739
A14: SABADO | B14: 44575 | C14: 143786 | D14: 85342 | E14: 2700 | F14: 1700 | G14: =24410+7860 -> 32270 | H14: 23350 | J14: 24780 | K14: 61099
A15: DOMINGO | B15: 44576
A16: LUNES | B16: 44577 | C16: 193994 | D16: 129790 | E16: =230+50+1200+1000+800 -> 3280 | F16: =1700 -> 1700 | G16: =39420+6180 -> 45600 | H16: 39300 | J16: 27290 | K16: 69804
A17: MARTES | B17: 44578 | C17: 222688 | D17: 144939 | E17: 530 | F17: 800 | G17: =35530+5010 -> 40540 | H17: 44200 | J17: =50380+650 -> 51030 | K17: 81049
A18: MIERCOLES | B18: 44579 | C18: 200453 | D18: =116128+2900 -> 119028 | E18: 3000 | F18: 0 | G18: =1450+52010 -> 53460 | H18: 23440 | J18: 34340 | K18: 74975
A19: JUEVES | B19: 44580 | C19: 265491 | D19: 199980 | E19: 2400 | F19: 1000 | G19: 72530 | H19: 68240 | J19: 54090 | K19: 63291
A20: VIERNES | B20: 44581 | C20: 194050 | D20: 114480 | E20: 2400 | F20: 1000 | G20: =34590+5800 -> 40390 | H20: 41390 | J20: 36070 | K20: 69930
A21: SABADO | B21: 44582 | C21: =226474-39600 -> 186874 | D21: 158547 | E21: =1900+1000+250+500+210 -> 3860 | F21: 2100 | G21: =25370+8330 -> 33700 | H21: 24477 | J21: 36590 | K21: 65727
A22: DOMINGO | B22: 44583
A23: LUNES | B23: 44584 | C23: 205787 | D23: 13220 | E23: 2500 | F23: 2100 | G23: =750+7450+28410 -> 36610 | H23: 35050 | J23: 47470 | K23: 71437
A24: MARTES | B24: 44585 | C24: =175685+101448 -> 277133 | D24: 164542 | E24: =400+2100+100+80+50 -> 2730 | F24: =1000+800 -> 1800 | G24: =4400+63590 -> 67990 | H24: 30830 | J24: 56720 | K24: =43450+45018 -> 88468
A25: MIERCOLES | B25: 44586 | C25: 288807 | D25: 219649 | E25: =500+1400+2000+100+320+140 -> 4460 | F25: 200 | G25: =9400+10350+29000+26000 -> 74750 | H25: 41727 | J25: 67950 | K25: 57518
A26: JUEVES | B26: 44587 | C26: 273674 | D26: 185370 | E26: =1100+2400+50+240+120 -> 3910 | F26: 1000 | G26: =32600+9250 -> 41850 | H26: 32550 | J26: 52740 | K26: 84374
A27: VIERNES | B27: 44588 | C27: 296465 | D27: 182327 | E27: =2800+160+170 -> 3130 | F27: 500 | G27: =46970+11230 -> 58200 | H27: 38757 | J27: 45780 | K27: 103358
A28: SABADO | B28: 44589 | C28: 154742 | D28: 105487 | E28: 3600 | F28: 1900 | G28: =34910+3500 -> 38410 | H28: 27607 | J28: 28450 | K28: 46705
A29: DOMINGO | B29: 44590
A30: LUNES | B30: 44591 | C30: 235399 | D30: 152439 | E30: =2000+3300+250+720+110-900 -> 5480 | F30: =1900 -> 1900 | G30: =3100+39880 -> 42980 | H30: 44020 | J30: 61260 | K30: 78580
A31: MARTES | B31: 44592 | C31: 330134 | D31: 243732 | E31: 4100 | F31: 2100 | G31: =54780+10850 -> 65630 | H31: 69910 | J31: 78510 | K31: 83726
A32: TOTAL | B32: ENERO | C32: =SUM(C2:C31) -> 6005352 | D32: =SUM(D2:D31) -> 3792365 | G32: =SUM(G2:G31) -> 1226740 | H32: =SUM(H2:H31) -> 1024168 | J32: =SUM(J2:J31) -> 1217507 | K32: =SUM(K2:K31) -> 2016984
A34: MIERCOLES | B34: 44593 | C34: 335969 | D34: 246292 | E34: 2700 | F34: 1500 | G34: =56820+23100 -> 79920 | H34: 64817 | J34: 89050 | K34: 87609
A35: JUEVES | B35: 44594 | C35: 301366 | D35: 182630 | E35: =1200+2900+250+300+130 -> 4780 | F35: 2000 | G35: =5700+57100 -> 62800 | H35: 49870 | J35: 49760 | K35: 94376
A36: VIERNES | B36: 44595 | C36: 235122 | D36: 157367 | E36: =3500+500+100+200+50 -> 4350 | F36: =700+200+1000 -> 1900 | G36: =42500+20480 -> 62980 | H36: 27237 | J36: 40730 | K36: 75525
A37: SABADO | B37: 44596 | C37: 194718 | D37: 105130 | E37: =4580-1700 -> 2880 | F37: =2200+1000+1000+500 -> 4700 | G37: =30640+8640 -> 39280 | H37: 20780 | J37: 50478 | K37: 84798
A39: LUNES | B39: 44598 | C39: 192636 | D39: 113022 | E39: =1200+1000+800+480+120 -> 3600 | F39: 1800 | G39: =28890+5470 -> 34360 | H39: 11200 | J39: 49270 | K39: 60977
A40: MARTES | B40: 44599 | C40: 260187 | D40: 160600 | E40: 3760 | F40: 1500 | G40: 42120 | H40: 44470 | J40: 49410 | K40: 86318
A41: MIERCOLES | B41: 44600 | C41: 302785 | D41: 210680 | E41: 1350 | F41: 1500 | G41: 51110 | H41: 89527 | J41: 59710 | K41: 69105
A42: JUEVES | B42: 44601 | C42: 296810 | D42: 242895 | E42: 2100 | F42: 900 | G42: 68890 | H42: 65270 | J42: 89430 | K42: 61275
A43: VIERNES | B43: 44602 | C43: 224635 | D43: 258190 | E43: 2020 | F43: 900 | G43: 52190 | H43: 27110 | J43: 57780 | K43: 68965
A44: SABADO | B44: 44603 | C44: 152015 | D44: 95630 | E44: 1000 | F44: 3100 | G44: 30510 | H44: 26330 | J44: 46280 | K44: 46080
A46: LUNES | B46: 43874 | C46: 239929 | D46: 152013 | E46: 800 | F46: 2300 | G46: =50930+12790 -> 63720 | H46: 26798 | J46: 46234 | K46: 73326
A47: MARTES | B47: 43875 | C47: 369456 | D47: 271350 | E47: 3700 | F47: 2100 | G47: 106690 | H47: 35160 | J47: 17600 | K47: 83906
A48: MIERCOLES | B48: 43876 | C48: 247847 | D48: 192635 | E48: 3600 | F48: 1900 | G48: =38680+28600 -> 67280 | H48: 37230 | J48: 59495 | K48: 66852
A49: JUEVES | B49: 43877 | C49: 323230 | D49: 227440 | E49: =500+1600+200+280+50 -> 2630 | F49: =900+600+500+2000 -> 4000 | G49: =47380+23880 -> 71260 | H49: 67300 | J49: 62210 | K49: 99030
A50: VIERNES | B50: 43878 | C50: 242040 | D50: 162880 | E50: 2600 | F50: 2700 | G50: 61480 | H50: 1350 | J50: 59220 | K50: 90290
A51: SABADO | B51: 43879 | C51: 216051 | D51: 136310 | E51: =700+1900 -> 2600 | F51: =2000+2000 -> 4000 | G51: =3700+29260 -> 32960 | H51: 19800 | J51: 78840 | K51: 74301
A53: LUNES | B53: 43881
A54: MARTES | B54: 43882 | C54: 128365 | D54: 95780 | E54: =900+2100+300+420+120 -> 3840 | F54: 2500 | G54: =700+38950 -> 39650 | H54: 21040 | J54: 31840 | K54: 36235
A55: MIERCOLES | B55: 44247 | C55: 229870 | D55: 117760 | E55: 2400 | F55: 1300 | G55: =27510+11840 -> 39350 | H55: 32927 | J55: 39670 | K55: 95160
A56: JUEVES | B56: 43884 | C56: 311345 | D56: 189340 | E56: =1700+2500+50+200+120 -> 4570 | F56: =1100+1000+1000 -> 3100 | G56: =28690+28640 -> 57330 | H56: 35140 | J56: 60460 | K56: 110215
A57: VIERNES | B57: 44249 | C57: 291727 | D57: 173487 | E57: 2210 | F57: 10900 | G57: 49340 | H57: 45037 | J57: 60130 | K57: 120070
A58: SABADO | B58: 44250 | C58: 252553 | D58: 153048 | E58: =2000+600+400+90-500 -> 2590 | F58: =3000+900+500+400+500+400 -> 5700 | G58: =46368+11600 -> 57968 | H58: 37630 | J58: 21570 | K58: 89945
A60: LUNES | B60: 43888 | C60: 267352 | D60: 146317 | E60: 2370 | F60: 5500 | G60: 53580 | H60: 51990 | J60: 37610 | K60: 109615
A61: MARTES | B61: 43889 | C61: 330593 | D61: 214628 | E61: 2600 | F61: 6500 | G61: 77750 | H61: 54685 | J61: 59990 | K61: 94195
A62: TOTAL | B62: FEBRERO | C62: =SUM(C34:C61) -> 5946601 | G62: =SUM(G34:G61) -> 1302518 | J62: =SUM(J34:J61) -> 1216767
A63: MIÉRCOLES | B63: 44256 | C63: 315986 | D63: 241184 | E63: 1200 | F63: 5600 | G63: =51040+25690 -> 76730 | H63: 85131 | J63: 40650 | K63: 64752
A64: JUEVES | B64: 44257 | C64: 353881 | D64: 226320 | E64: 1900 | F64: 4400 | G64: =39650+12980 -> 52630 | H64: 103717 | J64: 62530 | K64: 91601 | N64: =(E64+F64+L64)-M64 -> 6300
A65: VIERNES | B65: 44258 | C65: 389340 | D65: 300350 | E65: 2770 | F65: 5400 | G65: 83140 | H65: 64800 | J65: 60120 | K65: 70280
A66: SÁBADO | B66: 44259 | C66: 248482 | D66: 197215 | E66: =2200+200+300+440+160 -> 3300 | F66: =5000+2400 -> 7400 | G66: =8290+71500 -> 79790 | H66: 22800 | J66: 85760 | K66: 54917
A67: DOMINGO | B67: 44260
A68: LUNES | B68: 44261 | C68: 285945 | D68: 175855 | E68: =2600+100+2600+140 -> 5440 | F68: =5000+400+1600+400 -> 7400 | G68: =5000+67900 -> 72900 | H68: 34255 | J68: 57490 | K68: 98400
A69: MARTES | B69: 44262 | C69: 341464 | D69: 197410 | E69: 1900 | F69: 4600 | G69: =34600+8730 -> 43330 | H69: 63458 | J69: 88190 | K69: 104004
A70: MIÉRCOLES | B70: 44263 | C70: 349456 | D70: 212668 | E70: 4000 | F70: 4600 | G70: =78460+7970 -> 86430 | H70: 78328 | J70: =60010+16970 -> 76980 | K70: 96198
A71: JUEVES | B71: 44264 | C71: 369223 | D71: 219357 | E71: =1400+1800+320+130 -> 3650 | F71: =2400 -> 2400 | G71: =46830+61930 -> 108760 | H71: 66476 | K71: 106736
A72: VIERNES | B72: 44265 | C72: 255457 | D72: 137498 | E72: 2200 | F72: 2900 | G72: 70560 | H72: 58726 | J72: 58280 | K72: 79209
A73: SÁBADO | B73: 44266 | C73: 235350 | D73: 175730 | E73: =200+1900+350+820+130 -> 3400 | F73: =2000+1100 -> 3100 | G73: =2900+81540 -> 84440 | H73: 10530 | K73: 57560
A74: DOMINGO | B74: 44267
A75: LUNES | B75: 44268 | C75: 289283 | D75: 185707 | E75: =400+1700+150+760+110 -> 3120 | F75: =1100+4000+1000 -> 6100 | G75: =25130+57620 -> 82750 | H75: 54587 | K75: 86476
A76: MARTES | B76: 44999 | C76: 309395 | D76: 193254 | E76: 2480 | F76: 3800 | G76: =24100+37270 -> 61370 | H76: 95273 | K76: 58701
A77: MIÉRCOLES | B77: 44270 | C77: 302433 | D77: 190708 | E77: 2380 | F77: 700 | G77: =61480+15530 -> 77010 | H77: 66218 | K77: 94695
A78: JUEVES | B78: 44271 | C78: 352509 | D78: 262433 | E78: =800+2200+360+50 -> 3410 | F78: =3000+600+1000 -> 4600 | G78: =128020+90020 -> 218040 | H78: 71293 | K78: 75036
A79: VIERNES | B79: 44272 | C79: 290086 | D79: 159616 | E79: 1730 | F79: 6200 | G79: 88740 | H79: 33083 | K79: 73240
A80: SÁBADO | B80: 44273 | C80: 197787 | D80: 127087 | E80: 800 | F80: 4200 | G80: =68790+20750 -> 89540 | H80: 18639 | K80: 58010
A81: DOMINGO | B81: 44274
A82: LUNES | B82: 44275 | C82: 318307 | D82: 175569 | E82: =1200+2800+50+260+40 -> 4350 | F82: 4000 | G82: =86510+4510 -> 91020 | H82: 28298 | K82: 141348
A83: MARTES | B83: 44276 | C83: 414354 | D83: 287714 | E83: 1500 | F83: 11000 | G83: 117520 | H83: 73235 | K83: 122240 | L83: RECORD
A84: MIÉRCOLES | B84: 44277 | C84: 386269 | D84: 244349 | E84: 2500 | F84: 300 | G84: =72630+34170 -> 106800 | H84: 84879 | K84: 104050
A85: JUEVES | B85: 44278 | C85: 345200 | D85: 236050 | E85: =400+1700+420 -> 2520 | F85: 3100 | G85: =50670+32000+14610 -> 97280 | H85: 55250 | K85: 109000
A86: VIERNES | B86: 44279 | C86: 182483 | D86: 115360 | E86: 1980 | F86: 1100 | G86: =29090+26810 -> 55900 | H86: 31030 | K86: 73730
A87: SÁBADO | B87: 44280 | C87: 237180 | D87: 159950 | E87: 3000 | F87: 3000 | G87: =78730+28850 -> 107580 | H87: 20050
A88: DOMINGO | B88: 44281
A89: LUNES | B89: 45012 | C89: 338066 | D89: 168370 | E89: =900+1300+200+540+80 -> 3020 | F89: =500 -> 500 | G89: =64270+25150 -> 89420 | H89: 31660 | K89: 111756
A90: MARTES | B90: 44283 | C90: 428687 | D90: 228027 | E90: 3000 | F90: 500 | G90: =57180+55810 -> 112990 | H90: 94707 | K90: 121400
A91: MIÉRCOLES | B91: 44284 | C91: 493770 | D91: 268230 | E91: 1890 | F91: 500 | G91: 154050 | H91: 79190 | K91: 113630
A92: JUEVES | B92: 44285 | C92: 441856 | D92: 241500 | E92: =1700+400+100+100+60 -> 2360 | F92: =1000+3000 -> 4000 | G92: =68690+39040 -> 107730 | H92: 78000 | K92: 122326
A93: VIERNES | B93: 44286 | C93: 382670 | D93: 249670 | E93: 1800 | F93: 8000 | G93: 131710 | H93: 67160 | K93: 96050
A94: SÁBADO | B94: MARZO | C94: =SUM(C63:C93) -> 8854919 | D94: =SUM(D63:D93) -> 5577181 | G94: =SUM(G63:G93) -> 2548160 | K94: =SUM(K63:K93) -> 2385345
A95: SABADO | B95: 44287 | C95: 291506 | D95: 197975 | E95: 1300 | F95: 5300 | G95: =98380+32050 -> 130430 | H95: 50551 | K95: 83131
A96: DOMINGO | B96: 44288
A97: LUNES | B97: 44289 | C97: 478931 | D97: 285476 | E97: =3800+600+400+1900 -> 6700 | F97: =1300+4000 -> 5300 | G97: =77790+67490 -> 145280 | H97: 118835 | K97: 116425
A98: MARTES | B98: 44290 | C98: 414347 | D98: 220312 | E98: 3300 | F98: 5300 | G98: =70390+20760 -> 91150 | H98: 79062 | K98: 114235
A99: MIÉRCOLES | B99: 44291 | C99: 477266 | D99: 301664 | E99: 3000 | F99: 8800 | G99: 157540 | H99: 109245 | K99: 102442
A100: JUEVES | B100: 44292 | C100: 307345 | D100: 205745 | E100: =700+2900+50+300+50 -> 4000 | F100: =600+4000+1000 -> 5600 | G100: =58290+64210 -> 122500 | H100: 40065 | J100: 44470 | K100: 83580
A101: VIERNES | B101: 44293 | C101: 257470 | D101: 175150 | E101: =1000+1900+250+160+100 -> 3410 | F101: =600+5000 -> 5600 | G101: =79380+47400 -> 126780 | H101: 29723 | K101: 80020
A102: SÁBADO | B102: 44294 | C102: 264568 | D102: 136679 | E102: 7000 | F102: 2000 | G102: =66030+12450 -> 78480 | H102: 23617 | K102: 116813
A103: DOMINGO | B103: 44295
A104: LUNES | B104: 44296 | C104: 297144 | D104: 157530 | E104: =2000+600+500+720+160 -> 3980 | F104: =2000+200+5000 -> 7200 | G104: =15250+74710 -> 89960 | H104: 49989 | K104: 77699
A105: MARTES | B105: 44297 | C105: 321850 | D105: 164719 | E105: =1300+3400+400+500 -> 5600 | F105: 7000 | G105: =59630+11390 -> 71020 | H105: 72497 | K105: 120221
...

Sheet ENERO 2023
B1: MP | C1: CHEQUE | D1: TRANSFERENCIA | E1: ADEUDA | F1: GASTOS | H1: RETIROS
B2: 12848.82 | G2: LA SERENISIMA | H2: 102 | I2: CE
A3: LUNES 2 | F3: 1495 | G3: BRIE
F4: 3000 | G4: EVA
F5: 276 | G5: FP
B6: 25500 | G6: POLLO
B7: 10266.47 | G7: MARILU
B8: =3298*3 -> 9894 | G8: pulpa frutilla
F9: 300 | G9: moto florida
F10: 7300 | G10: huevo
F11: 421 | G11: filtro cafe
A15: MARTES 3 | C15: 51121.27 | G15: quintela | H15: 77 | I15: H
B16: 30616.38 | G16: horeca
B17: 22910.3 | G17: criollo
B18: =42480-1800 -> 40680 | G18: edu
D19: 16000 | G19: harina
D20: 8275.19 | G20: valot
F21: 2750 | G21: cucharas
D22: 19200 | G22: wraps
A28: MIERCOLES 4 | B28: 5590 | G28: tenedores | H28: 67.5 | I28: H
B29: 6545.77 | G29: la serenisima
F30: 740 | G30: folex
C31: 44931.91 | G31: ormazabal
F32: 1000 | G32: hielo
B33: 4080 | G33: choco alpino pins
B42: 25500 | G42: pollo | I42: deposite a bbva 202k y me los transferi a mi mp
C43: 25550.52 | G43: matiz | H43: 81 | I43: CE
A44: JUEVES 5 | B44: 10896.05 | G44: cuyaires
D45: 40232.5 | G45: motobaires
F46: 8000 | G46: remis marcelo
F47: 686 | G47: ferreteria
F48: 10000 | G48: Marcelo
A54: VIERNES 6 | F54: =489+239 -> 728 | G54: fp | H54: 60 | I54: H
B55: 38990 | G55: edu | H55: 5000 | I55: Retiro C
B56: 6545.77 | G56: la serenisima
B57: 12684 | G57: limpieza
B58: 64832.77 | G58: gonzanio
F59: 3000 | G59: eva
F60: 1300 | G60: moto contadora
B61: 43689.1 | G61: coca
F62: 10000 | G62: Marce
F63: =1375+1930 -> 3305 | G63: Ferreteria
A68: SABADO 7 | B68: 25500 | G68: pollo | H68: 38 | I68: C
F69: 250 | G69: film | I69: 8 ADELANTO CE
F70: 9600 | G70: cele
F71: 600 | G71: hs extra kiara
F72: 600 | G72: hs extra leonel
A80: LUNES 9 | B80: =18543.25+23313.68 -> 41856.93 | G80: quintela | H80: 72 | I80: CE
B81: 16382.4 | G81: marilu | I81: deposite 47k en bbva y me transferi a mp
B82: 9818.64 | G82: la serenisima
B83: 15350 | G83: edu
F84: 1000 | G84: hielo
F85: 240 | G85: fp
F86: 500 | G86: leche alm
B87: 4954 | G87: harina alm
B88: 9300 | G88: choco alpino
A96: MARTES 10 | F96: 7300 | G96: HUEVO | H96: 70 | I96: H
B97: 20928.83 | G97: criollo
B98: 7278.56 | G98: horeca
B99: 15000 | G99: harina
B100: 6007.65 | G100: cuyaires
F101: 800 | G101: vegetalina *500gr
F102: 900 | G102: manteca
B103: 19200 | G103: wraps
B104: 20100 | G104: manteca
A110: MIERCOLES 11 | F110: 3000 | G110: EVA | H110: 90 | I110: H
B111: 25500 | G111: POLLO | H111: 12000 | I111: Cobo pago H
B112: 25632.24 | G112: MILKAUT
C113: 107749.67 | G113: ormazabal
C114: 22331.81 | G114: matiz
B115: 6545.77 | G115: la serenisima
A128: JUEVES 12 | F128: =1700+808+1426 -> 3934 | G128: FP | H128: 58 | I128: C
F129: 1800 | G129: Ensaladera
F130: 1000 | G130: hielo
F131: 11800 | G131: aceite freidora
A143: VIERNES 13 | B143: 38400 | G143: edu | H143: 85 | I143: H
F144: 511 | G144: fp
F145: 1000 | G145: hielo | I145: 413
B146: 13075.81 | G146: la serenisima
F147: 4500 | G147: EVA
F148: 9000 | G148: JAVIER
C149: 78650 | G149: PENGUIN
A158: SABADO 14 | C158: 45747.2 | G158: quintela | H158: 44 | I158: H
B159: 25500 | G159: pollo
F160: 12800 | G160: cele
F161: 3000 | G161: tanen
A168: LUNES 16 | F168: 210 | G168: des piso | I168: deposite 35k y me lo transferi a mp
F169: 210 | G169: rucula | H169: 48 | I169: C
D170: 35100 | G170: edu
F171: 4500 | G171: eva
B172: 10211.36 | G172: la serenisima
F173: 5200 | G173: fumigator
F174: 7400 | G174: huevos
A183: MARTES 17 | B183: 11174.77 | G183: marilu | H183: 80
B184: 4506.26 | G184: criollo
B185: 10532.23 | G185: horeca
B186: 12800 | G186: harina
B187: 6596 | G187: pulpa frutilla
B188: 9600 | G188: wraps
A199: MIERCOLES 18 | B199: 25500 | G199: pollo | H199: 70 | I199: H
...

Sheet FEBRERO 2023
A1: z | B1: MP | C1: CHEQUE | D1: TRANSFERENCIA | E1: ADEUDA | F1: GASTOS | H1: RETIROS
B2: 10560 | G2: wraps | H2: 77 | I2: H
A3: MIERCOLES 1 | F3: 765 | G3: fp | I3: 7606 use de mp
B4: 25500 | G4: pollo
B5: 6807.58 | G5: la serenisima
C6: 31938.65 | G6: ormazabal
C7: 36514 | G7: matiz
F8: 3715 | G8: fp
B9: 6000 | G9: frutos rojos congelados
F10: 4000 | G10: paltas
A15: JUEVES 2 | B15: 34825.75 | G15: milkaut | H15: 87 | I15: C
B16: 12060.17 | G16: marilu | I16: 21918,46 use de bbva
F17: 500 | G17: ledevit
F18: 421 | G18: filtros cafe
D19: 15673.09 | G19: colucci procesadora
F20: 2000 | G20: guantes nitrilo costa
A28: VIERNES 3 | F28: 225 | G28: rucula | H28: 42 | I28: C
F29: 430 | G29: limpieza
G30: eva
F31: 206 | G31: fp
B32: 37900 | G32: edu
C33: 38563.52 | G33: matiz
D34: 58443 | G34: motobaires
F42: 600 | G42: hielo | H42: 71 | I42: C
B43: 25500 | G43: pollo
A44: SABADO 4 | F44: 8200 | G44: huevo
A54: LUNES 6 | F54: 3800 | G54: eva | I54: C deposite 105000+19000+55500 en bbva y transf 140 a nora y 39500 a mi mp
B55: 6706.69 | G55: serenisima del viernes | H55: 55 | I55: C
F56: 902 | G56: carrefour
F57: 480 | G57: chino
F58: 314 | G58: rucula
B59: 11300 | G59: edu
C60: =25632.16+22702.02 -> 48334.18 | G60: quintela
F61: 1000 | G61: moto contadora
G62: hilo encerado
A68: MARTES 7 | B68: 3523.98 | G68: horeca | H68: 30 | I68: C
B69: 25614.21 | G69: criollo | H69: 20 | I69: retiro H :))
B70: 13878.36 | G70: marilu | H70: 32.5 | I70: Caja Roja
D71: 21742 | G71: limpieza
B72: 8263 | G72: ventilador
F73: 824 | G73: carrefour
D74: 46827 | G74: Penguin | I74: se pagó el dia 13/2
A80: MIERCOLES 8 | B80: 34306.03 | G80: coca | H80: 50 | I80: C
B81: 6807.58 | G81: la serenisima | H81: 45063 | I81: caja roja
B82: 10129.01 | G82: la serenisima boleta dia 6/2
B83: 27597.1 | G83: milkaut
C84: 15469.69 | G84: ormazabal
B85: 28000 | G85: edu
F86: 1700 | G86: cele
B87: 10560 | G87: wraps
A96: JUEVES 9 | F96: 640 | G96: fp | H96: 20 | I96: transferi a cecimp
F97: 600 | G97: hielo | H97: 37 | I97: C
B98: 5600 | G98: harina
B99: 25500 | G99: pollo
B100: 22500 | G100: manteca fac 3/2
F101: 12800 | G101: aceite freidora
F102: 1000 | G102: hielo
B103: 9100 | G103: choco alpino
F104: 500 | G104: tinta sello
A110: VIERNES 10 | F110: =330+252 -> 582 | G110: fp | H110: 30 | I110: caja roja
F111: 661 | G111: carrefour limpieza
B112: 9284.75 | G112: la serenisima
F113: 4000 | G113: eva
A128: SABADO 11 | H128: 20 | I128: H
H129: 19 | I129: p
A143: LUNES 13 | F143: 550 | G143: fp | H143: 60 | I143: H
B144: 43300 | G144: edu se pago el 14/2
C145: =32508.13+21189.28 -> 53697.41 | G145: quintela
B146: 6807.58 | G146: la serenisima
B147: 11600 | G147: harina
B148: 13375.35 | G148: marilu
F149: 4000 | G149: eva
B150: 6000 | G150: adelanto eva
F151: 1000 | G151: hielo
F152: 9300 | G152: huevo
A158: MARTES 14 | B158: 23400 | G158: manteca | H158: 63 | I158: H
F159: 4700 | G159: lu y ma Sol
B160: 6076 | G160: chocobco alpino
D161: 7444 | G161: pulpa frutilla
G162: fp naranja
F163: 2118 | G163: naranja
A168: MIERCOLES 15 | B168: 7420.16 | G168: la serenisima | H168: 3000 | I168: uso C de mp
C169: 33010.76 | G169: ormazabal | H169: 65 | I169: H
B170: 25500 | G170: pollo | H170: 15259 | I170: Fbtl /MP
D171: 14000 | G171: edu
B172: 8100 | G172: feras frutos rojos
F173: 2980 | G173: libreria
F174: 787.37 | G174: fp
A183: JUEVES 16 | F183: 8000 | G183: amasadora | H183: 79 | I183: C
F184: 1400 | G184: trapos franja francesa
F185: 1600 | G185: hilo encerado
F186: 1000 | G186: hielo
B187: 21120 | G187: wraps
B188: 22405.74 | G188: cuyaires
A199: VIENRES 17 | B199: 42788.62 | G199: baires moto | I199: 15 transf H de mp
B200: 11040 | G200: la serenisima | H200: 30 | I200: H
F201: 440 | G201: rucula
B202: 17000 | G202: edu
B203: 6500 | G203: sorbetes
F204: 37500 | G204: M
...

Sheet MARZO 2023
A1: z | B1: MP | C1: CHEQUE | D1: TRANSFERENCIA | E1: ADEUDA | F1: GASTOS | H1: RETIROS
C2: 39246.29 | G2: ormazabal | H2: 52.5 | I2: H
A3: MIERCOLES 1 | B3: 10396.64 | G3: la serenisima | I3: 50 transf H BBV | J3: cancelado
B4: 30000 | G4: pollo
B5: 18340 | G5: edu
B6: 28217.49 | G6: coca
A15: JUEVES 2 | B15: 56121.4 | G15: gonzanio | H15: 90 | I15: 90 H
F16: 770 | G16: etiquetas | I16: 50 Lleve
F17: 1000 | G17: hielo
B18: 8400 | G18: harina
A28: VIERNES 3 | B28: =18440-500 -> 17940 | G28: edu | H28: 31 | I28: H
B29: 11467.04 | G29: la serenisima
F30: 2000 | G30: eva
F31: 13200 | G31: aceite freidora
F32: 76 | G32: fp
F33: 606 | G33: carrefour
B34: 4538 | G34: pulpa frutilla
F35: 800 | G35: muzza
F36: 1422 | G36: limon
F42: 604 | G42: carrefour | H42: 53 | I42: C
B43: 30000 | G43: pollo
A44: SABADO 4 | C44: 14580 | G44: matiz
B45: 17457.4 | G45: milkaut
F46: 1300 | G46: BRIE
F47: 650 | G47: FRUTAS PREMIUM
A54: LUNES 6 | B54: 7779.2 | G54: la serenisima
B55: 41300 | G55: edu | H55: 73 | I55: C
C56: =42560.9+48152.74-2395.8 -> 88317.84 | G56: quintela
B57: 26695.18 | G57: marilu
F58: 648 | G58: rucula
B59: 9740.3 | G59: horeca
B60: 29620.4 | G60: criollo
B61: 36874.75 | G61: motobaires
F62: 11800 | G62: huevo
F63: 1200 | G63: brie
F64: 2000 | G64: hielo
A68: MARTES 7 | B68: 42240 | E68: pagada | G68: wraps 2 cajas | H68: 97 | I68: H
D69: 69696 | E69: pagada | G69: penguin cafe | I69: deposite 120 a bbva y me o transferi a mp
D70: 24684 | E70: pagada | G70: penguin syrup
A80: MIERCOLES 8 | B80: 30000 | G80: pollo | H80: 84 | I80: H
B81: 39600 | G81: edu | H81: 34 | I81: Saque 50
C82: 60331.42 | G82: ormazabal
F83: 474 | G83: fp
B84: 24100 | G84: manteca
B85: 8284.85 | G85: la serenisima
B86: 26224.71 | G86: milkaut
B87: 39158.46 | G87: coca
F88: 2000 | G88: trapos franja francesa
A96: JUEVES 9 | C96: 39943.36 | G96: matiz | H96: 90 | I96: C
F97: 957 | G97: fp | H97: 30
B98: 23713.74 | G98: cuyaires
B99: 18800 | G99: harinas del rosario
B100: 9953 | G100: della taza limp grupo
A110: VIERNES 10 | F110: 2000 | G110: hielo | H110: 40
B111: 16400 | G111: edu
B112: 31500 | G112: pollo
B113: 12866 | G113: marilu
F114: 4000 | G114: eva
F115: 1200 | G115: moto contadora
A128: SABADO 11 | F128: 12700 | G128: huevo | I128: 11 uso C de MP
H129: 46 | I129: C
A143: LUNES 13 | F143: 1828 | G143: queso brie | H143: 70 | I143: C
C144: =33371.9+25989.36 -> 59361.26 | G144: quintela
F145: 664 | G145: mayonesa
F146: 601 | G146: fp
B147: 42000 | G147: edu
B148: 9206.8 | G148: la serenisima
B149: 21184 | G149: marilu
F150: 2600 | G150: hs extra rodri
F151: 4000 | G151: eva
F152: 1236 | G152: yogur
F153: 10000 | G153: mica
A158: MARTES 14 | C158: 3657 | G158: cabify agus
B159: 31680 | E159: pagado | G159: wraps | H159: 60 | I159: H
F160: 3606 | G160: leche
B161: 20250 | G161: pollo en mercou
B162: =21861.31 -> 21861.31 | G162: criollo
B163: =4023.41+2126.84 -> 6150.25 | G163: horeca
F164: 622 | G164: yogur
B165: 11649 | G165: feras frutos cong
A168: MIERCOLES 15 | C168: 34857.06 | G168: ormazabal
B169: 57527.88 | G169: coca | H169: 86 | I169: H
B170: 16019.051 | G170: la serenisima
B171: 19100 | G171: edu
B172: 31712.51 | G172: milkaut
D173: 100000 | G173: laurimar
F174: 13200 | G174: aceite freidora
A183: JUEVES 16 | C183: 36743.25 | G183: matiz
B184: 17700 | G184: limpiez | I184: 51 deposite mio en bbva y me tramsferi a ceecimp
B185: 63979.47 | G185: marilu | H185: 61 | I185: C
F186: 1000 | G186: hielo
B187: 15080 | G187: harina
F188: 1000 | G188: tuto farra
A199: VIENRES 17 | H199: 70? | I199: No lo anote liquide sueldos
B200: 8284.85 | G200: la serenisima
B201: 34800 | G201: edu
A214: SABADO 18
F215: 14200 | G215: huevo | H215: 56
A226: LUNES 20 | F226: 1850 | G226: brie | H226: 116 | I226: c
B227: 26100 | E227: si | G227: edu
...

Sheet ABRIL 2023
A1: z | B1: MP | C1: CHEQUE | D1: TRANSFERENCIA | E1: ADEUDA | F1: GASTOS | H1: RETIROS
F2: =1450+1450 -> 2900 | G2: MAPLE DE HUEVO | H2: 68 | I2: C
A3: SABADO 1 | F3: 15000 | G3: HUEVO
A15: LUNES 3 | F15: 1697 | G15: brie | H15: 102 | I15: C
B16: 18002.35 | G16: la serenisima
B17: 26800 | G17: edu
B18: 27214.77 | G18: criollo
B19: 7971.11 | G19: horeca
C20: 58467.5 | G20: quintela
B21: 6174.79 | G21: tenedores
A28: MARTES 4 | F28: 300 | G28: curitas | H28: 80 | I28: H
F29: 2156 | G29: panceta | I29: transferi de Bbva a cecimp 70k
F30: 6020 | G30: pollo
F31: 45 | G31: verdeo
E32: 2798.13 | G32: quintela panceta
F33: 1200 | G33: moto
D34: 60592.32 | G34: marilu
F35: 5000 | G35: eva
B36: 2120 | G36: wraps
B37: 4552 | G37: leche carrefour
F38: 15000 | G38: huevo
B39: =1875+1917 -> 3792 | G39: crema
B40: 3977 | G40: cajas breik
B42: 51350 | G42: edu | H42: 97 | I42: H
B43: 15414.46 | G43: la serenisima
A44: MIERCOLES 5 | B44: 10880 | G44: valot
B45: 36487.8 | G45: marilu
D46: 52450 | G46: laurimar
D47: 65340 | E47: pagado | G47: penguin
D48: 53920.63 | G48: motobaires
B49: 25677 | G49: milkaut
B50: 9600 | G50: feras
C51: 50736.43 | G51: ormazabal
F52: 2300 | G52: ormazabal
A54: JUEVES 6 | B54: 20520.92 | G54: la serenisima | H54: 90 | I54: C
B55: 15960 | G55: harina
C56: 64051 | G56: matiz
D57: 52282.26 | G57: coca_Femsa
B58: 31000 | G58: manteca
A68: VIERNES 7 | H68: 74 | I68: C
A80: SABADO 8 | F80: 15000 | G80: huevo | H80: 90 | I80: C
A96: LUNES 10 | F96: 921 | G96: fp | H96: 15 | I96: C
C97: =36325.48+33186.67 -> 69512.15 | G97: quintela | I97: 207000 tranferi MIO de bbva a cecimp
F98: 1920 | G98: brie
B99: =47550-450 -> 47100 | G99: edu
B100: 13545.75 | G100: la serenisima
B101: 121869.19 | G101: marilu
B102: 11064 | G102: choco alpino bco y negro
F103: 5500 | G103: eva
F104: 183 | G104: levadura
F105: 473 | G105: film
A110: MARTES 11 | F110: 2000 | G110: hielo | H110: 105 | I110: H
B111: 8450 | G111: horeca
B112: 39077.24 | G112: criollo
F113: 37500 | G113: miguel individuales
F114: 2400 | G114: dunia pol
B115: 12378 | G115: tati
A128: MIERCOLES 12 | B128: 20600 | G128: edu | H128: 110 | I128: H
B129: 37437.44 | G129: milkaut
C130: 44598.59 | G130: ormazabal
F131: 514 | G131: semolin
B132: 6876 | G132: nuevo emporio
F133: 4000 | G133: nahuel
B134: 2120 | G134: WRAPS
D135: 44044 | E135: pagada | G135: Penguin
A143: JUEVES 13 | F143: 723 | G143: naranja | H143: 28.5 | I143: C
B144: 17528.67 | G144: la serenisima
B145: 8942.27 | G145: criollo
B146: 24224.24 | G146: cuyaires
F147: 13200 | G147: aceite
B148: 25000 | G148: harina
F149: 3500 | G149: Andres dia de prueba
A158: VIERNES 14 | B158: 34900 | G158: edu | H158: 83 | I158: H
B159: 18061 | G159: la serenisima
B160: =23280+3540 -> 26820 | G160: art limpieza
C162: 43662.89 | G162: matiz
F163: 6000 | G163: eva
A168: SABADO 15 | F168: 52500 | G168: pollo | H168: 37 | I168: C
F169: 15000 | G169: huevo
A183: LUNES 17 | F183: 5500 | G183: Eva | H183: 93 | I183: C
F184: 1500 | G184: nafta | I184: 15K transferi de r2 mp a ceci mp
C185: =31880.96+24244.77 -> 56125.73 | G185: quintela | I185: (eran 20 y devolvi 5 en ef)
B186: 10680.23 | G186: horeca
B187: =1483+23011.69 -> 24494.69 | G187: el criollo
B188: 13014.77 | G188: la serenisima
F189: 712 | G189: brie
F190: 1290 | G190: azucar
B191: 37700 | G191: edu
D192: 31000 | G192: manteca
D193: 41127.97 | G193: marilu
D194: 57874.92 | G194: coca Femsa
A199: MARTES 18 | G199: marcelo de la torre | H199: 100 | I199: H | J199: se gasto en pollo de Martes y viernes
B200: 11460 | G200: frutos Rojos
D201: 100000 | G201: laurimar
D202: 65700 | G202: uniformes
D203: 34860 | E203: si | G203: wraps
F204: 290 | G204: libreria
A214: MIERCOLES 19 | F214: 52500 | G214: pollo | H214: 110 | I214: Pollo Se saco de la recaudacion 18/4
B215: 13545.75 | G215: la serenisima
B216: 39204 | E216: pagada | G216: penguin
...

Sheet MAYO 2023
A1: z | B1: MP | C1: CHEQUE | D1: TRANSFERENCIA | E1: ADEUDA | F1: GASTOS | H1: RETIROS
F2: 1219 | G2: LIMPIEZA CARREFOUR | I2: repuse 94000 en ef porque use de bbva
A3: MARTES 2 | F3: 1792 | G3: FP | H3: 80 | I3: H
B4: 31000 | G4: MANTECA
B5: 32805.2 | G5: MARILU
F6: 5200 | G6: eva
F7: 10000 | G7: marcelo
F8: =2400+2730 -> 5130 | G8: repuestos marcelo
C9: =43784.52 -> 43784.52 | G9: quintela
A15: MIERCOLES 3 | B15: 9933.5 | G15: la serenisima | I15: 50k transferi de bbva a cecimp
B16: 40550 | G16: edu | H16: 100 | I16: H
B17: 26759.58 | G17: criollo
B18: 2812.95 | G18: horeca
C19: 13105.92 | G19: ormazabal
D20: 56510 | G20: motobaires
F21: 52500 | G21: mercou
B22: 1633 | G22: uber contadora
B23: 1118 | G23: arroz
A28: JUEVES 4 | D28: 49549.5 | E28: pagada | G28: penguin | H28: 108 | I28: C
C29: 10329.08 | G29: criollo
C30: 15389.06 | G30: horeca
B42: 32050 | G42: edu | H42: 75.5 | I42: H
B43: 4966.75 | G43: la serenisima
A44: VIERNES 5 | F44: 5800 | G44: EVA
F45: 3600 | G45: Chino
A54: SABADO 6 | F54: 6500 | G54: 2 dias prueba jm | H54: 80 | I54: H
B55: 4231.5 | G55: brie
A68: LUNES 8 | C68: =69472.22 -> 69472.22 | G68: quintela | H68: 70 | I68: H
B69: 9933.5 | G69: la serenisima
B70: 23550 | G70: edu
B71: 54000 | G71: pollo
B72: 36108.72 | G72: marilu
C73: 47206.7 | G73: matiz
F74: 1000 | G74: hielo
A80: MARTES 9 | F80: 5200 | G80: eva | I80: deposite en bbva 220 y me lo transferi a cecimp
B81: 31000 | G81: manteca | H81: 100 | I81: H
B82: 6871.36 | G82: horeca
B83: 24517.17 | G83: criollo
B84: 12888 | G84: pulpa frutilla
B85: 2348 | G85: sorbetes compostables
F86: 15000 | G86: huevo
B87: 3458 | G87: revolvedores
B88: 28800 | E88: si | G88: wraps
A96: MIERCOLES 10 | B96: =43000-600 -> 42400 | G96: edu
B97: 14900.26 | G97: la serenisima | I97: 6k transferi de mp a cecimp
C98: 59978.49 | G98: ormazabal
B99: 44065.19 | G99: milkaut
F100: =1250+476+481 -> 2207 | G100: art limpi
F101: 2000 | G101: eva
F102: 1360 | G102: arroz
A110: jueves 11 | B110: 54000 | G110: mercou | H110: 70 | I110: H
D111: 82764 | E111: pagada | G111: penguin
B112: 17600 | G112: harina
B113: 10707.71 | G113: geobazar
B114: 14573 | G114: jujuy
D115: 19000 | G115: tachos
B116: 13680.26 | G116: nuevo emporio
B117: 3755 | G117: silpack macarons
D118: 59360.84 | G118: coca
F119: 2000 | G119: eva
F120: 14000 | G120: aceite freidora
A128: VIERNES12 | B128: 15200 | G128: tutto farra choco alpino
D129: 2280 | G129: tutto farra choco alpino
D130: =39050-400 -> 38650 | G130: edu
B131: 21584.83 | G131: la serenisima
D132: 39020 | G132: prod limpieza
F133: 6300 | G133: eva
F134: 46 | G134: alqui salio de caja
B135: 9600 | G135: feras frutos rojos cong
B136: 1350 | G136: hilo encerado
A143: SABADO 13 | F143: 15000 | G143: huevo | H143: 100
F144: 7900 | G144: sueldo Karen
A158: LUNES 15 | B158: 19752.4 | G158: la serenisima | H158: 80 | I158: H
B159: 54000 | G159: pollo
B160: 21350 | G160: edu
D161: 34326.84 | G161: marilu
F162: 1750 | G162: hilleret
F163: 820 | G163: mermelada arandano
A168: MARTES 16 | C168: 62470.95 | G168: matiz | H168: 70
B169: 38758.58 | E169: si | G169: criollo
B170: 21253.86 | E170: si | G170: horeca
B172: 9765 | G172: choco alpino bco granel
B173: 9600 | G173: Frutos Rojos
A183: MIERCOLES17 | B183: 29400 | G183: edu | H183: 62
B184: 9933.5 | G184: la serenisima
D185: 35500 | G185: manteca
C186: 44679.99 | G186: ormazabal
B187: 41681.89 | G187: milkaut
A199: JUEVES 18 | D199: 74834.87 | G199: gonzanio | H199: 60
B200: 54000 | G200: pollo | I200: deposite en BBVA 52 mio y me lo transferi a cecimp
D201: 73825.02 | G201: cuyaires
D202: 53032.48 | G202: motobaires
F203: 7850 | G203: eva
F204: 1300 | G204: palta
B205: 17600 | G205: harina
A214: VIERNES 19 | B214: 14900 | G214: la serenisima | H214: 11.2
D215: 15150 | G215: edu
D216: 49549.5 | E216: pagada | G216: penguin
B217: 1700 | G217: eva
B218: 37291.42 | G218: coca
...

Sheet JUNIO 2023
A1: z | B1: MP | C1: CHEQUE | D1: TRANSFERENCIA | E1: ADEUDA | F1: GASTOS EN EFT | H1: RETIROS
F2: 567 | G2: albahaca | H2: 120 | I2: H
B3: 30580 | G3: harina
A4: JUE 1 | D4: 56567,5 | E4: pagada | G4: penguin
C5: 56017,55 | G5: matiz
A15: VIERNES 2 | B15: 18674,44 | G15: la serenisima
B16: 30400 | G16: edu
D17: 12523,72 | G17: marilu
B18: 52332,42 | G18: coca
F19: 7000 | G19: eva
B20: 7720 | G20: eva
A28: SABADO 3 | B28: 48000 | G28: pollo | H28: 66 | I28: C | J28: Que paso aca?
B29: 44683.02 | G29: milkaut
F30: 2400 | G30: horas extra carla
F31: 15000 | G31: huevo
B42: 37000 | G42: manteca | H42: 98 | I42: H
B43: 22950 | G43: edu
A44: LUNES 5 | B44: 10926.68 | G44: la serenisima
D45: 100000 | G45: Laurimar
F46: 2200 | G46: azucar
C47: =63761.74+23173.92-6352.5 -> 80583.16 | G47: quintela
F48: 1200 | G48: durazno
A54: MARTES 6 | D54: 50173.35 | G54: criollo | H54: 100 | I54: H
D55: 8264.99 | G55: horeca | I55: c uso del bbva (84037,22+9800) se repone depositamdo el ef en la cuenta, mañana miercoles
B56: 36917.23 | G56: marilu | I56: deposite 310000 y me transferi 216162,78, quedo todo cancelado en 0
B57: 18411.86 | G57: cuyaires
B58: 29750.06 | G58: harina
F59: 1200 | G59: farmacia
D60: 57814.1 | E60: si | G60: baires moto
F61: 645 | G61: limpieza
B62: 8828.8 | G62: colorantes
B63: 8735 | G63: breik
B64: 12800 | G64: frutos rojos
F65: 1332 | G65: leche
A68: MIERCOLES 7 | C68: 42237.7 | G68: ormazabal | H68: 90 | I68: H
B69: 5463.34 | G69: la serenisima
B70: 12600 | G70: edu
F71: 2785 | G71: leche
A80: JUEVES 8 | B80: 48000 | G80: pollo | H80: 100 | I80: H
D81: 86636 | E81: pagado | G81: penguin
F82: 200 | G82: costa
F83: 2000 | G83: moto contadora
A96: VIERNES 9 | F96: 330 | G96: curitas | H96: 60 | I96: H transfirio 40k a su mp
D97: 52265.50 | G97: abogada vero lanosky
F98: 590 | G98: gomitas
B99: 18700 | G99: edu
B100: 32822.08 | G100: la serenisima
B101: 23740 | G101: articulos limpieza
A110: SABADO 10 | B110: 23918 | G110: milkaut | H110: 70 | I110: H
C111: 54911 | G111: matiz
B112: 12091.4 | G112: brie
B113: 12100 | G113: eva
F114: 15000 | G114: huevo
A128: LUNES12 | D128: 40700 | G128: manteca | H128: 100 | I128: H
B129: 23616.93 | G129: la serenisima
F130: 1303 | G130: fp | I130: deposite en bbva 111000 y me transferi a cecimp, cancelado
D131: 43755.78 | G131: marilu
B132: =33600-15500 -> 18100 | G132: edu
C133: =24617.45+50587.26 -> 75204.71 | G133: quintela
D134: 100000 | G134: laurimar
F135: 2200 | G135: telegrama
A143: MARTES 13 | B143: 48000 | G143: pollo | H143: 90 | I143: H
F144: 2785 | G144: leche
D145: 31293.5 | G145: criollo
D146: 7383.59 | G146: horeca
B147: 26840 | E147: pagada | G147: wraps
D148: 67672.2 | G148: coca
F149: 2200 | G149: caja edulcorante
F150: 398 | G150: rucula
B151: 78045 | E151: pagada | G151: penguin
A158: MIERC 14 | C158: 60527.47 | G158: ormazabal | H158: 100 | I158: H
G159: milkaut
B160: 13337 | G160: la serenisima
D161: 34450 | G161: edu
F162: 2872 | G162: fp paltas
D163: 5140 | G163: soros
B164: 7610 | G164: soros
A168: JUE 15 | F168: 2513 | G168: leche | H168: 72 | I168: C
D169: 72116 | E169: pagada | G169: penguin | I169: 8 transfirio h a su mp? cancelado con 7 que use de bbva
B170: 20440 | G170: harina
B171: 37792.83 | G171: milkaut
F172: 2300 | G172: telegrama
F173: 15000 | G173: gonzalo liquidacion
A183: VIE 16 | D183: 66073.26 | G183: motobaires | H183: 50 | I183: H
B184: 57000 | G184: cinta scotch
B185: 22300 | G185: edu
B186: 24914.6 | G186: tati
F187: 22400 | G187: rodri
F188: 15200 | G188: aceite
B189: 38243.39 | G189: la serenisima
A199: SAB 17 | F199: 1400 | G199: huevo | H199: 99 | I199: C
B200: 48000 | G200: pollo
B201: 4742.4 | G201: brie
C202: 36688.69 | G202: matiz
F203: 15000 | G203: huevo
B204: 12625 | G204: eva
A214: LU 19 | C214: 63944.39 | G214: quintela | H214: 80 | I214: H
A226: MA 20 | D226: 40700 | E226: pagada | G226: manteca | H226: 121500 | I226: H | J226: 111500
D227: 38409.45 | G227: criollo
D228: 13131.2 | G228: horeca
...

Sheet JULIO 2023
A1: z | B1: MP | C1: CHEQUE | D1: TRANSFERENCIA | E1: ADEUDA | F1: GASTOS EN EFT | H1: RETIROS
F2: 15000 | G2: ag leo | H2: 94 | I2: C
A3: SABADO 1
A15: LUNES 3 | I15: deposite en Bbva 201 mio y lo tr a cecimp
F16: 4950 | G16: dai limpieza | H16: 84 | I16: C
B17: 14053.3 | G17: la serenisima
B18: 39500 | G18: edu
C19: 61196.96 | G19: quintela
F20: 15000 | G20: huevo
B21: 8162.4 | G21: pulpa frutilla
B22: 7242 | G22: tenedor descartable
A28: MARTES 4 | B28: 26840 | G28: wraps | H28: 83 | I28: C
B29: 40700 | G29: manteca
C30: 51340.29 | G30: matiz
D31: 26130.97 | G31: criollo
D32: 15825.99 | G32: horeca
B33: 1436.5 | G33: restante feras
D34: 53043.07 | G34: motobaires
D35: 22680 | E35: pagado | G35: Penguin
B42: 11664.79 | G42: la serenisima | H42: 105 | I42: C
B43: 13550 | G43: edu
A44: MIERCOLES 5 | D44: 48000 | G44: pollo
C45: 63044.63 | G45: ormazabal
B46: 20816.23 | G46: milkaut
F47: 4400 | G47: sole limpieza
F48: 15800 | G48: ACEITE freidora
F49: 18000 | G49: conducto fabricio
F50: 10000 | G50: puso H conducto fabricio, compensado
A54: JUEVES 6 | B54: 21000 | G54: HARINA | H54: 90 | I54: H
D55: 30800 | G55: DISTRI LIMPIEZA
D56: 26559.84 | G56: CUYAIRES
D57: 37966.78 | G57: MARILU
F58: 16300 | G58: ACEITE OLIVA PANES
F59: 2767 | G59: nuevo emporio
F60: 3000 | G60: electricidasd
A68: VIERNES 7 | B68: 16108.31 | G68: la serenisima | H68: 90 | I68: H
B69: 20750 | G69: edu
B70: 46135.77 | G70: coca
A80: SABADO 8 | B80: 12925.4 | G80: queso brie y crudo | H80: 120 | I80: H
C81: =49543.45+52593.8 -> 102137.25 | G81: quintela
F82: 15500 | G82: huevo
F83: 1660 | G83: yogur
A96: LUNES 10 | B96: 21872.63 | G96: la serenisima | H96: 120 | I96: H
F97: 507 | G97: ricota | I97: transferi de bbva a cecimp 150k y ya esta compensado en ef
D98: 51000 | G98: mercou
B99: 41850 | G99: edu | I99: hernan pagó | J99: 502447 | K99: batidora | L99: 1000 U$S
F100: 2000 | G100: hielo | J100: 115120 | K100: mixer
F101: 2000 | G101: mermelada | I101: uso de mp 21/7 | J101: 30000
B102: 13590 | G102: breik | I102: total adeudado | J102: =SUM(J99:J100)-J101 -> 587567
A110: MARTES 11 | D110: 129149.99 | E110: Pagado | G110: jhon and joe | H110: 130 | I110: H | J110: bien
B111: 40700 | G111: manteca
D112: 3241.14 | G112: horeca
D113: 31125.53 | G113: criollo
D114: 15300 | G114: harina
C115: 65034.73 | G115: matiz
B116: 13420 | G116: wraps
A128: MIERCOLES 12 | C128: 73516 | G128: ormzabal | H128: 90 | I128: H
B129: 16108.31 | G129: la serenisima
B130: 38197.91 | G130: milkaut
B131: 14500 | G131: edu
F132: 2750 | G132: dai limpieza
A143: JUEVES 13 | D143: 51000 | G143: mercou | H143: 103 | I143: C
D144: 47951.77
F145: 31000 | G145: MARCELO ALQ
F146: 2400 | G146: MOTO CONTADORA
B147: 13998 | G147: 2k harina alm
B148: 9140 | G148: colorante
A158: VIERNES 14 | B158: 20350 | G158: edu | H158: 130 | I158: H
B159: 48631.72 | G159: coca
B160: 26780.83 | G160: la sereniima
A168: SABADO 15 | B168: 4590 | G168: brie | H168: 120 | I168: H
A183: LUNES 17 | B183: 42000 | G183: Damian heladera | H183: 90 | I183: H
F184: 4400 | G184: Dai limpieza
F185: 6250 | G185: Rodri sabado
B186: 16108.31 | G186: la serenisima
C187: 54720.48 | G187: matiz
F188: =507*2 -> 1014 | G188: ricota
C189: =47023.02+55842.83 -> 102865.85 | G189: quintela
G190: edu
A199: MARTES 18 | D199: 40700 | G199: manteca | I199: deposite mio en bbva 148500 y me lo transferi a cecimp
D200: 31800 | G200: harina | H200: 111 | I200: C
D201: 19789.14 | G201: criollo
D202: 10951.26 | G202: horeca
B203: 13420 | E203: pagado | G203: wraps
A214: MIERCOLES 19 | B214: 13265.67 | G214: la serenisima | H214: 80 | I214: H
B215: 60331.7 | G215: milkaut
B216: 22250 | G216: edu
D217: 51000 | G217: pollo
F218: 1700 | G218: mermelada
C219: 222914.97 | G219: ormazabal
D220: 102000 | E220: pagada | G220: cafe
F221: 16000 | G221: huevo
F222: 2000 | G222: palta
B223: 2700 | G223: palta
B224: 1840 | G224: vegetalina
A226: JUEVES 20 | B226: 38310 | G226: limpieza | H226: 110 | I226: H
F227: 1258 | G227: palta
F228: 1920 | G228: guantes nitrilo
B229: 67881 | G229: motobaires
F230: 4200 | G230: matias prueba
...

Sheet AGOSTO 2023
A1: z | B1: MP | C1: CHEQUE | D1: TRANSFERENCIA | E1: ADEUDA | F1: GASTOS EN EFT | H1: RETIROS
F2: 840 | G2: chorizo | H2: 140 | I2: H
A3: MARTES 1 | D3: 36647.12 | E3: pagado | G3: valot
B4: 32057.59 | G4: criollo
B5: 22361.88 | G5: horeca
B6: 14100 | G6: tacos
B7: 18000 | G7: cartas
G8: matiz? | I8: C uso 77898 de Bbva repone en efectivo
G9: dia amira
A15: MIERCOLES 2 | B15: 12509.04 | G15: la serenisima | H15: 140 | I15: H
D16: 51000 | G16: pollo
C17: 41552.38 | G17: ormazabal
B18: 40700 | G18: manteca
D19: 68340 | G19: distri LJ limpieza
B20: 43550 | G20: edu
F21: 17000 | G21: huevo
F22: 6250 | G22: rodri
A28: JUEVES 3 | B28: 20800 | G28: harina | H28: 121 | I28: H
F29: 2600 | G29: hielo
B42: 26700 | G42: edu | H42: 152 | I42: C
B43: 18763.57 | G43: la serenisima
A44: VIERNES 4 | D44: 73463.5 | G44: motobaires
B45: 23132 | G45: harina de almendras y colorante
B46: 4800 | G46: yogur y vegetalina
A54: SABADO 5 | B54: 47519.62 | G54: milkaut | H54: 81 | I54: C
C55: =76748.42+43926.63 -> 120675.05 | G55: quintela
F56: 3800 | G56: leche
A68: LUNES 7 | B68: 35000 | G68: escribania poder (pague yo en ef y me lo transferi en mp)
B69: 51000 | G69: pollo | H69: 84 | I69: H
B70: =31150-15500 -> 15650 | G70: edu | I70: deposite 230k en Bbva y me lo transferi a mp
F71: 5600 | G71: dai limpieza
F72: 526 | G72: carrefour ricota
B73: 29209 | G73: la serenisima
B74: 50642.61 | G74: marilu
F75: 17000 | G75: huevo
D76: 87021 | G76: honorarios abogada
B77: 31000 | G77: choco alpino pins
B78: 10425 | G78: pulpa de frutilla
A80: MARTES 8 | B80: 10795 | G80: certfic control fiscal key digital
F81: 1620 | G81: moto contadora
D82: 40700 | G82: manteca | H82: 167 | I82: H
D83: 41166.32 | G83: cuyaires
B84: 14100 | G84: wraps
A96: MIERCOLES 9 | B96: 35900 | G96: edu | H96: 100 | I96: H
F97: 2600 | G97: brie
F98: 4200 | G98: limpieza
B99: 12509.04 | G99: la serenisima | K99: batidora | L99: 1000 U$S
C100: 63835.09 | G100: ormazabal | K100: mixer
D101: 57294.45 | G101: criollo
D102: 15590.5 | G102: horeca
B103: 12000 | G103: duniapol
B104: 50869.91 | G104: coca
C105: 37971.7 | G105: matiz
B106: 16990 | G106: micron
B107: 10240 | G107: brie
B108: 2519 | G108: MOTO cajas macarons
A110: JUEVES 10 | B110: 7963 | G110: harina almendra | H110: 138 | I110: H
B111: 32500.06 | G111: harina
D112: =144000+8000 -> 152000 | E112: pagado | G112: john and joe
D113: 50873.17 | G113: marilu
F114: 3080 | G114: leche carrefour
F115: 18400 | G115: aceite freidora
B116: 4000 | G116: libreria
B117: 3740 | G117: vitalcer
B118: 4460 | G118: chino
B119: 16575 | G119: feras
A128: VIERNES 11 | B128: 29550 | G128: edu | H128: 120
B129: 51000 | G129: pollo
B130: 27763.92 | G130: la serenisima
G131: bolsas cafe
A143: SABADO 12 | F143: 17500 | G143: huevo | H143: 150 | I143: H
B145: 33981.95 | G145: milkaut
A158: LUNES 14 | B158: 15399.22 | G158: la serenisima | H158: 117 | I158: H
B159: 18700 | G159: edu | I159: pague a rodri y leo 30 mio en ef y me lo devolvi del bbva a mi mp
F160: 5700 | G160: dai limpieza
C161: 96336.63 | G161: quintela
A168: MARTES 15 | D168: 44000 | G168: manteca | H168: 87 | I168: H
D169: 19050 | G169: penguin
A183: MIERCOLES 16 | C183: 49625.27 | G183: ormazabal | H183: 100 | I183: h
B184: 29053.74 | G184: milkaut
B185: 44300 | G185: edu
B186: 39285.59 | G186: criollo
B187: 15477.03 | G187: horeca
F188: 5600 | G188: sole limpieza
F189: 444 | G189: lavandina
B190: 20931.18 | G190: la serenisisma
D191: 72872.25 | G191: motobaires
F192: 7000 | G192: enchufe pauna
A199: JUEVES 17 | D199: 58500 | G199: pollo | H199: 78 | I199: H
B200: 28200 | G200: wraps
F201: 326 | G201: frutas premium
C202: 58261.02 | G202: matiz
D203: 60300 | G203: limpieza
D204: 11293.51 | G204: horeca
B205: 69236.42 | G205: coca
D206: 32670 | G206: harina
B207: 14505 | G207: breik
A214: VIERNES 18 | B214: 26117 | G214: la serenisima | H214: 103.5
B215: 15300 | G215: edu
B216: 9170 | G216: breik cajas
...

Sheet CIERRE 2024
A1: < | B1: FECHA | C1: VENTA DIARIA | D1: ZETA | E1: CAJA | F1: CAMBIO | G1: TARJETAS | H1: PEDIDOS YA PAGO-ONLINE | I1: CTA CTE | J1: MERCADO | K1: EFECTIVO DEL DIA | L1: CAJA FUERTE | M1: CAJITA
A2: LUNES | B2: 45292
A3: MARTES | B3: 45293 | C3: 566040 | D3: 358700 | E3: 3900 | F3: 7500 | G3: =8400+186800 -> 195200 | H3: 132856 | I3: 33700 | J3: 61300 | K3: 163640
A4: MIERCOLES | B4: 45294 | C4: 531340 | D4: 408580 | E4: 3900 | F4: 10400 | G4: =135000+7000 -> 142000 | H4: 152707 | J4: 122080 | K4: 124160
A5: JUEVES | B5: 45295 | C5: =1193100-396200 -> 796900 | D5: 549460 | E5: =600+1500+2200+250+500+800+240 -> 6090 | F5: =10400 -> 10400 | G5: =9500+247550 -> 257050 | H5: 129775 | I5: =465500-396200 -> 69300 | J5: 149610 | K5: 187490
A6: VIERNES | B6: 45296 | C6: =1639650-796900-396200 -> 446550 | D6: 296500 | E6: 7800 | F6: 10300 | G6: 179800 | H6: 92371 | I6: 31400 | J6: =212610-J5 -> 63000 | K6: =249340-K5 -> 61850
A7: SABADO | B7: 45297 | C7: 511010 | D7: 414500 | E7: =700+2100+500+500+800+280 -> 4880 | F7: 4400 | G7: =238000+24700 -> 262700 | H7: 69621 | J7: 95700 | K7: 85110
A8: DOMINGO
A9: LUNES | B9: 45299 | C9: 500720 | D9: 350950 | E9: 4800 | F9: 4400 | G9: 155100 | H9: 69936 | J9: 116800 | K9: 155370
A10: MARTES | B10: 45300 | C10: 527390 | D10: 368840 | E10: =1000+400+750+500+840+240 -> 3730 | F10: =4400 -> 4400 | G10: =123810+6200 -> 130010 | H10: 173866.5 | J10: 62600 | K10: 157750
A11: MIERCOLES | B11: 45301 | C11: 670100 | D11: 495650 | E11: =2000+1000+1200+300+500+840+250 -> 6090 | F11: 4400 | G11: =211000+23700 -> 234700 | H11: 111871 | I11: 26800 | J11: 132200 | K11: 148750
A12: JUEVES | B12: 45302 | C12: 732930 | D12: 647150 | E12: =800+2500+700+550+500+880+220 -> 6150 | F12: =4400 -> 4400 | G12: =162600+106000 -> 268600 | H12: 207310.5 | J12: 138700 | K12: 94280
A13: VIERNES | B13: 45303 | C13: 549550 | D13: 450950 | E13: 1000 | F13: 4400 | G13: =228270+6800 -> 235070 | H13: 86871 | J13: 131000 | K13: 98600
A14: SABADO | B14: 45304 | C14: 548110 | D14: 456960 | E14: 1800 | F14: 2400 | G14: =218760+69900 -> 288660 | H14: 88886 | J14: 79500 | K14: 91150
A15: DOMINGO
A16: LUNES | B16: 45306 | C16: 630080 | D16: 480860 | E16: 3500 | F16: 1400 | G16: =200500+49300+11400 -> 261200 | H16: 95947 | I16: 24200 | J16: 131960 | K16: 124120
A17: MARTES | B17: 45307 | C17: 549500 | D17: 438150 | E17: 5300 | F17: 4400 | G17: =212000+6500 -> 218500 | H17: 115901 | J17: 92750 | K17: 122350
A18: MIERCOLES | B18: 45308 | C18: 714720 | D18: 568600 | E18: 4500 | F18: 7400 | G18: =174600+65400 -> 240000 | H18: 156310 | J18: 139000 | K18: 130220
A19: JUEVES | B19: 45309 | C19: 750160 | D19: 592160 | E19: =1200+1200+900+500+820+250 -> 4870 | F19: 7400 | G19: =11000+248500 -> 259500 | H19: 195000 | I19: 24700 | J19: 154160 | K19: 138900
A20: VIERNES | B20: 45310 | C20: 606205 | D20: 479460 | E20: =1000+1400+950+500+800+250 -> 4900 | F20: 10400 | G20: =5200+261400 -> 266600 | H20: 92811 | J20: 89960 | K20: 126745
A21: SABADO | B21: 45311 | C21: 432800 | D21: 270730 | E21: =1000+900+900+500+820+240 -> 4360 | F21: 6400 | G21: =159500+3000 -> 162500 | H21: 60951 | J21: 58130 | K21: 159970
A22: DOMINGO
A23: LUNES | B23: 45313 | C23: 447650 | D23: 287450 | E23: 8000 | F23: 14400 | G23: 166100 | H23: 38980 | J23: 105200 | K23: 145700
A24: MARTES | B24: 45314 | C24: 776700 | D24: 619600 | E24: 5000 | F24: 4400 | G24: =159000+71000 -> 230000 | H24: 202181 | J24: 167900 | K24: 166200
A25: MIERCOLES | B25: 45315 | C25: 507630 | D25: 396210 | G25: 83350 | H25: 83510 | J25: 95800 | K25: 127480
A26: JUEVES | B26: 45316 | C26: =831440-210100 -> 621340 | D26: 689410 | G26: 119200 | H26: 102901 | J26: 76600 | K26: 139630
A27: VIERNES | B27: 45317 | C27: 552470 | D27: 431850 | E27: 6500 | F27: 6600 | G27: =190100+14000 -> 204100 | H27: 125551 | J27: 140200 | K27: 124920
A28: SABADO | B28: 45318 | C28: 446070 | D28: 322740 | E28: 4500 | F28: 6500 | G28: 144340 | H28: 97156 | J28: 76600 | K28: 128730
A29: DOMINGO
A30: LUNES | B30: 45320 | C30: 604740 | D30: 431040 | E30: 2600 | F30: =1600+3000+2000 -> 6600 | G30: =192800+1100 -> 193900 | H30: 127400 | J30: 118700 | K30: 160100
A31: Martes | B31: 45321 | C31: 495230 | D31: 386430 | E31: =500+1900+750+200+160+300 -> 3810 | F31: 4600 | G31: =6500+187030 -> 193530 | H31: 77500 | J31: 142100 | K31: 87000
A32: Miercoles | B32: 45322 | C32: 518050 | D32: 423980 | E32: 3200 | F32: 4600 | G32: 155400 | H32: 115510 | J32: 184680 | K32: 70770
A33: TOTAL | C33: =SUM(C2:C32) -> 15033985
A34: JUEVES | B34: 45323 | C34: 552340 | D34: 441800 | F34: 3600 | G34: 229500 | H34: 94400 | J34: 123900 | K34: 81540
A35: VIERNES | B35: 45324 | C35: 552810 | D35: 383410 | F35: 11600 | G35: 123600 | H35: 92456 | J35: 134210 | K35: 165400
A36: SABADO | B36: 45325 | C36: 432660 | D36: 344900 | E36: =1500+1500+700+400+310 -> 4410 | F36: =2000+1000+6000 -> 9000 | G36: =14900+223100 -> 238000 | H36: 36600 | J36: 56600 | K36: 87760
A37: DOMINGO
A38: LUNES | B38: 45327 | C38: 649730 | D38: 501120 | E38: 3000 | F38: 7500 | G38: 233740 | H38: 137261 | J38: 118500 | K38: 168390
A39: MARTES | B39: 45328 | C39: 659570 | D39: 478990 | E39: 3000 | F39: 3500 | G39: 230810 | H39: 135871 | J39: 128880 | K39: 168080
A40: MIERCOLES | B40: 45329 | C40: 710220 | D40: 526620 | E40: 3500 | F40: 3500 | G40: =250570+21600 -> 272170 | H40: 138610 | J40: 118700 | K40: 189200
A41: JUEVES | B41: 45330 | C41: 693630 | D41: 458600 | E41: 3500 | F41: 3500 | G41: 296450 | H41: 40483 | J41: 165530 | K41: 170730
A42: VIERNES | B42: 45331 | C42: 460060 | D42: 355300 | E42: 5730 | F42: 3500 | G42: 184200 | H42: 79800 | J42: 65490 | K42: 137720
A43: SABADO | B43: 45332 | C43: 622970 | D43: 451280 | F43: 11500 | G43: 163900 | H43: 81611 | J43: 119680 | K43: 161690
A44: DOMINGO
A45: LUNES | B45: 45334 | C45: 534760 | D45: 418560 | E45: 5000 | F45: 9500 | G45: 145500 | H45: 34771 | J45: 110140 | K45: 122500
A46: MARTES | B46: 45335 | C46: 523205 | D46: 428605 | E46: 5400 | F46: 9500 | G46: 286900 | H46: 182000 | J46: 159005 | K46: 116000
A47: MIERCOLES | B47: 45336 | C47: 838350 | D47: 608400 | E47: 500 | F47: 9500 | G47: 178320 | H47: 141900 | J47: 216000 | K47: 222000
A48: JUEVES | B48: 45337 | C48: 799600 | D48: 660680 | G48: 352500 | H48: 189800 | J48: 324000 | K48: 387850
A49: VIERNES | B49: 45338 | C49: 609960 | D49: 500700 | G49: 223900 | H49: 110446 | J49: 182000 | K49: 103660
A50: SABADO | B50: 45339 | C50: 599610 | D50: 435250 | E50: 3000 | F50: =3600+8000 -> 11600 | G50: 286850 | H50: 12700 | J50: 159500 | K50: 164360
A51: DOMINGO
A52: LUNES | B52: 45341 | C52: 595240 | D52: 446920 | G52: 277300 | H52: 79750 | J52: 121820 | K52: 147920
A53: MARTES | B53: 45342 | C53: 662170 | D53: 500410 | E53: =2000+3400+1400+200+600+200+250 -> 8050 | F53: =1000+1000+1000+500 -> 3500 | G53: =254200+28400 -> 282600 | H53: 108150 | J53: 95060 | K53: 159660
A54: MIERCOLES | B54: 45343 | C54: 661440 | D54: 474300 | E54: 6000 | F54: 3500 | G54: 235200 | H54: 156600 | J54: 70600 | K54: 193340
A55: JUEVES | B55: 45344 | C55: 696780 | D55: 587780 | E55: 6000 | F55: 3500 | G55: =231800+7600 -> 239400 | H55: 134055 | J55: 181200 | K55: 109000
A56: VIERNES | B56: 45345 | C56: 562300 | D56: 451400 | E56: 6000 | F56: 3500 | G56: 233700 | H56: 72255 | J56: 181500 | K56: 106100
A57: SABADO | B57: 45346 | C57: 773900 | D57: 567100 | E57: 6000 | F57: 11500 | G57: 359470 | H57: 70200 | J57: 119330 | K57: 238400
A58: DOMINGO
A59: LUNES | B59: 45348 | C59: 653040 | D59: 537640 | E59: =600+1500+1900+1550+200+740+200+200 -> 6890 | F59: 11500 | G59: =90500+103900 -> 194400 | H59: 110231 | J59: 231740 | K59: 106300
A60: Martes | B60: 45349 | C60: 588360 | D60: 449620 | G60: 255580 | H60: 90900 | J60: 104340 | K60: 138540
A61: MIERCOLES | B61: 45350 | C61: 685580 | D61: 489000 | F61: 3500 | G61: 250700 | H61: 109626 | J61: 146500 | K61: 202080
A62: Jueves | B62: 45351 | C62: 1338120 | D62: 1188960 | F62: 3500 | G62: 731800 | H62: 201311 | J62: 226860 | K62: 181160
A63: TOTAL | C63: =SUM(C34:C62) -> 16456405
A64: VIERNES | B64: 45352 | C64: 765740 | D64: 627400 | F64: 2500 | G64: 312700 | H64: 144381 | J64: 178800 | K64: 141740
A65: SÁBADO | B65: 45353 | C65: 605600 | D65: 492000 | G65: 213900 | H65: 81505 | J65: 102700 | K65: 113600
A66: DOMINGO | B66: 45354
A67: LUNES | B67: 45355 | C67: 534500 | D67: 459100 | F67: 2500 | G67: 126300 | H67: 138666 | J67: 127600 | K67: 75400
A68: MARTES | B68: 45356 | C68: 850260 | D68: 716700 | G68: 349400 | H68: 19115 | J68: 174900 | K68: 143460
A69: MIÉRCOLES | B69: 45357 | C69: 686210 | D69: 559100 | G69: 361200 | H69: 66215 | J69: 110500 | K69: 140110
A70: JUEVES | B70: 45358 | C70: 876350 | D70: 733560 | G70: 354300 | H70: 183315 | J70: 99380 | K70: 172890
A71: VIERNES | B71: 45359 | C71: 630640 | D71: 492840 | F71: 2500 | G71: 278900 | H71: 72105 | J71: 168540 | K71: 126500
A72: SÁBADO | B72: 45360 | C72: 697970 | D72: 556580 | F72: 2500 | G72: 299700 | H72: 165100 | J72: 165100 | K72: 139190
A73: DOMINGO | B73: 45361
A74: LUNES | B74: 45362 | C74: 461400 | D74: 337560 | F74: 2500 | G74: 146000 | H74: 68700 | J74: 112060 | K74: 111440
A75: MARTES | B75: 45363 | C75: 561770 | D75: 402790 | F75: 2500 | G75: 200130 | H75: 51700 | J75: 144750 | K75: 188780
A76: MIÉRCOLES | B76: 45364 | C76: 549780 | D76: 430960 | F76: 2500 | G76: 158800 | H76: 122900 | J76: 149660 | K76: 122320
A77: JUEVES | B77: 45365 | C77: 809220 | D77: 685500 | F77: 2500 | G77: 391900 | H77: 102110 | J77: 174700 | K77: 137720
A78: VIERNES | B78: 45366 | C78: =1528640-C77 -> 719420 | D78: 585770 | H78: 143121 | J78: =300870-J77 -> 126170 | K78: =293970-K77 -> 156250
A79: SÁBADO | B79: 45367 | C79: 545560 | D79: 429750 | F79: 2500 | G79: 228000 | H79: 64155 | J79: 155600 | K79: 115810
A80: DOMINGO | B80: 45368
A81: LUNES | B81: 45369 | C81: 615660 | D81: 461160 | G81: =44600+14600+198700 -> 257900 | H81: 65915 | J81: 124260 | K81: 177800
A82: MARTES | B82: 45370 | C82: 658390 | D82: 514780 | F82: 2500 | G82: 194800 | H82: 202959 | J82: 97180 | K82: 154710
A83: MIÉRCOLES | B83: 45371 | C83: 560030 | D83: 414960 | F83: 2500 | G83: 163300 | H83: 160250 | J83: 103010 | K83: 143370
A84: JUEVES | B84: 45372 | C84: =1726560-C83-C82 -> 508140 | D84: =857550-D83 -> 442590 | F84: 2500 | G84: =482900-G83 -> 319600 | H84: =482900-H83-H83 -> 162400 | J84: =482900-J83-J82 -> 282710 | K84: =421550-K83-K82 -> 123470
A85: VIERNES | B85: 45373 | C85: 635530 | D85: 558060 | F85: 2500 | G85: 263300 | H85: 110351 | J85: 195700 | K85: 69870
A86: SÁBADO | B86: 45374 | C86: 747520 | D86: 568280 | F86: 2500 | G86: 347600 | H86: 124721 | K86: 147040
A87: DOMINGO | B87: 45375
A88: LUNES | B88: 45376 | C88: 784860 | D88: 646500 | F88: 2500 | G88: 361100 | H88: 79200 | J88: 196400 | K88: 181160
A89: MARTES | B89: 45377 | C89: 926250 | D89: 776700 | F89: 2500 | G89: 391800 | H89: 130500 | J89: 261800 | K89: 161850
A90: MIÉRCOLES | B90: 45378 | C90: 884120 | D90: 766180 | F90: 2500 | G90: 327200 | H90: 102600 | J90: 293480 | K90: 140340
A91: JUEVES | B91: 45379 | C91: 712350 | D91: 620460 | F91: 2500 | G91: 365240 | H91: 63300 | J91: 185120 | K91: 88190
A92: VIERNES | B92: 45380 | C92: 662760 | D92: 485840 | F92: 2500 | G92: 275900 | H92: 140011 | J92: 78540 | K92: 188220
A93: SÁBADO | B93: 45381 | C93: 450230 | D93: 353060 | F93: 2500 | G93: 175300 | H93: 58600 | J93: 128610 | K93: 97170
A94: DOMINGO | B94: 45382
A95: TOTAL | C95: =SUM(C66:C94) -> 16068920
A96: LUNES | B96: 45383
A97: MARTES | B97: 45384 | C97: 740780 | D97: 658980 | F97: 2500 | G97: 297240 | H97: 128300 | J97: 249280 | K97: 73800
A98: MIÉRCOLES | B98: 45385 | C98: 539350 | D98: 439220 | F98: 2000 | H98: 100526 | J98: 71140 | K98: 90530
A99: JUEVES | B99: 45386 | C99: 1084390 | D99: 896260 | F99: 2000 | G99: 443400 | H99: 287600 | K99: 181930
A100: VIERNES | B100: 45387 | C100: 716170 | D100: 561090 | F100: 2000 | G100: 249750 | H100: 124800 | J100: 161200 | K100: 175180
...

Sheet CIERRE 2025
A1: < | B1: FECHA | C1: VENTA DIARIA | D1: ZETA | E1: CAJA | F1: CAMBIO | G1: TARJETAS | H1: RAPPI PAGO-ONLINE | I1: PEDIDOSYA PAGO-ONLINE | J1: CTA CTE | K1: MERCADO | L1: EFECTIVO DEL DIA | M1: RETIROS | N1: CAJA
A2: LUNES | B2: 45292
A3: MARTES | B3: 45293 | C3: 566040 | D3: 358700 | E3: 3900 | F3: 7500 | G3: =8400+186800 -> 195200 | H3: 132856 | J3: 33700 | K3: 61300 | L3: 163640
A4: MIERCOLES | B4: 45294 | C4: 531340 | D4: 408580 | E4: 3900 | F4: 10400 | G4: =135000+7000 -> 142000 | H4: 152707 | K4: 122080 | L4: 124160
A5: JUEVES | B5: 45295 | C5: =1193100-396200 -> 796900 | D5: 549460 | E5: =600+1500+2200+250+500+800+240 -> 6090 | F5: =10400 -> 10400 | G5: =9500+247550 -> 257050 | H5: 129775 | J5: =465500-396200 -> 69300 | K5: 149610 | L5: 187490
A6: VIERNES | B6: 45296 | C6: =1639650-796900-396200 -> 446550 | D6: 296500 | E6: 7800 | F6: 10300 | G6: 179800 | H6: 92371 | J6: 31400 | K6: =212610-K5 -> 63000 | L6: =249340-L5 -> 61850
A7: SABADO | B7: 45297 | C7: 511010 | D7: 414500 | E7: =700+2100+500+500+800+280 -> 4880 | F7: 4400 | G7: =238000+24700 -> 262700 | H7: 69621 | K7: 95700 | L7: 85110
A8: DOMINGO
A9: LUNES | B9: 45299 | C9: 500720 | D9: 350950 | E9: 4800 | F9: 4400 | G9: 155100 | H9: 69936 | K9: 116800 | L9: 155370
A10: MARTES | B10: 45300 | C10: 527390 | D10: 368840 | E10: =1000+400+750+500+840+240 -> 3730 | F10: =4400 -> 4400 | G10: =123810+6200 -> 130010 | H10: 173866.5 | K10: 62600 | L10: 157750
A11: MIERCOLES | B11: 45301 | C11: 670100 | D11: 495650 | E11: =2000+1000+1200+300+500+840+250 -> 6090 | F11: 4400 | G11: =211000+23700 -> 234700 | H11: 111871 | J11: 26800 | K11: 132200 | L11: 148750
A12: JUEVES | B12: 45302 | C12: 732930 | D12: 647150 | E12: =800+2500+700+550+500+880+220 -> 6150 | F12: =4400 -> 4400 | G12: =162600+106000 -> 268600 | H12: 207310.5 | K12: 138700 | L12: 94280
A13: VIERNES | B13: 45303 | C13: 549550 | D13: 450950 | E13: 1000 | F13: 4400 | G13: =228270+6800 -> 235070 | H13: 86871 | K13: 131000 | L13: 98600
A14: SABADO | B14: 45304 | C14: 548110 | D14: 456960 | E14: 1800 | F14: 2400 | G14: =218760+69900 -> 288660 | H14: 88886 | K14: 79500 | L14: 91150
A15: DOMINGO
A16: LUNES | B16: 45306 | C16: 630080 | D16: 480860 | E16: 3500 | F16: 1400 | G16: =200500+49300+11400 -> 261200 | H16: 95947 | J16: 24200 | K16: 131960 | L16: 124120
A17: MARTES | B17: 45307 | C17: 549500 | D17: 438150 | E17: 5300 | F17: 4400 | G17: =212000+6500 -> 218500 | H17: 115901 | K17: 92750 | L17: 122350
A18: MIERCOLES | B18: 45308 | C18: 714720 | D18: 568600 | E18: 4500 | F18: 7400 | G18: =174600+65400 -> 240000 | H18: 156310 | K18: 139000 | L18: 130220
A19: JUEVES | B19: 45309 | C19: 750160 | D19: 592160 | E19: =1200+1200+900+500+820+250 -> 4870 | F19: 7400 | G19: =11000+248500 -> 259500 | H19: 195000 | J19: 24700 | K19: 154160 | L19: 138900
A20: VIERNES | B20: 45310 | C20: 606205 | D20: 479460 | E20: =1000+1400+950+500+800+250 -> 4900 | F20: 10400 | G20: =5200+261400 -> 266600 | H20: 92811 | K20: 89960 | L20: 126745
A21: SABADO | B21: 45311 | C21: 432800 | D21: 270730 | E21: =1000+900+900+500+820+240 -> 4360 | F21: 6400 | G21: =159500+3000 -> 162500 | H21: 60951 | K21: 58130 | L21: 159970
A22: DOMINGO
A23: LUNES | B23: 45313 | C23: 447650 | D23: 287450 | E23: 8000 | F23: 14400 | G23: 166100 | H23: 38980 | K23: 105200 | L23: 145700
A24: MARTES | B24: 45314 | C24: 776700 | D24: 619600 | E24: 5000 | F24: 4400 | G24: =159000+71000 -> 230000 | H24: 202181 | K24: 167900 | L24: 166200
A25: MIERCOLES | B25: 45315 | C25: 507630 | D25: 396210 | G25: 83350 | H25: 83510 | K25: 95800 | L25: 127480
A26: JUEVES | B26: 45316 | C26: =831440-210100 -> 621340 | D26: 689410 | G26: 119200 | H26: 102901 | K26: 76600 | L26: 139630
A27: VIERNES | B27: 45317 | C27: 552470 | D27: 431850 | E27: 6500 | F27: 6600 | G27: =190100+14000 -> 204100 | H27: 125551 | K27: 140200 | L27: 124920
A28: SABADO | B28: 45318 | C28: 446070 | D28: 322740 | E28: 4500 | F28: 6500 | G28: 144340 | H28: 97156 | K28: 76600 | L28: 128730
A29: DOMINGO
A30: LUNES | B30: 45320 | C30: 604740 | D30: 431040 | E30: 2600 | F30: =1600+3000+2000 -> 6600 | G30: =192800+1100 -> 193900 | H30: 127400 | K30: 118700 | L30: 160100
A31: Martes | B31: 45321 | C31: 495230 | D31: 386430 | E31: =500+1900+750+200+160+300 -> 3810 | F31: 4600 | G31: =6500+187030 -> 193530 | H31: 77500 | K31: 142100 | L31: 87000
A32: Miercoles | B32: 45322 | C32: 518050 | D32: 423980 | E32: 3200 | F32: 4600 | G32: 155400 | H32: 115510 | K32: 184680 | L32: 70770
A33: TOTAL | C33: =SUM(C2:C32) -> 15033985
A34: JUEVES | B34: 45323 | C34: 552340 | D34: 441800 | F34: 3600 | G34: 229500 | H34: 94400 | K34: 123900 | L34: 81540
A35: VIERNES | B35: 45324 | C35: 552810 | D35: 383410 | F35: 11600 | G35: 123600 | H35: 92456 | K35: 134210 | L35: 165400
A36: SABADO | B36: 45325 | C36: 432660 | D36: 344900 | E36: =1500+1500+700+400+310 -> 4410 | F36: =2000+1000+6000 -> 9000 | G36: =14900+223100 -> 238000 | H36: 36600 | K36: 56600 | L36: 87760
A37: DOMINGO
A38: LUNES | B38: 45327 | C38: 649730 | D38: 501120 | E38: 3000 | F38: 7500 | G38: 233740 | H38: 137261 | K38: 118500 | L38: 168390
A39: MARTES | B39: 45328 | C39: 659570 | D39: 478990 | E39: 3000 | F39: 3500 | G39: 230810 | H39: 135871 | K39: 128880 | L39: 168080
A40: MIERCOLES | B40: 45329 | C40: 710220 | D40: 526620 | E40: 3500 | F40: 3500 | G40: =250570+21600 -> 272170 | H40: 138610 | K40: 118700 | L40: 189200
A41: JUEVES | B41: 45330 | C41: 693630 | D41: 458600 | E41: 3500 | F41: 3500 | G41: 296450 | H41: 40483 | K41: 165530 | L41: 170730
A42: VIERNES | B42: 45331 | C42: 460060 | D42: 355300 | E42: 5730 | F42: 3500 | G42: 184200 | H42: 79800 | K42: 65490 | L42: 137720
A43: SABADO | B43: 45332 | C43: 622970 | D43: 451280 | F43: 11500 | G43: 163900 | H43: 81611 | K43: 119680 | L43: 161690
A44: DOMINGO
A45: LUNES | B45: 45334 | C45: 534760 | D45: 418560 | E45: 5000 | F45: 9500 | G45: 145500 | H45: 34771 | K45: 110140 | L45: 122500
A46: MARTES | B46: 45335 | C46: 523205 | D46: 428605 | E46: 5400 | F46: 9500 | G46: 286900 | H46: 182000 | K46: 159005 | L46: 116000
A47: MIERCOLES | B47: 45336 | C47: 838350 | D47: 608400 | E47: 500 | F47: 9500 | G47: 178320 | H47: 141900 | K47: 216000 | L47: 222000
A48: JUEVES | B48: 45337 | C48: 799600 | D48: 660680 | G48: 352500 | H48: 189800 | K48: 324000 | L48: 387850
A49: VIERNES | B49: 45338 | C49: 609960 | D49: 500700 | G49: 223900 | H49: 110446 | K49: 182000 | L49: 103660
A50: SABADO | B50: 45339 | C50: 599610 | D50: 435250 | E50: 3000 | F50: =3600+8000 -> 11600 | G50: 286850 | H50: 12700 | K50: 159500 | L50: 164360
A51: DOMINGO
A52: LUNES | B52: 45341 | C52: 595240 | D52: 446920 | G52: 277300 | H52: 79750 | K52: 121820 | L52: 147920
A53: MARTES | B53: 45342 | C53: 662170 | D53: 500410 | E53: =2000+3400+1400+200+600+200+250 -> 8050 | F53: =1000+1000+1000+500 -> 3500 | G53: =254200+28400 -> 282600 | H53: 108150 | K53: 95060 | L53: 159660
A54: MIERCOLES | B54: 45343 | C54: 661440 | D54: 474300 | E54: 6000 | F54: 3500 | G54: 235200 | H54: 156600 | K54: 70600 | L54: 193340
A55: JUEVES | B55: 45344 | C55: 696780 | D55: 587780 | E55: 6000 | F55: 3500 | G55: =231800+7600 -> 239400 | H55: 134055 | K55: 181200 | L55: 109000
A56: VIERNES | B56: 45345 | C56: 562300 | D56: 451400 | E56: 6000 | F56: 3500 | G56: 233700 | H56: 72255 | K56: 181500 | L56: 106100
A57: SABADO | B57: 45346 | C57: 773900 | D57: 567100 | E57: 6000 | F57: 11500 | G57: 359470 | H57: 70200 | K57: 119330 | L57: 238400
A58: DOMINGO
A59: LUNES | B59: 45348 | C59: 653040 | D59: 537640 | E59: =600+1500+1900+1550+200+740+200+200 -> 6890 | F59: 11500 | G59: =90500+103900 -> 194400 | H59: 110231 | K59: 231740 | L59: 106300
A60: Martes | B60: 45349 | C60: 588360 | D60: 449620 | G60: 255580 | H60: 90900 | K60: 104340 | L60: 138540
A61: MIERCOLES | B61: 45350 | C61: 685580 | D61: 489000 | F61: 3500 | G61: 250700 | H61: 109626 | K61: 146500 | L61: 202080
A62: Jueves | B62: 45351 | C62: 1338120 | D62: 1188960 | F62: 3500 | G62: 731800 | H62: 201311 | K62: 226860 | L62: 181160
A63: TOTAL | C63: =SUM(C34:C62) -> 16456405
A64: VIERNES | B64: 45352 | C64: 765740 | D64: 627400 | F64: 2500 | G64: 312700 | H64: 144381 | K64: 178800 | L64: 141740
A65: SÁBADO | B65: 45353 | C65: 605600 | D65: 492000 | G65: 213900 | H65: 81505 | K65: 102700 | L65: 113600
A66: DOMINGO | B66: 45354
A67: LUNES | B67: 45355 | C67: 534500 | D67: 459100 | F67: 2500 | G67: 126300 | H67: 138666 | K67: 127600 | L67: 75400
A68: MARTES | B68: 45356 | C68: 850260 | D68: 716700 | G68: 349400 | H68: 19115 | K68: 174900 | L68: 143460
A69: MIÉRCOLES | B69: 45357 | C69: 686210 | D69: 559100 | G69: 361200 | H69: 66215 | K69: 110500 | L69: 140110
A70: JUEVES | B70: 45358 | C70: 876350 | D70: 733560 | G70: 354300 | H70: 183315 | K70: 99380 | L70: 172890
A71: VIERNES | B71: 45359 | C71: 630640 | D71: 492840 | F71: 2500 | G71: 278900 | H71: 72105 | K71: 168540 | L71: 126500
A72: SÁBADO | B72: 45360 | C72: 697970 | D72: 556580 | F72: 2500 | G72: 299700 | H72: 165100 | K72: 165100 | L72: 139190
A73: DOMINGO | B73: 45361
A74: LUNES | B74: 45362 | C74: 461400 | D74: 337560 | F74: 2500 | G74: 146000 | H74: 68700 | K74: 112060 | L74: 111440
A75: MARTES | B75: 45363 | C75: 561770 | D75: 402790 | F75: 2500 | G75: 200130 | H75: 51700 | K75: 144750 | L75: 188780
A76: MIÉRCOLES | B76: 45364 | C76: 549780 | D76: 430960 | F76: 2500 | G76: 158800 | H76: 122900 | K76: 149660 | L76: 122320
A77: JUEVES | B77: 45365 | C77: 809220 | D77: 685500 | F77: 2500 | G77: 391900 | H77: 102110 | K77: 174700 | L77: 137720
A78: VIERNES | B78: 45366 | C78: =1528640-C77 -> 719420 | D78: 585770 | H78: 143121 | K78: =300870-K77 -> 126170 | L78: =293970-L77 -> 156250
A79: SÁBADO | B79: 45367 | C79: 545560 | D79: 429750 | F79: 2500 | G79: 228000 | H79: 64155 | K79: 155600 | L79: 115810
A80: DOMINGO | B80: 45368
A81: LUNES | B81: 45369 | C81: 615660 | D81: 461160 | G81: =44600+14600+198700 -> 257900 | H81: 65915 | K81: 124260 | L81: 177800
A82: MARTES | B82: 45370 | C82: 658390 | D82: 514780 | F82: 2500 | G82: 194800 | H82: 202959 | K82: 97180 | L82: 154710
A83: MIÉRCOLES | B83: 45371 | C83: 560030 | D83: 414960 | F83: 2500 | G83: 163300 | H83: 160250 | K83: 103010 | L83: 143370
A84: JUEVES | B84: 45372 | C84: =1726560-C83-C82 -> 508140 | D84: =857550-D83 -> 442590 | F84: 2500 | G84: =482900-G83 -> 319600 | H84: =482900-H83-H83 -> 162400 | K84: =482900-K83-K82 -> 282710 | L84: =421550-L83-L82 -> 123470
A85: VIERNES | B85: 45373 | C85: 635530 | D85: 558060 | F85: 2500 | G85: 263300 | H85: 110351 | K85: 195700 | L85: 69870
A86: SÁBADO | B86: 45374 | C86: 747520 | D86: 568280 | F86: 2500 | G86: 347600 | H86: 124721 | L86: 147040
A87: DOMINGO | B87: 45375
A88: LUNES | B88: 45376 | C88: 784860 | D88: 646500 | F88: 2500 | G88: 361100 | H88: 79200 | K88: 196400 | L88: 181160
A89: MARTES | B89: 45377 | C89: 926250 | D89: 776700 | F89: 2500 | G89: 391800 | H89: 130500 | K89: 261800 | L89: 161850
A90: MIÉRCOLES | B90: 45378 | C90: 884120 | D90: 766180 | F90: 2500 | G90: 327200 | H90: 102600 | K90: 293480 | L90: 140340
A91: JUEVES | B91: 45379 | C91: 712350 | D91: 620460 | F91: 2500 | G91: 365240 | H91: 63300 | K91: 185120 | L91: 88190
A92: VIERNES | B92: 45380 | C92: 662760 | D92: 485840 | F92: 2500 | G92: 275900 | H92: 140011 | K92: 78540 | L92: 188220
A93: SÁBADO | B93: 45381 | C93: 450230 | D93: 353060 | F93: 2500 | G93: 175300 | H93: 58600 | K93: 128610 | L93: 97170
A94: DOMINGO | B94: 45382
A95: TOTAL | C95: =SUM(C66:C94) -> 16068920
A96: LUNES | B96: 45383
A97: MARTES | B97: 45384 | C97: 740780 | D97: 658980 | F97: 2500 | G97: 297240 | H97: 128300 | K97: 249280 | L97: 73800
A98: MIÉRCOLES | B98: 45385 | C98: 539350 | D98: 439220 | F98: 2000 | H98: 100526 | K98: 71140 | L98: 90530
A99: JUEVES | B99: 45386 | C99: 1084390 | D99: 896260 | F99: 2000 | G99: 443400 | H99: 287600 | L99: 181930
A100: VIERNES | B100: 45387 | C100: 716170 | D100: 561090 | F100: 2000 | G100: 249750 | H100: 124800 | K100: 161200 | L100: 175180
...

Sheet Hoja 11
B3: LUNES | C3: MARTES | D3: MIERCOLES | E3: JUEVES | F3: VIERNES | G3: SABADO | H3: DOMINGO
A4: TURNO | E4: JUAN | F4: JUAN | G4: JUAN
A5: MAÑANA | B5: JUAN SOLO | C5: JUAN SOLO | D5: JUAN SOLO
A6: 8 A 14 HS | E6: PRIS | F6: PRIS | G6: PRIS
C7: S
A8: TURNO | B8: AGUS | C8: AGUS | D8: AGUS | E8: AGUS | F8: AGUS | G8: AGUS
A9: TARDE
A10: 14 A 20 HS | B10: SEBA | C10: PRIS | D10: SEBA | E10: SEBA | F10: SEBA | G10: SEBA
A11: FRANCOS | B11: SEBA | C11: SEBA | D11: SEBA | E11: SEBA | F11: SEBA | G11: SEBA | H11: AGUS

Sheet SEPTIEMBRE 2023
A1: z | B1: MP | C1: CHEQUE | D1: TRANSFERENCIA | E1: ADEUDA | F1: GASTOS EN EFT | H1: RETIROS
F2: =3888+2268 -> 6156 | G2: leche carrefour | H2: 120 | I2: H
A3: VIERNES 1 | F3: 5600 | G3: dai limpieza
B4: 18350 | G4: edu
B5: 18500 | G5: syrups
F6: 1500 | G6: moto syrups
D7: 76865.25 | G7: motobaires
B8: 200000 | G8: laurimar
A15: SABADO 2 | B15: 21075.7 | G15: brie | H15: 85 | I15: H
B16: 19701.7 | G16: la serenisima | I16: 250 se transf de bbva a h
B17: 45984.22 | G17: milkaut | I17: 250 se transf de bbva a C (94656 pague comafi de bbva y 155344 a mi mp)
F18: 23500 | G18: huevo
A28: LUNES 4 | B28: 51917.47 | G28: la serenisima | H28: 90 | I28: H
B29: 45600 | G29: edu
F30: 2270 | G30: carrefour
C31: =46212.86+69735.93 -> 115948.79 | G31: quintela
D32: 55903.55 | G32: marilu
F33: 5600 | G33: dai limpieza
D42: 66000 | G42: pollo | H42: 133 | I42: H
D43: 50000 | G43: manteca
A44: MARTES 5 | D44: =24257.9+18540.68 -> 42798.58 | G44: criollo
D45: 4116.53 | G45: horeca
D46: 22641.45 | G46: feras
F47: 10000 | G47: enchife cafetera
F48: 1600 | G48: moto contadora
A54: MIERCOLES 6 | F54: 5600 | G54: sole limpieza | H54: 123 | I54: H
F55: 869 | G55: prod limpieza
B56: 20900 | G56: edu
C57: 41066.61 | G57: ormazabal
D58: 108262.33 | G58: gonzanio
A68: JUEVES 7 | F68: 2000 | G68: hielo | H68: 180 | I68: H
B69: 32670 | G69: harina
D70: 79217.8 | G70: cuyaires
C71: 71385.2 | G71: matiz
B72: 20449 | G72: wraps
B73: 40898 | G73: wraps
A80: VIERNES 8 | B80: 40850 | G80: edu
B81: 26268.94 | G81: la serenisima
F82: 5600 | G82: dai limpieza
B83: 45591.93 | G83: coca femsa
D84: 192753 | G84: penguin
A96: SABADO 9 | B96: 52984.37 | G96: milkaut | H96: 76 | I96: C
F97: 23500 | G97: huevos
K99: batidora | L99: 1000 U$S
K100: mixer
A110: LUNES 11 | D110: 58705.09 | G110: marilu | H110: 106.9 | I110: H
F111: 5600 | G111: dai limpieza
C112: =69393.5+44354.97 -> 113748.47 | G112: quintela
B113: 26268.94 | G113: la serenisima
B114: 23300 | G114: edu
F115: 3700 | G115: frutas premium
B116: 20900 | G116: chco alpino bco pins x 6k
A128: MARTES 12 | B128: 25798.01 | G128: criollo | H128: 110 | I128: H
B129: 4116.53 | G129: horeca
D130: 38990 | G130: lj limpieza
F131: 498 | G131: fp
B132: 66000 | G132: pollo
B133: 50000 | G133: manteca
B134: 38742 | G134: modo barista
A143: MIERCOLES 13 | F143: 5600 | G143: sole limpieza | H143: 150
B144: 12982.92 | G144: la serenisima
C145: 88438.13 | G145: ormazabal
B146: 44472.82 | G146: milkaut
B147: 45750 | G147: edu
A158: JUEVES 14 | D158: 20449 | G158: tacos wraps | H158: 96
D159: 26320 | G159: harina
C160: 75135.25 | G160: matiz
B161: 19040 | G161: festines
F162: 1160 | G162: coca
B163: 70000 | G163: gilda tratamiento fabri
F164: 23200 | G164: aceite
A168: VIERNES 15 | F168: 5600 | G168: dai limpieza | H168: 160
B169: 19050 | G169: edu
B170: 13791.28 | G170: la serenisima
B171: 30833.24 | G171: coca
A183: SABADO 16 | C183: 74611.02 | G183: quintela | I183: 50 mp H
B184: 20925.67 | G184: criollo | I184: 50 mp C
B185: 19078.65 | G185: horeca | I185: 200 galicia H
F186: 23500 | G186: huevo | I186: 200 ef C
D187: 88511.5 | G187: motobaires | H187: 87.7
A199: LUNES 18 | B199: 66000 | G199: pollo | H199: =72.5+90 -> 162.5
D200: 37246.42 | G200: marilu
B201: 24600 | G201: edu
B202: 29967.45 | G202: la serenisima
F203: 5600 | G203: dai limpieza
B204: 20676 | G204: colorante red
D205: 213928 | G205: penguin
A214: MARTES 19 | D214: 50000 | G214: manteca | H214: 143
F215: 87300 | G215: rollos posnet (se uso del ef guardado)
D216: 262400 | G216: laurimar
B217: 22000 | G217: tuppers chino
A226: MIERCOLES 20 | B226: 43300 | G226: edu | H226: =33.2+70 -> 103.2
F227: 5600 | G227: sole limp
C228: 53034.57 | G228: ormazabal
B229: 20686.92 | G229: la serenisima
B230: 42897.3 | G230: milkaut
B231: 7000 | G231: buganza calcu y mouse
A241: JUEVES 21 | B241: 4095 | G241: sorbetes | H241: 152
C242: 68362.13 | G242: matiz
B243: 33590 | G243: harina
...

Sheet OCTUBRE 2023
A1: z | B1: MP | C1: CHEQUE | D1: TRANSFERENCIA | E1: ADEUDA | F1: GASTOS EN EFT | H1: RETIROS
F2: 23500 | G2: huevo | H2: 78.5 | I2: H
A3: LUNES 2 | F3: 5600 | G3: dai limpieza
B4: 49500 | G4: Edu
B5: 29967.45 | G5: la serenisima
D6: 52871.92 | G6: marilu
F7: 1160 | G7: ricota
B8: 25306.93 | G8: criollo
B9: 199254.71 | G9: horeca | I9: tenia a favor 13k
A15: MARTES 3 | D15: 58000 | G15: manteca | H15: 131.5 | I15: H
B16: 20442.5 | G16: feras f rojos
D17: 25306.93 | E17: si | G17: criollo
D18: 19254.71 | E18: si | G18: horeca
A28: MIERCOLES 4 | C28: 79121.56 | G28: ormazabal | H28: 130
F29: 5000 | G29: Milo
B30: 27423.44 | G30: la serenisima
D31: 20449 | G31: wraps
G32: sole limpieza ?
B33: 45250 | G33: edu
B42: 23200 | G42: aceite freidora | H42: =85.5-55 -> 30.5
B43: 66000 | G43: pollo
A44: JUEVES 5 | B44: 12716 | G44: pulpa frutilla
C45: 55417.75 | G45: matiz
G46: penguin
B47: 84267.69 | G47: femsa coca
B48: 46980 | G48: cajon de dinero
A54: VIERNES 6 | B54: =26700-1600 -> 25100 | G54: edu | H54: 134.5 | I54: H
B55: 20686.92 | G55: la serenisima
F56: 4900 | G56: dai
D58: 77591.25 | G58: motobaires
F59: 1930 | G59: banana
F60: 3000 | G60: hielo
A68: SABADO 7 | F68: 23500 | G68: huevo | H68: 95
F69: 1055 | G69: coliflor
C70: =83836.67+53160.68 -> 136997.35 | G70: quintela
A80: LUNES 9 | B80: =60200-25000 -> 35200 | G80: edu | H80: 80
F81: 1542 | G81: frutas premium
B82: 33106.98 | G82: la serenisima
F83: 5600 | G83: dai
D84: 49644.39 | G84: marilu
B85: 4893 | G85: frutas premium
B86: 1849 | G86: uber a la contadora
B87: 15500 | G87: megafono
A96: MARTES 10 | D96: 66000 | G96: pollo | H96: =110+42 -> 152
D97: 122517.34 | G97: gonzanio
C98: 52834.11 | G98: ormazabal
D99: 58000 | G99: manteca | K99: batidora | L99: 1000 U$S
B100: 7800 | G100: pila megafono | K100: mixer
F101: 6000 | G101: prensa francesa
F102: 198 | G102: fp
A110: MIERCOLES 11 | B110: 56300 | G110: edu | H110: 150 | I110: h
B111: 20686.92 | G111: la serenisima
F112: 4900 | G112: sole limpieza
B113: 33931.11 | G113: milkaut
D114: 62920 | G114: dristi LJ
F115: 3770 | G115: aceite de coco
B116: 20449 | G116: wraps
F117: 561 | G117: esponja acero
A128: JUEVES 12 | B128: 58750 | G128: huevo | H128: =92.5+13 -> 105.5
F129: 191.76 | G129: puerro
B130: 27080 | G130: harina
B131: 39352.68 | G131: cuyaires
B132: 9885.45 | G132: horeca
B133: 17288.14 | G133: criollo
A143: VIERNES 13 | B143: 40241.22 | G143: la serenisima | H143: 110
B144: 22800 | G144: oliva
F145: 5836.9 | G145: suprema
B146: =13600-2400-700 -> 10500 | G146: edu
C147: 55094.9 | G147: matiz
B148: 37748.56 | G148: coca
A158: SABADO 14 | B158: 20000 | G158: gilda | H158: 97 | I158: h
B159: 75000 | G159: pollo
B160: 5268.2 | G160: brie
C161: =80197.6+29824.08 -> 110021.68 | G161: quintela
B162: 109531.87 | G162: marilu
D163: 72418.5 | E163: si | G163: motobaires
A168: LUNES 16
A183: MARTES 17 | B183: 54500 | G183: edu | H183: 142 | I183: H
B184: 16606.39 | G184: colorantes
A199: MIERCOLES 18 | H199: 12 | I199: mas 120 q se uso para alq
C200: 54788.56 | G200: ormazabal
D201: 20171.3 | G201: horeca
D202: 88008.5 | G202: el criollo
B203: 21721.21 | G203: la serenisima
F204: 7400 | G204: sole limpieza
F205: 544 | G205: limpiavidrios
F206: 1800 | G206: yogur
D207: 246840 | G207: penguin
B208: 48279 | G208: wraps
A214: JUEVES 19 | F214: 1250 | G214: champi | H214: 134.5
C215: 53115.95 | G215: matiz
B216: 29693.37 | G216: milkaut
B217: 29370 | G217: harina del rosario
B218: 17110 | G218: breik hoja de carta papel
A226: VIERNES 20 | B226: 75000 | G226: pollo | H226: 95 | I226: mas 40 q se uso para alq
B227: 14480.8 | G227: la serenisima
F228: 595 | G228: morron
B229: 34100 | G229: edu
F230: 7400 | G230: dai limpieza
D231: 70948.76 | G231: marilu
...

Sheet NOVIEMBRE 2023
A1: 7 | B1: MP | C1: CHEQUE | D1: TRANSFERENCIA | E1: ADEUDA | F1: GASTOS EN EFT | H1: RETIROS
F2: 7400 | G2: SOLE limpieza | H2: 164 | I2: H
A3: MIERC 1 | B3: 32400 | G3: edu
B4: 20604.17 | G4: la serenisima
C5: 41283.46 | G5: ormazabal
D6: 54585.87 | G6: valot
B7: 160083 | G7: motofeca
A15: JUE 2 | F15: =970+890 -> 1860 | G15: fp | H15: =90+34 -> 124
B16: 39450 | G16: harina del rosario
A28: VIE 3 | F28: 7400 | G28: dai limp | H28: 120
B29: 10200 | G29: edu
B30: 15204.8 | G30: la serenisima
C31: 99641.75 | G31: matiz
D32: 107145.5 | G32: baires
B42: 6295.7 | G42: BRIE | H42: 120
B43: 50667.98 | G43: milkaut
A44: SAB 4 | D44: 65138.4 | G44: marilu
B45: 75000 | G45: pollo
B46: 23500 | G46: huevo
C47: =102873.6+50933.74 -> 153807.34 | G47: quintela
D48: 170000 | G48: laurimar
A54: LU 6 | F54: 7400 | G54: dai limpieza | H54: 130
B55: 15204.8 | G55: la serenisima
B56: 69500 | G56: edu
B57: 25400 | G57: alpino pins bco
A68: MA 7 | F68: 2839 | G68: moto contadora | H68: 127 | I68: C
B69: 23667 | G69: pulpa frutilla
B70: 9943 | G70: choco alp negro
F71: 10800 | G71: fumigador
A80: MIE 8 | B80: 58000 | G80: manteca | H80: 148.5
B81: 27900 | G81: edu
B82: 15204.8 | G82: la serenisima
C83: 157235.49 | G83: ormzabal
F84: 916 | G84: yogur
F85: 3600 | G85: hielo
F86: 29925 | G86: wraps
D87: 213444 | E87: pagado | G87: motofeca
B88: 19320 | G88: colorantes
A96: JUE 9 | F96: 813 | G96: fp | H96: 106
B97: 18000 | G97: harina | I97: adelante 10000 a cecimp
K99: batidora | L99: 1000 U$S
K100: mixer
A110: VIE 10 | B110: 27600 | E110: pagado | G110: aceite fereidora | H110: 40 | I110: me fui a las 15
B111: 24000 | E111: pagado | G111: huevo
D112: 75000 | E112: pagado | G112: pollo
B113: 35349.18 | E113: pagado | G113: la serenisima
B114: 16900 | E114: pagado | G114: edu
F115: 7400 | G115: dai limpieza
D116: 78950 | E116: pagado | G116: distri LJ
C117: 99601.5 | G117: MATIZ
B118: 27324.86 | E118: pagado | G118: Marilu
B119: 43603.3 | E119: pagado | G119: feras
F120: 1400 | G120: curitas
A128: SAB 11 | D128: 50746 | G128: vero ianovsky | H128: 111
B129: 50667.98 | G129: milkaut | I129: adelante a ceci 20000 , en total fueron 30
F130: =1670+4338.46 -> 6008.46 | G130: fp | I130: se compenso con hernan
B131: 97411.28 | G131: coca
F132: 1000 | G132: panceta
F133: =877+3615.38 -> 4492.38 | G133: fp
A143: LU 13 | B143: 23947.56 | G143: la serenisima | H143: 170 | I143: H
C144: =7312.03+89215.96+36287.12 -> 132815.11 | G144: quintela
F145: 7400 | G145: dai limpieza
B146: 71900 | G146: edu
A158: MA 14 | D158: 50000 | G158: pollo | H158: 106 | I158: H
F159: 6816 | G159: pollo
D160: =69002.03+8459.39 -> 77461.42 | G160: cuyaires
G161: cuyaires
D162: 50746 | G162: honorarios Vero acuerdo tachella
H164: =46+50+50 -> 146 | I164: deposite a bbva y me transferi a cecimp
A168: MIE 15 | B168: 29162.71 | G168: la serenisima | H168: 90 | I168: H
B169: 28800 | G169: edu
D170: 90333.53 | G170: ormazabal
B171: 29599.99 | G171: syrups
A183: JUE 16 | B183: 32966.06 | G183: criollo | H183: 154 | I183: C
B184: 4707.99 | G184: horeca
B185: 37500 | G185: harina
D186: 72368.21 | G186: marilu
B187: 24000 | G187: huevo
F188: 3600 | G188: hielo
A199: VIE 17 | D199: 58000 | G199: manteca
D200: 70200 | G200: edu
D201: 75000 | G201: pollo
B202: 53110.28 | G202: la serenisima
F203: 7400 | G203: dai limpieza
C204: 30008 | G204: matiz
D205: 129394.32 | G205: escribana
F206: 3440 | G206: aceite de coco
A214: SAB 18 | B214: 6215.5 | G214: brie | H214: 142
C215: 66945.07 | G215: quintela
B216: 111107.64 | G216: milkaut
A226: LU 20 | B226: 14000 | G226: lana navidad | H226: 80
A241: MA 21 | B241: 41624 | G241: wraps | H241: =45.5+20.5 -> 66 | I241: H
B242: 1018 | F242: =2111.67+1048 -> 3159.67 | G242: fp | I242: se usaron 60 par alquiler
D243: 75000 | E243: debe factura a | G243: pollo
B244: 27700 | G244: choco alpino negro
B245: 61235.11 | G245: femsa coca
D246: 104362.5 | G246: motobaires
B248: 9119.4 | G248: sprinkles
B249: 5070 | G249: delantales
A255: MIE 22 | C255: 146268.13 | G255: ormazabal | H255: 35 | I255: 100 Alquiler
...

Sheet DICIEMBRE 2023
B1: MP | C1: CHEQUE | D1: TRANSFERENCIA | E1: ADEUDA | F1: GASTOS EN EFT | H1: RETIROS
C2: 69428 | G2: matiz | H2: =70-60+40+16.5 -> 66.5 | I2: -mARY
A3: VIE 1 | B3: 17880.67 | G3: la serenisima
F4: 7400 | G4: dai
A15: SAB 2 | F15: 3596 | G15: fp palta | H15: 78.5
B16: 37947.92 | G16: milkaut
G17: transferi mio a bbva 162 (con eso pague comafi 131)
G18: y 30625,67 transferi a mi mp
A28: LU 4 | D28: 78000 | E28: pagado | G28: pollo | H28: 162
B29: 35555.02 | G29: la serenisima
B30: 24000 | E30: pagado | G30: huev0
B31: 88200 | E31: pagado | G31: edu
C32: =94409.04+99620.51 -> 194029.55 | G32: quintela
F33: 7400 | G33: dai limpieza
D34: 100000 | G34: laurimar
B35: 28645 | G35: choco alpino bco
G36: transferi a bbva 120000 mio y lo pase a cecimp
C42: 74152.05 | G42: ORMAZABAL | H42: 190
F43: 654 | G43: carrefour
A44: MA 5 | D44: 41624 | G44: wraps
A54: MIE 6 | F54: 5550 | G54: sole | H54: 110
B55: 65731.37 | G55: milkaut
F56: 1210 | G56: chino
B57: 77018.7 | G57: disam
B58: 64316.57 | G58: coca
D59: 94622 | G59: motobaires
F60: 800 | G60: chinches
F61: 600 | G61: octagon
F62: 631 | G62: mostaza
D63: 172338.82 | E63: pagado | G63: motofeca
A68: JUE 7 | D68: 36300 | E68: PAGADO | G68: harina del rosario | H68: 130
B69: 17880.67 | G69: la serenisima
B70: 91900 | E70: SI | G70: edu | I70: use 24700 de r2mp y comprense con hernan
D71: 79570 | E71: pagado | G71: distri lj
C72: 126102.4 | E72: pagado | G72: matiz
D73: 37285.39 | E73: pagado | G73: criollo
D74: 25443.61 | E74: pagado | G74: horeca
F75: 8300 | G75: adelanto feriado cristian cocina
A80: VIE 8
A96: SAB 9 | F96: =773+2385 -> 3158 | G96: manteca | H96: 80
B97: 78000 | E97: pagado | G97: pollo
B98: 6408.4 | G98: brie
K99: batidora | L99: 1000 U$S
K100: mixer
A110: LU 11 | F110: 8300 | G110: dai limpieza | H110: 100
B111: 50000 | E111: PAGADO | G111: edu
B112: 24000 | E112: pagado | G112: huevo
B113: 22761.68 | G113: la serenisima
C114: 106972.32 | E114: pagado | G114: quintela
F115: 4400 | G115: hielo
D116: 73000 | E116: pagado | G116: manteca
A128: MA 12 | D128: 75891.08 | E128: pagado | G128: marilu | H128: 140
D129: 100000 | G129: laurimar | I129: Deposite en bbva 134k mio y lo transferi a cecimp
B130: 22600 | G130: pulpa frutilla
B131: 13420.48 | G131: Colorante y colormix
A143: MIE 13 | B143: 46000 | E143: pagado | G143: aceite freidora | H143: 110
B144: 91308.49 | E144: pagado | G144: criollo
B145: 18390.26 | E145: pagado | G145: horeca
B146: 54486.51 | G146: coca
B147: 28550 | E147: pagado | G147: edu
B148: 22761.68 | G148: la serenisima
F149: 7400 | G149: sole limpieza
F150: 1000 | G150: hilo encerado
C151: 137011.6 | E151: pagado | G151: ormazabal
D152: 177870 | E152: pagado | G152: motofeca
D153: 87000 | E153: pagado | G153: pollo
F154: 5550 | G154: sole limpieza
A158: JUE 14 | B158: 53600 | G158: harina del rosario | H158: 150
B159: 83248 | G159: wraps
A168: VIE 15 | D168: 24000 | G168: edu | H168: 150
B169: 19997 | G169: nuevo emporio crema
F170: 7400 | G170: dai limpieza
B171: 17880.67 | G171: la serenisima
F172: 654 | G172: filtro cafe
A183: SAB 16 | D183: 107629.54 | G183: milkaut | H183: 90
I184: transferi 60 a cecimp y de ahi a arthurmp para pagar milkaut xq no se llegaba
A199: LU 18 | F199: 7400 | G199: dai limpieza | H199: 137
C200: 149287.39 | G200: quintela | I200: deposite en bbva 117k mio y lo transferi a cecimp
B201: =114750-63000 -> 51750 | G201: edu
F202: 2890 | G202: maple huevo
D203: 102000 | G203: pollo
B204: 30606.82 | G204: la serenisima
C205: 153089.1 | G205: matiz
B206: 31000 | G206: huevo
A214: MA 19 | B214: 40592.57 | G214: criollo | H214: 220
B215: 22817.29 | G215: horeca
D216: 37900.61 | G216: valot
D217: 99495.9 | E217: pagado | G217: cuyaires
F218: 3200 | G218: hielo
D219: 73000 | E219: pagado | G219: manteca
A226: MIE 20 | B226: 29150 | E226: pagado | G226: edu | H226: 158
C227: 254120.23 | G227: ormazabal
D228: 160083 | E228: pagado | G228: motofeca
F229: 7400 | G229: sole
D230: =98930+43420 -> 142350 | E230: pagado | G230: distrib LJ
B231: 45439.24 | G231: milkaut
A241: JUE21 | D241: 82156.08 | G241: MARILU | H241: =55+80 -> 135
D242: 108000 | E242: pagado | G242: POLLO
A255: VIE 22 | B255: 34600 | G255: edu | H255: =60 -> 60
F256: 7400 | G256: dai
...

Sheet ENERO 2024
B1: MP | C1: CHEQUE | D1: TRANSFERENCIA | F1: GASTOS EN EFT | H1: RETIROS
A2: MA 2 | C2: 86737.2 | G2: ormzabal | H2: 150
B3: 31000 | E3: pagado | G3: huevo
F4: 1360 | G4: fp
C5: =113926.51+34823.8 -> 148750.31 | G5: quintela
B6: 40700 | E6: pagado | G6: harina del rosario
D7: 87771.37 | E7: pagado | G7: criollo
D8: 118510.13 | E8: pagado | G8: horeca
A15: MIE 3 | F15: 13000 | G15: 2 Luces TUBO cocina | H15: 100
B16: 20000 | G16: Cortinero
F17: 2255 | G17: frutas premium | I17: Ceci uso 105 de bbva y repuso 93 en la cuenta resta 13
B18: 48000 | E18: pagado | G18: edu
D19: 114000 | E19: pagado | G19: pollo
B20: 33555.11 | G20: la serenisima
B21: 75478.92 | G21: milkaut
F29: 1990 | G29: fp | H29: 180
D30: 18580 | G30: distri lj
A31: JUE 4 | D31: 152400 | G31: key digital
B32: 34420 | G32: choco alpino negro
G33: pulpa frutilla consul cris
A41: VIE 5 | B41: 27150 | G41: edu
B42: 33289.37 | G42: la serenisima
F43: 9600 | G43: dai limpieza
B44: 121190.81 | G44: coca
B45: 8270 | G45: pulpa frutilla
F46: 6400 | G46: hielo
A55: SAB 6 | B55: 11236.2 | G55: brie | H55: =60 -> 60 | I55: se uso 22,5 sueldo cris
B56: 31000 | G56: huevo
A67: LU 8 | F67: 720 | G67: Esponjas | H67: 126
F68: 9400 | G68: Limpieza
C69: 105439.14 | E69: pagado | G69: quintela
B70: 38100 | E70: pagado | G70: edu
B71: 114000 | E71: pagado | G71: pollo
B72: 23030.41 | G72: la serenisima
A83: MA 9 | F83: 1900 | G83: tutto farra | H83: =50+107 -> 157
F84: 1200 | G84: garbanzo
C85: 82953.4 | E85: pagado | G85: matiz
D86: 62975.5 | G86: valot | K86: batidora | L86: 1000 U$S
D87: 101004.75 | E87: pagado | G87: motobaires | K87: mixer
D88: 12520 | G88: colorante
B89: 6800 | G89: JUGUERITA
F90: 6500 | G90: Luz Fabrica
A97: MIE 10 | B97: =32450-3500 -> 28950 | G97: edu | H97: =110+23 -> 133
F98: 1500 | G98: gelatina
F99: 2400 | G99: delicia
B100: 15498 | G100: la serenisima
C101: 485103.5 | G101: ormazabal
B102: 86502.66 | G102: milkaut
B103: 47173.91 | E103: pagado | G103: marilu
F104: 9600 | G104: soloe limpieza
A115: JUE 11 | B115: 54111.2 | E115: Pagado | G115: tacos wraps | H115: 90 | I115: hernan puso 100k y se le devolvio el mismo dia
D116: 108780 | E116: pagado | G116: distri lj
D117: 74619.49 | E117: Pagado | G117: cuyaires
D118: 73000 | E118: Pagado | G118: manteca
A130: VIE 12 | B130: 34200 | G130: edu | H130: 100 | I130: ceci deposito enbbva 248500 y use 320, debo71500
B131: 23030.41 | G131: la serenisima
A145: SAB 13 | B145: 31000 | G145: huevo | H145: 90
A155: LU 15 | C155: =153365.73+85110.8 -> 238476.53 | E155: pagado | G155: quintela | H155: 124
B156: 111000 | E156: pagado | G156: pollo
B157: =50700-1600 -> 49100 | E157: pagado | G157: edu menos banana
B158: 44804.58 | G158: la serenisima
C159: 93357.9 | E159: pagado | G159: matiz
F160: 9400 | G160: dai limpieza
F161: 6400 | G161: hielo
A170: MA 16 | D170: 298870 | E170: pagado | G170: motofeca | H170: 116.5
D171: 23917.2 | E171: pagado | G171: horeca
D172: 83085.22 | E172: pagado | G172: criollo
B173: 51600 | E173: pagado | G173: harina
A186: MIE 17 | B186: 25650 | E186: pagado | G186: edu | H186: =90+57.5 -> 147.5
B187: 129336.66 | G187: milkaut
F188: 9600 | G188: sole limpieza
A201: JUE 18 | B201: 50681.4 | G201: marilu | H201: 122
A213: VIE 19 | F213: 2450 | G213: brie | H213: 114
F214: 450 | G214: rucula
B215: 31000 | G215: huevo
B216: 42000 | E216: pagado | G216: aceite freidora
F217: 3910 | G217: banana
A228: SAB 20 | D228: 110000 | G228: pollo | H228: 141
F229: 3200 | G229: hielo
B230: 34007.8 | G230: brie
F231: 5000 | G231: karen 8hs extra semana anterior (vie y sab)
A242: LU22 | D242: 48840 | G242: syrups | H242: 108
B243: =26485.08+46438.48 -> 72923.56 | F243: 985 | G243: la serenisima
F244: 891.45 | G244: berenjena
C245: =99103.54+27192.37 -> 126295.91 | G245: quintela
B246: =117500-45000-1000 -> 71500 | G246: edu
A257: MA 23 | D257: 112530 | E257: pagado | G257: motobaires | H257: 166
B258: 102200 | E258: pagado | G258: manteca
C259: 94766.1 | G259: matiz
B260: 70111.6 | E260: pagado | G260: criollo
B261: 18616.85 | E261: pagado | G261: horeca
B262: 66500 | E262: pagado | G262: harina
D263: 151979.21 | G263: coca femsa
B264: 12924 | G264: colorante red x 2
F265: 4563 | G265: fp
F266: 1550 | G266: film
A270: MIE 24 | F270: 1325 | G270: lavandina | H270: 104
F271: 9600 | G271: sole limpieza
B272: 26485.08 | G272: la serenisima
B273: 79900 | G273: edu
...

Sheet FEBRERO 2024
B1: MP | C1: CHEQUE | D1: TRANSFERENCIA | F1: GASTOS EN EFT | H1: RETIROS
A2: JUE 1 | B2: 24689 | G2: Choco bco pins alpino x 3k | H2: 80
B3: 31000 | G3: huevo
B4: 51200 | G4: harina
D5: 102000 | E5: pagado | G5: manteca
B6: 21667.2 | G6: brie
A15: VIE 2 | B15: 20700 | G15: edu
F16: 3200 | G16: hielo
B17: 13242.54 | G17: la serenisima
B29: 91448.74 | G29: milkaut | H29: 84
B30: 40000 | G30: leo faltaba de sus vacaciones
A31: SAB 3 | F31: 5000 | G31: me faltaba a mi para completar repartija
A41: LU 5 | B41: 111000 | G41: pollo | H41: 150
B42: 44250 | G42: edu
F43: 1500 | G43: costa
F44: 1400 | G44: esponja
C45: 101657.85 | G45: quintela
A55: MA 6 | C55: 104285.4 | G55: matiz | H55: 156
B56: 34784.58 | G56: horeca
B57: 38548.14 | G57: criollo
D58: 157129.56 | G58: coca
B59: 12360.51 | G59: colorante rojo
A67: MIE 7 | F67: 3200 | G67: HIelo | H67: 180
F68: 10600 | G68: sole limpieza
B69: 68800 | E69: pagado | G69: edu
F70: 5560 | G70: prod limpieza
F71: 1200 | G71: tutto farra
F72: 3430 | G72: banana
C73: 192528.38 | G73: ormazabal
B74: 339707.5 | E74: pagado | G74: motofeca
A83: JUE 8 | D83: 156674.4 | E83: pagado | G83: gonzanio | H83: 180
B84: 135036 | E84: pagado | G84: motobaires
B85: 73121.55 | E85: pagado | G85: marilu
B86: 51500 | E86: pagado | G86: harina | K86: batidora | L86: 1000 U$S
B87: 32000 | E87: pagado | G87: huevo | K87: mixer
A97: VIE 9 | B97: 39422.02 | G97: la serenisima | H97: 139
B98: 47900 | E98: pagado | G98: EDU
A115: SAB 10 | B115: 111000 | G115: pollo | H115: =120+11 -> 131 | I115: 16hs
C116: 122706.1 | G116: quintela
F117: 1800 | G117: hielo
F118: 5000 | G118: horas extra cris cocina | I118: 153825 use bbva (deposite en ef 93 el 14/2)
B119: 50000 | G119: marcelo materiales | I119: y puse 60825 en ef el17/2 cuando le pagamos a cristian barra
I121: saldado
A130: LU 12 | F130: 4115 | G130: banana | H130: 80
A145: MA 13 | F145: 2865 | G145: banana | H145: 100
A155: MIE 14 | B155: 84800 | G155: edu | H155: =182+40 -> 222
B156: 68743.15 | G156: coca
B157: 24688 | G157: choco alpino bco x 3k
B158: 12364 | G158: colorante rojo
F159: 7000 | G159: hielo
A170: JUE 15 | B170: 51000 | G170: huevo | H170: 106
F171: 10188 | G171: leche
D172: 43206.67 | G172: valot
C173: 116374.9 | G173: ormazabal
B174: 102200 | G174: manteca
A186: VIE 16 | B186: 105222 | G186: la serenisima | H186: 91
F187: 3400 | G187: nueces
F188: 9600 | G188: sole limpieza
B189: 14300 | E189: pagado | G189: edu
C190: =111260.41+120398.97 -> 231659.38 | G190: quintela
D191: 99690 | E191: pagado | G191: LJ limpieza
C192: 130324.39 | G192: Matiz
A201: SAB 17 | F201: 6870 | G201: fp | H201: 155.5 | I201: 240 ef h
B202: 132755.63 | G202: milkaut | I202: 240 bbva C
B203: 42796.93 | E203: pagado | G203: horeca | I203: (use los 240 y debo 32)
B204: 50547.63 | E204: pagado | G204: criollo
B205: 70000 | G205: Marcelo
A213: LU 19 | B213: 42000 | E213: pagado | G213: almafuerte | H213: 90
F214: 3978 | G214: fp
B215: =125600-7000-2400-2400 -> 113800 | E215: pagado | G215: edu
F216: 12000 | G216: sole
F217: 6356 | G217: fp
B218: 15228.87 | G218: la serenisima
D219: 92877.91 | E219: pagado | G219: marilu
A228: MA 20 | D228: 111000 | E228: pagado | G228: pollo | H228: 175
D229: 120879 | E229: pagado | G229: motobaires
A242: MIE 21 | C242: 51457.11 | G242: ormazabal | H242: 173
B243: 15900 | G243: edu
B244: 37679.35 | G244: la serenisima
F245: 5070 | G245: fp
D246: 78716.68 | G246: coca
B247: 13380 | G247: colorante red x 2
B248: 11620 | G248: breik
F250: 2085 | G250: leche alm
D251: 339707.5 | E251: pagado | G251: motofeca
A257: JUE 22 | F257: 2095 | G257: leche alm | H257: 100
D258: 54111.2 | G258: wraps
D259: 27800 | G259: harina
F260: 2000 | G260: uber
B261: 168964.18 | E261: pagado | G261: cuyaires
A270: VIE 23 | B270: 68100 | E270: pagado | G270: edu | H270: 100
B271: 30382.24 | G271: la serenisima
F272: 6760 | G272: espinaca fp
B273: 77018.5 | G273: iceferas
A286: SAB 24 | F286: =5070+4378 -> 9448 | G286: fp | H286: 190
C287: 131028.12 | G287: matiz
B288: 99093.64 | G288: milkaut
A301: LU 26 | B301: =62000-10000-1500-1800 -> 48700 | E301: pagado | G301: edu | H301: =73+21 -> 94
F302: =2394+8940+4380 -> 15714 | G302: fp
B303: 40000 | E303: pagado | G303: huevo
...

Sheet MARZO 2024
B1: MP | C1: CHEQUE | D1: TRANSFERENCIA | F1: GASTOS EN EFT | H1: RETIROS
A2: VIE 1 | B2: 114000 | E2: pagado | G2: pollo
B3: 60000 | E3: pagado | G3: huevo
B4: 109100 | E4: pagado | G4: edu
B5: 27942.7 | G5: la serenisima
D6: =98360+62190 -> 160550 | E6: pagado | G6: distri lj
A13: SAB 2 | B13: 81373.86 | G13: MILKAUT | H13: 90
F15: 18000 | G15: premio y hs extra rodri
F27: 9600 | G27: dai limpieza | H27: 64
F28: 4700 | G28: marcadores pizarra
A29: LU 4 | C29: 78143 | G29: quintela
B30: 34622.22 | G30: la serenisima
C31: 168109.8 | G31: matiz
B32: 80300 | E32: pagado | G32: edu
B33: 8200 | G33: resma de hojas
A39: MA 5 | B39: 36300 | G39: harina | H39: 146
F40: 1700 | G40: vino bco
B41: 3166 | G41: uber a contadora
B42: 15000 | G42: microfibas trapo
B43: 102200 | E43: pagado | G43: manteca
A53: MIE 6 | F53: 8400 | G53: sole limpieza | H53: 120
B54: 63020 | E54: pagado | G54: edu sin lechuga morada
B55: 92736.95 | E55: pagado | G55: marilu
B56: 43830.42 | G56: la serenisima
C57: 240979.29 | G57: ormazabal
B58: 19666.93 | G58: horeca
B59: 60674.5 | G59: criollo
A65: JUE 7 | F65: 13000 | G65: lampara | H65: 150
F66: 2881.26 | G66: levhuga
B67: 114000 | E67: pagado | G67: pollo
A81: VIE 8 | B81: 47542 | G81: la serenisima | H81: =80+43 -> 123
B82: 42000 | E82: pagado | G82: aceite freidora
B83: 98751.04 | G83: coca
B84: 46600 | E84: pagado | G84: edu | K84: batidora | L84: 1000 U$S
B85: 66000 | E85: pagado | G85: huevo | K85: mixer
A95: SAB 9 | B95: 128909.92 | G95: milkaut | H95: 110
C96: 239292.72 | G96: quintela | H96: -50 | I96: lucho
H97: 60 | I97: resta
A113: LU 11 | F113: 10800 | G113: dai limpieza | H113: 100
F114: 2600 | G114: marcador tiza
B115: 150300 | E115: pagado | G115: edu
B116: 35264.39 | G116: la serenisima
C117: =70421+70024.5 -> 140445.5 | E117: pagado | G117: matiz
A128: MA 12 | D128: 246175.57 | E128: pagado | G128: cuyaires | H128: 150
B129: 64500 | E129: pagado | G129: harina
B130: 13379 | G130: colorante red
B131: 41198 | G131: choco alpino 3kbco y 3k negro
A143: MIE 13 | C143: 121500.14 | E143: pagado | G143: ormazabal | H143: 100
D144: 96791.52 | E144: pagado | G144: marilu
B145: 174409.69 | E145: pagado | G145: criollo
B146: 21542.45 | E146: pagado | G146: horeca
B147: 86000 | E147: pagado | G147: pollo
F148: 2926 | G148: fp
B149: 61000 | E149: pagado | G149: edu
B150: 30353.44 | G150: la serenisima
D151: 252890 | E151: pagada | G151: motofeca
A153: JUE 14 | F153: 10000 | G153: adelanto rodri | H153: 150
F154: 9600 | G154: sole
A168: VIE 15 | B168: 53514.05 | G168: la serenisima | H168: 134
B169: 56809.5 | E169: pagado | G169: tacos
F170: 2320.85 | G170: fp
F171: 7000 | G171: hielo
B172: 62800 | E172: pagado | G172: edu
B173: 79118 | G173: frutos rojos iceferas
F174: 3173.94 | G174: banana
A184: SAB 16 | G184: milkaut | H184: 118
B185: 15820.5 | G185: brie
F186: 1660 | G186: bolsas
F187: 4596 | G187: banana
C188: 100547.67 | E188: pagado | G188: quintela
B189: 53697.88 | G189: milkaut
A199: LU 18 | B199: 83100 | E199: pagado | G199: edu | H199: 178.5
B200: 43607.98 | G200: la serenisima
B201: 102200 | E201: pagado | G201: manteca
F202: 13500 | G202: dai
D203: 89543.92 | E203: pagado | G203: marilu
A211: MA 19 | F211: 2770 | G211: vino bco | H211: 150
F212: 3622.5 | G212: brocoli
C213: 139323.4 | E213: pagado | G213: matiz
B214: 69000 | E214: pagado | G214: huevo
C215: 97300 | G215: tati
C216: 46584 | G216: nuevo emporio
B217: 56809.5 | E217: pagado | G217: wraps
A226: MIE 20 | C226: 121259.62 | G226: ormazabal | H226: 150
D227: 187092.62 | E227: pagado | G227: marilu
D228: 146650 | E228: pagado | G228: distrib lj
B229: 35676.03 | G229: la serenisima
D230: 133889.75 | E230: pagado | G230: valot
B231: 111268 | G231: coca
B232: 61550 | E232: psgado | G232: edu
D233: =45140.5+14416.39 -> 59556.89 | E233: pagado | G233: horeca
D234: 69902.75 | E234: pagado | G234: criollo
A240: JUE 21 | B240: 46500 | E240: PAGADO | G240: harina | H240: 197
F241: 2046 | G241: brocoli
B242: 69000 | G242: cortinero
A255: VIE 22 | B255: 42000 | E255: PAGADO | G255: ACEITE ALMAFUERTE | H255: 70
F256: 9672.75 | G256: FP
B257: 48700 | E257: pagado | G257: EDU
B258: 30353.44 | G258: LA SERENISIMA
F259: 11760 | G259: breik
...

Sheet ABRIL 2024
B1: MP | C1: CHEQUE | D1: TRANSFERENCIA | F1: GASTOS EN EFT | H1: RETIROS
A2: LU 1 | G2: sab 30 | H2: 85
A13: MA 2 | F13: 6646.5 | G13: naranjas | H13: 60
F14: 4506 | G14: fp
F15: 7000 | G15: hielo
C16: 108926.17 | G16: quintela
B27: 144300 | E27: pagado | G27: EDU | H27: 83
C28: 79279.62 | G28: matiz
A29: MIE 3
A39: JUE 4 | B39: 69000 | E39: pagado | G39: huevo | H39: 180
C40: 129838.41 | G40: ormazabal
B41: 37400 | E41: pagado | G41: harina
C43: 133647.53 | E43: pagado | G43: marilu
A53: VIE 5 | B53: 51800 | E53: pagado | G53: edu | H53: 190
B54: 35839.8 | G54: brie
B55: 72614.64 | G55: la serenisima ( se pago boleta del 3 y del 5/4)
F56: 15000 | G56: dai limpieza
D57: 50000 | G57: liquidacion cristian nahuelcura Completada
D58: 13642.82 | G58: oficios manzanares pagados a socia de vero ianosky
A65: SAB 6 | D65: =75676.1+20571.79 -> 96247.89 | E65: pagado | G65: criollo | H65: 130
D66: 10501.07 | E66: pagado | G66: horeca
F67: 5800 | G67: hs extra karen
A81: LU 8 | B81: 151400 | E81: pagada | G81: EDU | H81: 200
F82: 13500 | G82: dai
F83: 4116.42 | G83: naranja
B84: 35586.93 | G84: la serenisima | L84: 1000 U$S
C85: 123141.32 | E85: pagado | G85: matiz
B86: 24500 | G86: tablita ñoquis
B87: 12141 | G87: colorante red y verde
B88: 50950 | G88: rolloa fiscales breik
A95: MA 9 | F95: 891 | G95: fp rucula | H95: 230
D96: =41942+68820.15 -> 110762.15 | E96: pagado | G96: criollo
D97: 80770.59 | E97: pagado | G97: horeca
B98: 69429.39 | E98: pagado | G98: cocA
F99: 19000 | G99: Luces
A113: MIE 10 | B113: 35586.93 | G113: la serenisima | H113: 174
D114: 164000 | E114: pagado | G114: manteca
D115: 93597.42 | E115: pagado | G115: marilu
D116: 72200 | E116: pagado | G116: distri LJ
F117: 12000 | G117: sole limpieza
B118: 78500 | E118: pagado | G118: edu
C119: 114247.57 | G119: ormazabal
D120: 227601 | E120: pagado | G120: motofeca
A128: JUE11 | B128: 46000 | E128: pagado | G128: huevo | H128: 172.5
F129: 2250 | G129: fp
B130: 37400 | E130: pagado | G130: harina
F131: 4000 | G131: envio syrups
B132: 27000 | G132: syrups
B134: 73758 | E134: pagado | G134: feras frutos rojos
A143: VIE 12 | C143: 145873.92 | G143: quintela | H143: 90
B144: 37027.71 | G144: la serenisima
B145: 79000 | E145: pagado | G145: edu
A153: SAB 13 | B153: 57951.73 | G153: milkaut | H153: 100 | I153: se uso todo para alq
B154: 17064.2 | G154: brie
D155: 160351.8 | E155: pagado | G155: marilu
A168: LU 15 | C168: 162219.75 | G168: matiz | H168: 120 | I168: se uso 50 alquiler
B169: 67286.64 | G169: la serenisima
B170: =158700-2400 -> 156300 | E170: pagado | G170: edu
F171: 891 | G171: fp, RUCULA
B172: 10750 | G172: TELEGRAMA JURKO CORREO ARG ON LINE
A184: MA 16 | B184: 46000 | E184: pagado | G184: huevo | H184: 160
F185: 891 | G185: fp
B186: 72075.19 | E186: pagado | G186: cuyaires | I186: deposite 81 en cuenta bbva para pago de tarjeta
B187: 79640 | E187: pagado | G187: choco alpino bco y negro 12k total
A199: MIE 17 | F199: 15000 | G199: sole limpieza | H199: 166.5
B200: 72180.82 | G200: coca
B201: 55400 | E201: pagado | G201: edu
C202: 131565.38 | E202: pagado | G202: ormazabal
B203: 37027.71 | G203: la serenisima
D204: 131787 | E204: pagado | G204: marilu
D205: 83120 | E205: pagado | G205: distri LJ
B206: 49852 | E206: pagado | G206: wraps
A211: JUE 18 | B211: 48400 | G211: harina | H211: 120
D212: 61718.85 | E212: pagado | G212: marilu
F213: 13160.35 | G213: ormazabal, en que metodo de pago fue?
B215: 23000 | G215: fumigador
A226: VIE 19 | B226: =37000-1500 -> 35500 | E226: pagado | G226: edu con cilantro descontado | H226: 112.5
F227: 2482 | G227: fp
B228: 35586.93 | G228: la serenisima | I228: Hernan se transfierio de mp 250k
B229: 8265 | G229: breik, cajas
B230: 13681 | G230: colorante red
F231: 13500 | G231: dai limpieza
F232: 10000 | G232: jarra de agua
A240: SAB 20 | F240: 5892.39 | G240: fp | H240: 90
B241: 75119.88 | G241: milkaut
D242: 164000 | E242: pagado | G242: manteca
A255: LU 22 | B255: 46000 | E255: pagado | G255: huevo | H255: 131.5
B256: 167700 | E256: pagado | G256: edu
C257: 165388.41 | G257: quintela
B258: 35586.93 | G258: la serenisima
D259: 98912.1 | E259: pagado | G259: marilu
F260: 12000 | G260: dai limpieza
A268: MA 23 | C268: 175335.92 | G268: ormazabal | H268: 164 | I268: hay 163,5
D269: 42113.82 | E269: pagado | G269: criollo
C270: 160605.74 | G270: matiz
D271: 70138.99 | E271: pagado | G271: horeca
A284: MIE 24 | B284: 56809.5 | E284: pagado | G284: Wraps | H284: 220
F285: 3689 | G285: prod limp
B286: 44857.78 | G286: la serenisima
D287: 42904.92 | E287: pagado | G287: marilu
...

Sheet MAYO 2024
B1: MP | C1: CHEQUE | D1: TRANSFERENCIA | F1: GASTOS EN EFT | H1: RETIROS
A2: JUE 2 | B2: 68528.61 | G2: la serenisima | H2: 211.5
B3: 46000 | E3: pagado | G3: huevo
F4: 3870 | G4: fp
C5: 64170 | E5: pagado | G5: matiz
D6: 148330 | E6: pagado | G6: distrib LJ
F7: 6990 | G7: carrefour
F16: 6461.2 | G16: fp | H16: 142 | I16: Sumar caja roja cambio de 200
F17: 3240 | G17: fp
A18: VIE 3 | B18: 21520.16 | G18: coca
F19: 12000 | G19: sole limpieza
A28: SAB 4 | F28: 4662 | G28: fp | H28: 90 | I28: habia 110
A42: LU 6 | B42: 3770 | G42: uber cafe | H42: 130 | I42: no esta
B43: 48369.4 | G43: la serenisima
C44: 101796.09 | G44: quintela
C45: 84031.2 | G45: matiz
D46: 296414.61 | E46: pagado | G46: marilu
D47: 303468 | E47: pagado | G47: motofeca
F48: 13000 | G48: dai limpieza
A54: MA 7 | B54: 46000 | G54: huevo | H54: 80 | I54: no esta
I55: deposite 898k en CA
B56: =172300-1100 -> 171200 | E56: pagado | G56: edu (sin cilantro)
D57: 48379.74 | E57: pagado | G57: criollo
D58: 42641.71 | E58: pagado | G58: horeca
C59: 104591.08 | G59: ormazabal
D60: 170000 | G60: honorarios vero ianovsky caso jurko
B61: 56809.5 | E61: pagado | G61: wraps
A70: MIE 8 | D70: 164000 | E70: pagado | G70: manteca | H70: 100 | I70: no esta
F71: 3500 | G71: hielo
F72: 12000 | G72: limpieza
F73: 30000 | G73: Uber | L73: 1000 U$S
F74: 3884.71 | G74: fp
B75: 98608.16 | G75: milkaut
B76: 34463.14 | G76: la serenisima
F77: 300000 | G77: Alquiler
A84: JUE 9 | D84: 81583.86 | E84: pagado | G84: cuyaires | H84: 115.5
F85: 8361 | G85: fp
B86: 3400 | G86: caja torta
F87: 15000 | G87: uber Marico
F88: 30000 | G88: uber Nhcura
B89: 42500 | G89: harina
A102: VIE 10 | B102: 21166.25 | G102: feras
B103: 47280 | G103: messian syrups | H103: 113
B104: 74700 | E104: pagado | G104: edu
B105: 87691.32 | G105: coca
F106: 4500 | G106: envio syrup
I114: 338,5 total
A117: SAB 11 | B117: 38977.7 | G117: brie | H117: 131.5
F118: 2229.12 | G118: fp
C119: 109053.32 | G119: matiz
B120: 18400 | G120: karen
A132: LU 13 | B132: 46000 | G132: aceite freidora | H132: 210
D133: 203836.08 | E133: pagado | G133: marilu
B134: 85760.19 | G134: la serenisima
C135: 209739.74 | G135: quintela
B136: 49990 | G136: choc alpino
B137: 91000 | E137: pagado | G137: edu
A142: MA 14 | B142: 46000 | E142: pagado | G142: huevo | H142: 160
D143: 70705.13 | E143: pagado | G143: criollo
D144: 19752.93 | E144: pagado | G144: horeca
D145: 45785 | G145: harina de almendra uriburu | I145: C uso 168737 del bbva
B146: 15861 | G146: colorante | I146: compensado con 160k que H se transf de mp
F147: 2200 | G147: fp
B148: 56809.5 | E148: pagado | G148: wraps
A157: MIE 15 | B157: 148500 | E157: pagado | G157: edu | H157: 130
B158: 34463.14 | G158: la serenisima
B159: 111544 | E159: pagado | G159: gonzanio
C160: 129760 | G160: ormazabal
F161: 9000 | G161: sole
F162: 3500 | G162: envio harina
D163: 303468 | E163: pagado | G163: motofeca
A173: JUE 16 | B173: 60100 | E173: pagado | G173: harina | H173: 140
B174: 35530 | G174: filtro psa
B175: 12240 | G175: cajas
A188: VIE 17 | B188: 151329.85 | G188: coca | H188: 90
B189: 6600 | G189: cajas
B190: 34463.14 | G190: la serenisima
C191: 96456.14 | G191: matiz
D192: 121250 | E192: pagado | G192: distri LJ
B193: 74000 | E193: pagado | G193: edu
B194: 20800 | G194: bazar
F195: 18000 | G195: dai limpieza
A200: SAB 18 | B200: 46000 | G200: huevo | H200: 160
C201: 72975.1 | G201: quintela
B202: 80002.69 | G202: milkaut
B203: 10000 | G203: karen
A215: LU 20 | F215: 16500 | G215: dai limpieza | H215: 100
B216: 51694.7 | G216: la serenisima
F217: 30000 | G217: Nafta y Repuestos
B218: 164000 | E218: pagado | G218: manteca
A229: MA 21 | B229: 103400 | E229: pagado | G229: edu | H229: 170
B230: 68358.47 | E230: pagado | G230: horeca
B231: 73729.5 | E231: pagado | G231: criollo
D232: 97378.44 | E232: pagado | G232: cuyaires
B233: 344930.78 | E233: pagado | G233: marilu
B234: 35791.8 | G234: duniapol
B235: 51500 | E235: pagado | G235: harina
B236: 15861.74 | G236: colorante
A244: MIE 22 | B244: =98200-2000-4000 -> 92200 | G244: edu sin verdeo y sin 1 cabutia | H244: 160
B245: 62436 | E245: pagado | G245: wraps
...

Sheet JUNIO 2024
B1: MP | C1: CHEQUE | D1: TRANSFERENCIA | F1: GASTOS EN EFT | H1: RETIROS
A2: SAB 1 | F2: 1926 | G2: levadura | H2: 130
D3: 311182.72 | E3: pagado | G3: marilu
C16: 172967.08 | G16: quintela | H16: 260
F17: 15000 | G17: dai
A18: LU 3 | B18: 39145.73 | G18: la serenisima
B19: 168400 | E19: pagado | G19: edu
D20: 180000 | G20: honorarios Ianovsky caso jurko | I20: use de bbva 285610, repuse en ef 230 y x transf 50
B21: 46000 | G21: aceite almafuerte
B22: 74587.5 | G22: frutos rojos
A28: MA 4 | F28: 6511.05 | G28: fp | H28: 158
D29: 43244.16 | E29: pagado | G29: criollo
D30: 31798.98 | E30: pagado | G30: horeca
B31: 46000 | G31: huevo
B32: 100000 | G32: bomba
A42: MIE 5 | B42: 39145.73 | G42: la serenisima | H42: 140
B43: 67273.29 | G43: milkaut
C44: 122906.72 | G44: ormazabal
B45: 78400 | E45: pagado | G45: edu (no vino zuchini)
D46: 421080 | E46: pagado | G46: motofeca
A54: JUE 6 | D54: 92996.97 | E54: pagado | G54: gonzanio | H54: 120
B55: 68250 | G55: harina
D56: 206097.71 | G56: coca
F57: 21000 | G57: SOLE limpieza
A70: VIE 7 | B70: 10700 | G70: costa
F71: 1583 | G71: lavandina
B72: 55000 | E72: pagado | G72: edu
B73: 39145.73 | G73: la serenisima | L73: 1000 U$S
D74: 315334 | E74: pagado | G74: marilu
B75: 36000 | G75: messian syrups
A84: SAB 8 | B84: 17589 | G84: brie | H84: 120
F85: 1845 | G85: panceta
D86: 164000 | E86: pagado | G86: manteca
C87: 191402.15 | G87: matiz
A102: LU 10 | D102: 250000 | G102: cuota 1 jurko | H102: 100 | I102: puse 30 | J102: me quede con 30
D103: 101423 | G103: conciliadora jurko | I103: 500 Alq
D104: 100000 | G104: abogada jurko
F105: 1280 | G105: fp
B106: 116500 | E106: pagado | G106: edu
F107: 18000 | G107: dai limpieza
F108: 2670 | G108: panceta
B109: 46000 | E109: pagado | G109: huevo
B110: 58266.91 | G110: la serenisima
C111: 110597.18 | E111: pagado | G111: quintela
A117: MA 11 | D117: 27961.91 | E117: pagado | G117: horeca | H117: 150
D118: 52244.26 | E118: pagado | G118: criollo
D119: 73402.29 | E119: pagado | G119: cuyaires
B120: 25000 | G120: breik
D121: 62436 | E121: pagado | G121: wraps
A132: MIE 12 | C132: 221666 | G132: ormazabal | H132: 146
B133: 48601.96 | G133: la serenisima
B134: 119933.28 | G134: milkaut
B135: 83300 | E135: pagado | G135: edu
B136: 18861 | G136: colorante rojo
B137: 45920 | G137: choco alpino
A142: JUE 13 | B142: 52000 | E142: pagado | G142: harina | H142: 140
F143: 3930 | G143: fp
F144: 3500 | G144: hielo
F145: rucula | G145: fp
A157: VIE 14 | F157: 15000 | G157: sole limpieza
F158: 4600 | G158: hielo
F159: 11327.58 | G159: fp
B160: 78291.46 | G160: la serenisima | I160: 150k se transf a Hernan
B161: 46000 | G161: HUEVO | I161: 150k uso lau de bbva
A173: SAB 15 | D173: 163762.41 | E173: pagado | G173: marilu | H173: 60 | I173: retiramos
H174: 90
A188: LU 17 | G188: CERRADO X FERIADO
A200: MA 18 | F200: 13500 | G200: dai | H200: 45
F201: 16850 | G201: fp
B202: 44948 | E202: pagado | G202: criollo
B203: 18582.15 | E203: pagado | G203: horeca
C204: 62063.32 | G204: quintela
C205: 279945.35 | G205: matiz
F206: 14000 | G206: horas de karen (semana anterior)
A215: MIE 19 | B215: 193300 | E215: pagado | G215: edu | H215: 170
D216: 148070 | E216: pagado | G216: distri LJ | I216: 70 retiro hernan
F217: 1600 | G217: vino?
B218: 38694.05 | G218: la serenisima
B219: 67273.29 | G219: milkaut
D220: 315810 | E220: pagado | G220: motofeca
A229: JUE 20 | B229: 50000 | G229: bomba | H229: 140
A244: VIE 21 | B244: 29029.08 | G244: la serenisima | H244: 210
B245: 52000 | G245: harina
B246: 164000 | E246: pagado | G246: manteca
B247: 123379.51 | G247: coca
B248: 37525 | G248: colorantes
F249: 9000 | G249: agustin
A257: SAB 22 | B257: 18880 | G257: brie | H257: 140
A273: LU 24 | F273: 17500 | G273: dai limpieza | H273: 190
B274: 92000 | E274: pagado | G274: edu
B275: 46000 | E275: pagado | G275: huevo
B276: 39145.73 | G276: la serenisima
A288: MA 25 | C288: =74452.51+3986.95 -> 78439.46 | G288: quintela | H288: 150
D289: 169584.32 | E289: pagado | G289: marilu | I289: 70k h H telecom
B290: 68607 | E290: pagado | G290: wraps | I290: 70k c
I291: compensado
A303: MIE 26 | B303: 88500 | E303: pagado | G303: edu | H303: 200
C304: 98456.87 | E304: listo | G304: ormazabal
B305: 14596.15 | E305: pagado | G305: criollo
B306: 39472.69 | E306: pagado | G306: horeca
...

Sheet JULIO 2024
B1: MP | C1: CHEQUE | D1: TRANSFERENCIA | F1: GASTOS EN EFT | H1: RETIROS
A2: LU 1 | B2: 120500 | E2: pagado | G2: EDU | H2: 145
C3: 154350.02 | G3: quintela
F4: 2500 | G4: auto lucho
B5: 38694.05 | G5: la serenisima
D6: 216932.07 | E6: pagado | G6: marilu
D7: 45785 | G7: harina de almendra
F8: 18000 | G8: dai limpieza
B16: 68607 | E16: pagado | G16: wraps | H16: 86
B17: =65799.05+44333.78 -> 110132.83 | E17: pagado | G17: criollo
A18: MA 2 | B18: 22106.6 | E18: pagado | G18: horeca
A28: MIE 3 | B28: 65600 | E28: pagado | G28: edu | H28: 160
D29: 46096.98 | E29: pagado | G29: cuyaires
D30: 421080 | E30: pagado | G30: motofeca
B31: 58718.59 | G31: la sernisima
C32: 192742.1 | G32: matiz
C33: 176519.26 | G33: ormzabal
A42: JUE 4 | B42: 48000 | E42: pagado | G42: harina | H42: 149
B43: 69600 | G43: oliva botellas
D44: 176000 | E44: pagado | G44: manteca
A54: VIE 5 | B54: 22492 | G54: tenedores | H54: 235
D55: 144370 | E55: pagado | G55: distribuidora lj
B56: 147152.99 | G56: coca femsa
D57: 200000 | G57: honorarios alcides rectificacion
B58: 45920 | G58: choco alpino
B59: 35280 | G59: colorante
B60: 39145.73 | G60: la serenisima
A70: SAB 6 | F70: 810 | G70: fp | H70: 223
F71: 20000 | G71: se usaron para sueldo karen
B72: 20670 | G72: brie
L73: 1000 U$S
A84: LU 8 | B84: =154000-3000 -> 151000 | E84: pagado | G84: edu vino 3 brocoli en lugar de 6 | H84: 170 | I84: DEPOSITE MIO 270 Y TRANSFERI A CECIMP
F85: 3500 | G85: hielo
B86: 46000 | E86: pagado | G86: huevo
B87: 39145.73 | G87: la serenisima
C88: 59617.91 | G88: quintela
D89: 242351.49 | E89: pagado | G89: marilu
F90: 18000 | G90: dai limpieza
A102: MA 9 | H102: 98
A117: MIE 10 | B117: 62979.18 | G117: la serenisima | H117: 220
C118: 64872.65 | G118: ormazabal
B119: 118500 | E119: pagado | G119: edu
B120: 115806.72 | E120: pagado | G120: criollo
B121: 52768.75 | E121: pagado | G121: horeca
B122: 68607 | E122: pagado | G122: wraps
A132: JUE 11 | B132: 67500 | E132: pagado | G132: harina | H132: 180
C133: 202873.9 | E133: listo | G133: matiz
D134: 130092.67 | E134: pagado | G134: gonzanio
F135: 2880 | G135: fp
A142: VIE 12 | F142: 5760 | G142: fp | H142: 100
B143: 58266.91 | G143: la serenisima
B144: 176000 | E144: pagado | G144: manteca
A157: SAB 13 | B157: 48000 | G157: huevo | H157: 212
B158: =41608.73+92519.31 -> 134128.04 | G158: milkaut
A173: LU 15 | B173: 102500 | E173: pagado | G173: edu | H173: 94.5
F174: 18000 | G174: dai
B175: 55048.69 | G175: la serenisima
D176: 205106.8 | E176: si | G176: marilu
F177: =41000+2400 -> 43400 | G177: pintureria
A188: MA 16 | C188: =45317.54+38291.17 -> 83608.71 | G188: quintela | H188: 134 | I188: transfer 350 h
B189: 30161.28 | G189: criollo | I189: transfer 350 c
B190: 50668.3 | G190: horeca
F191: 20000 | G191: marcelo
A200: MIE 17 | B200: 64497.56 | G200: la serenisima | H200: 180
D201: 19481 | G201: quintela (sumar ch sem q viene)
C202: 280857.19 | G202: ormazabal | I202: use 50k bbva y reintegre en ef
B203: 5400 | G203: impresion | I203: l
B204: 27000 | G204: messian
F205: 5000 | G205: envio syrup
B206: 102700 | E206: pagado | G206: edu
B207: 421080 | E207: pagado | G207: motofeca
F208: =6300+2400 -> 8700 | G208: pintureria
F209: 15000 | G209: ricota
B210: 220049.9 | G210: tubo de gas
A215: JUE 18 | C215: 204658.65 | G215: matiz | H215: 260
B216: 52100 | G216: harina
F217: 1600 | G217: bandeja torta
F218: 24000 | G218: ferreteria h
F219: 5000 | G219: grampas
F220: 22000 | G220: repuesto inodoro
G221: enduido ?
A229: VIE 19 | B229: 52800 | G229: choco alpino | H229: 207
B230: 26460 | G230: colorante rojo
B231: 36699.13 | G231: la serenisima
B233: 48000 | G233: huevo
F234: 5800 | G234: fp
F235: 20000 | G235: Marce
A244: SAB 20 | B244: 20800 | G244: brie | H244: 140
B245: 167644.66 | G245: milkaut | H245: 50 | I245: reintegró lau en ef xq uso del bbva
A257: LU 22 | B257: 185500 | E257: si | G257: edu | H257: 50
F258: 18000 | G258: dai limpieza
F259: 10000 | G259: trapos
F260: 1170 | G260: fp
C261: 146997.7 | G261: quintela
B262: 35699.13 | G262: la serenisima
F263: 30000 | G263: repuesto baño??
A273: MA 23 | D273: 16161.24 | G273: ferreteria | H273: 180
B274: 68607 | E274: pagado | G274: wraps
B275: 79560 | G275: iceferas
F276: 1600 | G276: costa
...

Sheet AGOSTO 2024
A1: ¿ | B1: MP | C1: CHEQUE | D1: TRANSFERENCIA | F1: GASTOS EN EFT | H1: RETIROS
A2: JUE 1 | F2: 1500 | G2: BIROMES | H2: 200
F3: 2340 | G3: fp
B4: 68000 | E4: pagado | G4: harina
F5: 25000 | G5: Arena cal cemento
F6: 5000 | G6: tutto farra
F16: 21000 | G16: DAI LIMPIEZA | H16: 177
B17: 60888.65 | G17: la serenisima
A18: VIE 2 | C18: 216749.9 | E18: pagado | G18: matiz
B19: 151732.77 | G19: milkaut debe nota de cred x crema
B20: 184000 | E20: pagado | G20: manteca
B21: 33800 | E21: pagado | G21: edu
F22: 8000 | G22: hielo (entra sab)
A28: SAB 3 | B28: 21330 | G28: brie | H28: 194
F29: 800 | G29: rucula
C30: 186514.24 | G30: quintela
D31: 254555.89 | E31: pagado | G31: marilu
A42: LU 5 | B42: 159000 | E42: si | G42: edu | H42: 180
B43: 48000 | G43: huevo | I43: use de bbva 217475,45
B44: 40907.1 | G44: la serenisima
F45: 23100 | G45: dai limpieza
B46: 4334 | G46: moto contadora
B47: 3626 | G47: moto contadora
A54: MA 6 | D54: 71350.6 | E54: pagado | G54: cuyaires | H54: 240
D55: 142727.38 | E55: pagado | G55: criollo
D56: 30638.71 | E56: pagado | G56: horeca
A70: MIE 7 | B70: 62500 | E70: pagado | G70: edu | H70: 270
B71: 65932.02 | G71: la serenisima
D72: 63570 | E72: pagado | G72: lj distribuidora
C73: 97858.71 | G73: ormazabal | L73: 1000 U$S
D74: 421080 | E74: pagado | G74: motofeca
B75: 4000 | G75: ricota
A84: JUE 8 | B84: 18000 | G84: messian | H84: 150
D85: 193189.45 | E85: Pagado | G85: gonzanio
B86: 67500 | G86: harina
F87: 5000 | G87: envio syrup
F88: 21000 | G88: daiana limpieza
A102: VIE 9 | H102: 180 | I102: saq 50k + 20bbva, compensado con lau
B105: 52500 | E105: pagado | G105: edu | I105: transfer 390 a herni bbva
B106: 40435.1 | G106: la serenisima
C107: 115100.8 | G107: matiz
A117: SAB 10 | D117: 96000 | E117: pagado | G117: huevo | H117: 300 | I117: -40H
D118: 174224.44 | E118: pagado | G118: marilu
B119: 23400 | G119: sorbetes
A132: LU 12 | B132: 76169.12 | G132: la serenisima | H132: 88
F133: 21000 | G133: dai limpieza | I133: pague 374k master de bbva y repuse en ef
C134: 84218.67 | G134: quintela
B135: 93800 | E135: pagado | G135: edu
D136: 63990 | G136: choco alpino
F137: 15000 | G137: (parte fac la serenisima)
F138: 2070 | G138: fp
F139: 20000 | G139: fabri extra medialunas itba
F140: 20000 | G140: Rodri extra medialunas itba
F141: 30000 | G141: Marcelo
D142: 18000 | G142: ferreteria
A143: MA 13 | B143: 90516.65 | G143: milkaut | H143: 143
F144: 2871 | G144: fp
D145: 184000 | E145: pagado | G145: manteca
B146: 148122.05 | G146: coca
A158: MIE 14 | C158: =16079.09+45247.68 -> 61326.77 | G158: ormazabal | H158: 150 | I158: -150H
B159: 104000 | E159: pagado | G159: edu
B160: 61360.66 | G160: la serenisima
D161: 505296 | E161: pagado | G161: motofeca
B162: 47989 | G162: colorantes
B163: 8000 | G163: ferreteria silicona
D164: 16834 | G164: ferreteria llaves alen
D165: =8850+8400 -> 17250 | G165: jujuy dia del niño
A174: JUE 15 | C174: 214216 | E174: listo | G174: matiz | H174: 230
B175: 77449.52 | G175: horeca
B176: 62877.93 | G176: criollo
B177: 83500 | G177: harina
A189: VIE 16 | B189: 39000 | E189: si | G189: edu | H189: 230
F190: 4800 | G190: pintureria
B191: 85913 | G191: la serenisima (debitar en prox fac leche alm)
C192: 250521.6 | E192: pagado | G192: marilu
D193: 157432.64 | G193: rex
A201: SAB 17 DOM 18 | B201: 22140 | G201: brie | I201: 216,5 SAB
F202: 35000 | G202: milagros | H202: 104 | I202: queda
F203: 58500 | G203: irene
F204: 19000 | G204: leo
H207: 150 | I207: DOM
A216: LU 19 | B216: 58639 | G216: la serenisima | H216: 100 | I216: 220
B217: 48000 | G217: huevo
B218: 114500 | E218: pagado | G218: edu
F219: 5000 | G219: bolsas residuos y cif
A230: MA 20 | B230: =83337.29 -> 83337.29 | G230: milkaut | H230: 60
B231: 90516.65 | G231: milkaut | I231: use 600k de bbva y repuse 300 | K231: compensado
D232: 220490 | E232: pagado | G232: distrib LJ | H232: -200 | I232: Alquiler
B233: 18233 | G233: pintura cobre
B234: 68607 | E234: pagado | G234: wraps
F235: 2100 | G235: marcadores pizarra mary
A245: MIE 21 | B245: 120000 | E245: pagado | G245: edu | H245: 176 | I245: 240
B246: 58115.5 | G246: la serenisima
C247: 168691.17 | G247: ormazabal
C248: =38573.23+159048.45 -> 197621.68 | G248: quintela
F249: 3350 | G249: ricota
A258: JUE 22 | D258: 229054.32 | E258: pagado | G258: marilu | H258: 108 | I258: 130
D259: 148185.67 | E259: pagado | G259: cuyaires
B260: 32000 | G260: harina
F261: 1710 | G261: espinaca
...

Sheet SEPTIEMBRE 2024
A1: . | B1: MP | C1: CHEQUE | D1: TRANSFERENCIA | F1: GASTOS EN EFT | H1: RETIROS
A2: LU 2 | B2: 61360.66 | G2: LA SERENISIMA | H2: 110
B3: 84000 | E3: pagado | G3: edu
F4: 30200 | G4: dai limpieza (con los 5 q se le debia del viernes)
D5: 184000 | E5: pagado | G5: manteca
G6: aceite freidora??
B7: 100000 | G7: marcelo (se le reintgro a hernan mp desde bbva)
B8: 63990 | G8: choco alpino
B9: 47600 | G9: almafuerte
B16: 68607 | E16: pagado | G16: wraps | H16: 170
C17: 97295.74 | G17: quintela | I17: transfer 500k hernan desde bbva
A18: MA 3 | B18: 265015.54 | E18: pagado | G18: marilu sin descuento
D19: 83500 | E19: pagado | G19: harina
A28: MIE 4 | B28: 65932 | G28: la serenisima | H28: 206
B29: 96000 | E29: pagado | G29: edu
C30: =165716.91+16079.09 -> 181796 | G30: ormazabal
B31: 82885 | G31: matafuegos atrlantida
D32: 400752 | E32: pagado | G32: motofeca
F33: 3400 | G33: ricota
A42: JUE 5 | F42: 4000 | G42: rolito | H42: 173
B43: 50000 | G43: huevo | I43: transfer 600k hernan desde bbva
F44: 2317.5 | G44: margarina
I45: transfer 50k ceci desde mp
A54: VIE 6 | F54: 3418 | G54: repollo | H54: 204
B55: 156500 | E55: si | G55: edu | I55: pago flow 110k hernan desde bbva
D56: 35043.36 | E56: pagado | G56: horeca
D57: 40393.63 | E57: pagado | G57: criollo
B58: 60888.65 | G58: la serenisima
C59: 215324 | E59: listo | G59: matiz
B60: 4720 | G60: uber contadora
B61: 172904 | G61: coca femsa
F62: 23100 | G62: dai limpieza
F63: 4725 | G63: prod limpieza
A70: SAB 7 DOM 8 | B70: 46545 | G70: brie | H70: 170
I71: COMPENSACION batidora hernan
I73: 1000 usd | J73: dolar hoy 1260 | K73: 1260000
I74: 45513 | J74: recupero | K74: 390000
H75: 140 | I75: 45538 | J75: recupero | K75: 500000
I76: 45540 | J76: recupero | K76: 600000
I77: 45541 | J77: recupero | K77: 110000
I78: diferencia | K78: =K73-K74-K75-K76-K77 -> -340000 | L78: a favor ceci
I79: 45542 | J79: compensacion | K79: 50000 | L79: mp
I80: 45545 | J80: compensacion | K80: 319390.28 | L80: bbva osde
J82: saldados | K82: 29000 | L82: a favor de hernan
A84: LU 9 | F84: 5150 | G84: breik marcadores | H84: 100
B85: 50000 | G85: huevo
B86: 51569.2 | G86: la serenisima
D87: 97590 | E87: pagado | G87: distib LJ
D88: 126985 | E88: pagado | G88: marilu
F89: 25200 | G89: dai limpieza
B90: 19582 | G90: colorante rojo
B91: 100000 | G91: marcelo pintor
B92: 115000 | E92: pagado | G92: edu
B93: 63990 | G93: choco alpino
A102: MA 10 | H102: 160
B105: 68607 | E105: pagado | G105: wraps
B106: 124490.7 | G106: milkaut
C107: =73523.85+75485.85+103660.7-9425.9 -> 243244.5 | G107: quintela
B108: 184000 | E108: pagado | G108: manteca
B109: 45750 | E109: pagado | G109: harina
A117: MIE 11 | B117: 75000 | E117: pagado | G117: edu | H117: 170
C118: 144986.98 | G118: ormazabal
D119: 338134.5 | E119: pagado | G119: motofeca
B120: 40907.1 | G120: la serenisima
D121: 44200 | G121: chapas
A132: JUE 12 | H132: 130
A143: VIE 13 | B143: 50000 | G143: huevo | H143: 220
B144: 87847.5 | G144: frutos rojos iceferas
F145: 2600 | G145: chorizo colorado catering hernan
D146: 219512.08 | E146: pagado | G146: marilu
B147: 40907.1 | G147: la serenisima
F148: 15000 | G148: lucho catering hernan (compensado)
B149: 95500 | E149: pagado | G149: edu
I150: 60 mp hernan
I151: 42 bbva ceci
I152: compensado
A158: SAB 14 DOM 15 | H158: 220 | I158: habia 300 le pague a seba de aca
H164: 240 | I164: domingo
A174: LU 16 | B174: 76881.81 | G174: la serenisima | H174: 130
C175: 207039.1 | G175: matiz
B176: 14776 | G176: sobre papas fritas | I176: 337k bbva Hernan
F177: 23100 | G177: dai limpieza | I177: 271113 bbva ceci (pago osde)
B178: 145000 | E178: si | G178: edu | I178: 214908 bbva ceci (mastercard)
D179: 71059.46 | G179: bashir platos | I179: 30000 uso ceci de mp (27/9)
B180: 13700 | G180: psa pieza | I180: 179021 a favor de hernan
F181: 2200 | G181: pilas balanza | I181: - 100000 mp hernan (24/9)
I183: resta 79k a favor de hernan
I184: compensado dia 5/10 x mp
A189: MA 17 | D189: =36386.76+64413.14 -> 100799.9 | G189: quintela | H189: 210
F190: 3183 | G190: pepino y acusai
B191: 80400 | G191: harina | I191: use 200k bbva y repuse en ef
B192: 35674 | G192: bashir platos
D193: 68607 | E193: pagado | G193: wraps fac 2422
A201: MIE 18 | B201: =75500-4500 -> 71000 | E201: si | G201: edu (no vino el brocoli) | H201: 230
F202: 3141 | G202: miel
F203: 1000 | G203: curitas
B204: 51569.2 | G204: la serenisima
D205: 269705.73 | E205: pagado | G205: marilu (sin dto)
C206: 143821.08 | G206: ormazabal
B207: 200000 | G207: Marcelo pintor
...

Sheet OCTUBRE 2024
A1: . | B1: MP | C1: CHEQUE | D1: TRANSFERENCIA | F1: GASTOS EN EFT | H1: RETIROS
A2: MA 1 | H2: 290
B16: =110000-6500 -> 103500 | E16: pagado | G16: edu (se devolvio lechuga) | H16: 35000 | I16: Adelanto Seba
C17: 112152.46 | G17: ormazabal | H17: 320
A18: MIE 2 | B18: 41243.36 | G18: la serenisima
B19: 38800 | G19: messian
B20: 155549.99 | G20: la redencion bebidas
F21: 2000 | G21: libreria
D22: 388470.5 | E22: pagado | G22: motofeca
D23: 37964.2 | G23: geobazar
B24: 32500 | G24: seña canastos cuchi
B25: 12667 | G25: sorbetes
B26: 27100 | G26: fumigador
A28: JUE 3 | B28: 8000 | G28: hielo | H28: 250
B29: 47600 | G29: almafuerte
A42: VIE 4 | B42: 123500 | E42: pagado | G42: edu | H42: 180
F43: 2990 | G43: bolsa consorcio | I43: deposite mio 800k para transferir a mi mp 640
B44: 53239.86 | G44: la serenisima | I44: y 160 a mastercard
C45: 214168.6 | G45: matiz
B46: 46800 | G46: harina
B47: 51356.66 | G47: milkaut
B48: 5268 | G48: moto contadora
B49: 100000 | G49: marcelo pintor
F50: 3400 | G50: bolsas
A54: SAB 5 DOM 6 | B54: 23925 | G54: brie | H54: 250 | I54: SAB
B55: 57000 | G55: huevo
D56: 262565.34 | E56: pagado | G56: marilu
H60: 70 | I60: DOM
A70: LU 7 | B70: =71000-4000 -> 67000 | E70: pagado | G70: edu (no vino banana) | H70: 220
F71: 3129 | G71: manteca
B72: 62587.2 | G72: la serenisima
B73: 57000 | E73: pagado | G73: huevo
C74: 152462.78 | G74: quintela
D75: 45785 | G75: uriburu (harina de alm)
B76: 97500 | G76: canastos bashir (falta fac a)
B77: 34400 | G77: tachos casa tati
A84: MA 8 | F84: 765 | G84: frutas premium rucula | H84: 300
C85: 49888.94 | G85: ormazabal
B86: 132748.51 | G86: cuyaires | I86: 330 a Hernan desde Bbva
B87: 47000 | G87: filtro psa santi | I87: 222951.33 Ceci pago Mastercard desd Bbva
D88: 218400 | E88: pagado | G88: Parada | I88: 43800 | J88: ceci bbva
I89: 4400 | J89: ceci bbva
I90: 36015 | J90: ceci bbva
I91: 22833 a favor de ceci
J92: compensado todo
A102: MIE 9 | H102: 290
B105: 68607 | E105: pagado | G105: wraps
B106: 126000 | E106: PAGADO | G106: edu
B107: 67250 | G107: la serenisima
B108: 14651.42 | G108: horeca
B109: 96479.5 | G109: criollo
D110: =186100+14400 -> 200500 | E110: pagado | G110: distri LJ
A117: JUE 10 | B117: 48200 | G117: harina | H117: 190
C118: 211504 | E118: pagado | G118: matiz
B119: 63990 | G119: choco alpino
A132: VIE 11 | B132: 116625 | G132: milkaut | H132: 310
B133: 62105 | G133: la serenisima
B134: 71000 | E134: pagado | G134: edu
A143: SAB 12 DOM 13 | B143: 24316.2 | G143: brie | H143: 170 | I143: SAB
D144: 260494 | E144: pagado | G144: marilu | H144: 40 | I144: estaba en la caja roja pero no se de que dia es
I145: lo puse en sobre de sabado
H146: =SUM(H143:H145) -> 210 | I146: ese seria el total
H149: 196 | I149: DOM
A158: LU 14 | B158: 85500 | E158: pagado | G158: edu | H158: 140
B159: 65898.43 | G159: puchos marilu (saldos)
A174: MA 15 | D174: 55157.85 | G174: quintela | H174: 290
B175: 85930 | G175: milkaut
B176: 87847.5 | G176: feras
D177: 69802.39 | E177: pagado | G177: marilu
D178: 150700 | E178: pagado | G178: parada | I178: deposite 600 mio en cuenta bbva y pague expensas por 493331,65
B179: 8250 | G179: resma hojas | I179: 106669 | J179: a favor
B180: 10300 | G180: dietetica az rubia | I180: 22883 | J180: a favor de la semana anterior
B181: 39000 | G181: colorante rojo | I181: 129552 | J181: total que me transferi a cecimp
A189: MIE 16 | B189: 83000 | E189: pagado | G189: edu | H189: 169
D190: 613954 | E190: pagado | G190: motofeca
F191: 2300 | G191: hielo
B192: 57000 | E192: pagado | G192: huevo
B193: 25525.24 | G193: la serenisima
C194: 138773.29 | G194: ormazabal
D195: 128852.68 | E195: pagado | G195: la redencion
A201: JUE 17 | F201: 8000 | G201: hielo | H201: 386.5
B202: 47700 | E202: pagado | G202: harina
D204: 100000 | G204: Marcelo pintor puso Hernan
G205: recupero 50k el 22/10
A216: VIE 18 | B216: 127000 | E216: pagado | G216: edu | H216: 286
F217: 3060 | G217: cerdo
B218: 85516.67 | G218: la serenisima
F219: 20000 | G219: flete heladera
F220: 7000 | G220: moto motofeca
E222: 1857314.7 | G222: HELADERA + KITCHEN AID
G223: NUEVO EMPORIO
A230: SAB 19 DOM 20 | D230: 216935.6 | E230: pagado | G230: matiz | I230: SAB
D231: 118711.5 | E231: pagado | G231: motofeca | I231: 100 aparte se uso para sueldos
B232: 25696.8 | G232: jamon crudo | I232: 140 se retiro
F233: 12000 | G233: palta
H237: 160 | I237: DOM
F238: 981 | G238: banana
F239: 12714 | G239: mayo y leche
A245: LU 21 | B245: 79000 | E245: pagado | G245: edu | H245: 310
B246: 85617.32 | G246: la serenisima
...

Sheet NOVIEMBRE 2024
A1: . | B1: MP | C1: CHEQUE | D1: TRANSFERENCIA | F1: GASTOS EN EFT | H1: RETIROS
A2: VIE 1 | F2: 20000 | G2: paro lucho | H2: 284
D3: 205200 | E3: pagado | G3: manteca
B4: 33000 | E4: si | G4: edu
B5: 42479.78 | G5: la serenisima
B6: 136471.9 | G6: milkaut
H16: 214.5 | I16: SAB
A18: SAB 2 DOM 3
H21: 130 | I21: DOM
A28: LU 4 | B28: 111800 | E28: si | G28: edu | H28: 326
B29: 57000 | G29: huevo
B30: 79864.9 | G30: la serenisima
F31: 5346 | G31: palta
F32: 4000 | G32: hielo
B33: 68607 | E33: pagado | G33: wraps
A42: MA 5 | F42: 4000 | G42: hielo | H42: 208
B43: 166251.05 | E43: pagado | G43: quintela VTO 5/12 | I43: hernan se transfierio 330k de mp
B44: =44147.72+5808 -> 49955.72 | E44: pagado | G44: criollo
B45: 143116.44 | E45: pagado | G45: horeca | I45: 130 se usaron para rescatar ch 868 de ormaabal
B46: 4500 | G46: moto uber a contadora
B47: 28000 | G47: fumigador
A54: MIE 6 | B54: 127000 | E54: si | G54: edu | H54: 460
B55: 42479.78 | G55: la serenisima | I55: se saco del galicia 250 para ch matiz
B56: 68316.37 | E56: pagado | G56: ormazabal VTO 21/11
B57: 63990 | G57: Choco alpino | I57: Hernan uso 180 del galicia va a depositar 100
I58: compenso 50 y resta 30
G59: 222000 efectivo contra ch Matiz #56860
I60: compensado con ceci que uso 40k para grua de auto el 15/11
B61: 137088 | E61: PAGADO | G61: la redencion
B62: 14650 | G62: costa
D63: 470387.5 | E63: pagado | G63: motofeca
A70: JUE 7 | F70: 4400 | G70: fp | H70: 189
F71: 1229 | G71: ketchup
D72: 227235.27 | E72: pagado | G72: marilu
B73: 23953.5 | G73: brie
B74: 46800 | E74: pagado | G74: harina
A84: VIE 8 | B84: 88500 | E84: si | G84: edu | H84: =190+36 -> 226
F85: 5630 | G85: breik
B86: 42975 | G86: la serenisima
A102: SAB 9 DOM 10
B105: 57000 | G105: huevo | H105: 260 | I105: SAB
F106: 1390 | G106: carrefour
H111: 172 | I111: DOM
A117: LU 11 | F117: 1390 | G117: detergente | H117: 200
B118: 68768.98 | G118: la serenisima
D119: 334012.83 | E119: pagado | G119: marilu
B120: 139000 | E120: si | G120: edu
A132: MA 12 | D132: =79632.44+25990.8 -> 105623.24 | E132: pagado | G132: quintela VTO 12/12 | H132: 300
D133: 147622.46 | E133: pagado | G133: horeca
D134: 10840.91 | E134: pagado | G134: criollo
D135: 103400 | E135: pagado | G135: distri LJ
A143: MIE 13 | B143: =89500-3000 -> 86500 | E143: si | G143: edu | H143: 300
B144: 42975.66 | G144: la serenisima
B145: 51356.66 | G145: milkaut
D146: =148477.48-15879.52 -> 132597.96 | E146: pagado | G146: ormazabal VTO 30/11 (desconte 15k)
B147: 65990 | G147: choco alpino
B148: 44793 | G148: cafiza
B149: 220000 | E149: pagado | G149: manteca
B150: 514734 | E150: PAGADO | G150: motofeca
B151: 50000 | G151: almafuerte
A158: JUE 14 | B158: 62901.7 | E158: pagado | G158: cuyaires | H158: 280
D159: 102500 | G159: ch rechaz quintela deposito contra ch
B160: 57000 | G160: huevo
B161: 46800 | E161: pagado | G161: harina
A174: VIE 15 | B174: 88439 | E174: falta 19000 | G174: la serenisima total:107439 | H174: 169 | I174: faltan 120k
F175: 10000 | G175: hielo
B176: 113500 | E176: si | G176: edu
B177: 196096 | E177: pagado | G177: gonzanio
B178: 143667 | E178: pagado | G178: la redencion
A189: SAB 16 DOM 17 | B189: 53194 | G189: brie | H189: 290 | I189: ok
B190: 18917.53 | E190: PAGADO | G190: criollo
B191: 65225.84 | E191: PAGADO | G191: horeca
F192: 6800 | G192: se completosueldo kren | H192: 140 | I192: ok
F193: 32500 | G193: sueldo sebastian *13hs
A201: LU 18 | H201: 66 | I201: hay 60
I202: Hernan se transfirio 55k
I204: se uso 65k para recatar ch ormazabal
A216: MA 19 | F216: 4716 | G216: fp | H216: 350 | I216: ok
D217: 84195.92 | G217: quintela reemplazo ch 556861 +$ 2000 impuestos
D218: 84195.92 | G218: ormazabal a cuenta
B219: 68607 | E219: pagado | G219: wraps
F220: 2979 | G220: yogur
F221: 4468 | G221: ypgur
D222: 167532.06 | E222: pagado | G222: quintela VTO 19/12
A230: MIE 20 | B230: 57000 | E230: pagado | G230: huevo | H230: 356 | I230: ok
B231: =115000-4000 -> 111000 | E231: si | G231: edu no vino verdeo
B232: =57170.51+19000 -> 76170.51 | E232: completa los 19000 que se debia | G232: la serenisima
B233: 55933.13 | E233: pagado | G233: ormazabal VTO 5/12
B234: 244509.36 | E234: pagado | G234: marilu
A245: JUE 21 | B245: 50000 | G245: messian syrups | H245: 320 | I245: ok
F246: 6000 | G246: envio syrups
B247: 49200 | E247: pagado | G247: harina
A258: VIE 22 | B258: 38000 | E258: si | G258: edu | H258: 220 | I258: FALTAN 70K
B259: 51492.56 | G259: la serenisima | I259: 351 transf hernan a su mp
B260: 130622.8 | G260: milkaut itflow
I261: 150k transf hernan a su mp el sab 23
I264: estado de cuenta hernan
I265: debe a R2 | J265: haber | K265: resta
I266: 330 | J266: 660
I267: 55
...

Sheet DICIEMBRE 2024
A1: f | B1: MP | C1: CHEQUE | D1: TRANSFERENCIA | F1: GASTOS EN EFT | H1: RETIROS
A2: DOM1 | F2: 1340 | G2: frutas premium | H2: 280 | I2: SAB
H8: 200 | I8: DOM
B16: 125000 | E16: si | G16: edu | H16: 290
B17: 38729.87 | G17: la serenisima
A18: LU 2 | B18: 212800 | E18: PAGADO | G18: manteca
A28: MA 3 | B28: 65990 | G28: choco alpino | H28: 280
B29: 57000 | G29: huevo
B30: 185271.45 | E30: pagado | G30: quintela VTO 3/1
B31: 91660.42 | E31: pagado
B32: 450846 | E32: pagado | G32: motofeca
A42: MIE 4 | B42: 91000 | E42: si | G42: edu | H42: 300
F43: 6030 | G43: panko
B44: 38729.87 | G44: la serenisima
B45: =5952+44848.13 -> 50800.13 | E45: pagado | G45: criollo
B46: 196061.56 | E46: pagado | G46: horeca
B47: 52000 | G47: aceite freidora almafuert
B48: 68607 | G48: wraps
A54: JUE 5 | B54: 30000 | E54: pagado | G54: harina | H54: 340
A70: VIE 6 | F70: 10000 | G70: hielo | H70: 330
B71: 50500 | E71: si | G71: edu
B72: 100671 | G72: Milkaut | I72: hernan uso 100000 de mp, ya se compenso en ef en la liquidacion de la semana
A84: SAB 7 DOM 8 | B84: 50732.5 | G84: brie | H84: 336
B85: 321361.39 | E85: pagado | G85: marilu
A102: LU 9 | H102: 244
B105: 77460 | G105: la serenisima
B106: 130000 | E106: si | G106: edu
B107: 121278.57 | E107: PAGADO | G107: la redencion
A117: MA 10 | F117: 1300 | G117: limpieza | H117: 430
B118: 57000 | E118: pagado | G118: huevo
F119: 2421 | G119: palta
B120: 456835.5 | E120: pagado | G120: motofeca
A132: MIE 11 | B132: 54191 | F132: 10575 | G132: la serenisima | H132: =290+32 -> 322
B133: 140000 | E133: si | G133: edu
B134: 54191.09 | G134: la serenisima
B135: 154629.14 | E135: pagado | G135: ormazabal VTO25/12
B136: 97703.35 | E136: pagado | G136: quintela VTO 11/1
A143: JUE 12 | F143: 5000 | G143: hielo | H143: =280+109 -> 389
B144: 18376.91 | E144: pagado | G144: criollo
B145: 216771.96 | E145: pagado | G145: horeca
B146: 45000 | G146: harina
B147: 22004.99 | G147: cuchillos descartables
F148: 1600 | G148: libreria
B149: 6500 | G149: libreria
A158: VIE 13 | B158: 50500 | E158: si | G158: edu | H158: =260+78 -> 338
B159: 38729.87 | G159: la serenisima
B160: 53687.7 | G160: gonzanio | I160: 90k uso hernan de mp para chapa rolo
I161: compensado
A174: SAB 14 DOM 15 | B174: 197221.17 | E174: pagado | G174: marilu | H174: =260+120 -> 380
B175: 10890 | G175: sorbetes
A189: LU 16 | F189: 1490 | G189: detergente | H189: 340
B190: 57000 | G190: huevo
B191: 94000 | E191: si | G191: edu
B192: 38729.87 | G192: la serenisima
A201: MA 17 | F201: 1700 | G201: bolsa residuo | H201: 174
B202: 142979 | G202: milkaut
B203: 286200.05 | E203: si | G203: manteca
B204: 338134.5 | E204: pagado | G204: motofeca
A216: MIE 18 | B216: 64199.71 | G216: la serenisima | H216: 350
B217: 158800 | E217: pgado | G217: distri LJ
B218: 101192.65 | E218: pagado | G218: marilu (peceto y lengua hernan) | I218: hernan puso 589k DEVOLVER EN USD
B219: 144000 | E219: si | G219: edu | I219: -101192,65 marilu navidad
I220: 487807.35 | J220: TOTAL
I221: 100000 | J221: 45661
I222: 61000 | J222: 45689
I223: 101350 | J223: 45698
I224: 100000 | J224: 45702
I225: 110000 | J225: 45708
I227: =I220-I221-I222-I223-I224-I225 -> 15457.35 | J227: RESTA | K227: LISTO
A228: JUE 19 | B228: 48400 | G228: cobo mixer falta fac A | H228: 350 | I228: sumar 300 usd HABILITACION
I230: -101355 | J230: 45709
I231: -60000 | J231: 45714
A243: VIE 20 | B243: 63629.16 | G243: LA SERENISIMA
B244: 70664 | E244: pagado | G244: wraps imprimir fac
F245: 4680 | G245: fp
B246: 143830.36 | E246: pagado | G246: la redencion
A256: SAB 21 DOM 22 | H256: 243
A272: LU 23 | F272: 2700 | G272: vino bco | H272: =270+21 -> 291
F273: 5000 | G273: hielo
B274: 67646 | G274: la serenisima
B275: =104500-4000 -> 100500 | E275: si | G275: edu (no vino el morron amarillo)
B276: 129984.13 | E276: pagado | G276: quintela VTO 23/1
B277: 57000 | G277: Huevo
A287: MA 24 | B287: 128850.71 | E287: pagado | G287: criollo | H287: 144
B288: 191236.83 | E288: pagado | G288: horeca
B289: 78162.03 | E289: pagado | G289: ormazabal VTO 8/1
B291: 65488.1 | E291: pagado | G291: marilu
A302: MIE 25
A316: JUE 26 | B316: 64500 | E316: pagado | G316: harina | H316: =340+30 -> 370
B317: 9667 | G317: sorbetes
F318: 1400 | G318: rucula
A334: VIE 27 | B334: 86500 | E334: si | G334: EDU | H334: 250
B335: 19364.94 | G335: la serenisima
B336: 185483.67 | E336: pagado | G336: marilu
B337: 43371.39 | G337: milkaut
B338: 450846 | E338: pagado | G338: motofeca
A346: SAB 28 DOM 29 | H346: 200
A358: LU 30 | H358: 390
B359: 57000 | G359: huevo
B360: 19364.94 | G360: la serenisima
...

Sheet ENERO 2025
B1: MP | C1: CHEQUE | D1: TRANSFERENCIA | E1: ADEUDA | F1: GASTOS EN EFT | H1: RETIROS
A2: JUE 2 | H2: 320 | I2: Desde 09 a la fecha se le debe a Edu total=
D3: 87470.17 | E3: pagado | G3: cuyaires
F4: 1703.65 | G4: fp
B5: 55600 | G5: ACEITE FREIDORA
B6: 69490 | G6: choco alpino
F16: 5000 | G16: hielo | H16: 340
B17: 141500 | E17: si | G17: edu
A18: VIE 3 | B18: 19364.94 | G18: la serenisima
A28: SAB 4 | D28: 200864 | E28: pagado | G28: marilu | H28: 300
F29: 15945 | G29: BRIE
A42: LU 6 | B42: 67500 | E42: si | G42: edu | H42: 320
B43: 38729 | G43: la serenisima
B44: 191600 | E44: pagado | G44: manteca
F45: 1690 | G45: Carrefour
A54: ma 7 | B54: 44100 | E54: pagado | G54: HARINA | H54: 310
B55: 152448.32 | E55: si | G55: QUINTELA VTO 7/2
B56: 57000 | E56: pagado | G56: huevo
B57: 113419 | G57: milkaut
A70: MIE 8 | B70: 38272 | G70: la serenisima | H70: 290
F71: 1690 | G71: Carrefour
B72: 68500 | E72: SI | G72: Edu
F73: 4600 | G73: Bire
C74: 61555.93 | E74: pagado | G74: Ormazabal
A84: JUE 9 | F84: 7000 | G84: Queo Brie | H84: 250
C85: 87847.5 | E85: pagado | G85: Frutos Rjos Ice Feras
A102: VIE 10 | H102: 197
B105: 75000 | E105: si | G105: edu
F106: 10000 | G106: hielo
B107: 125460 | E107: pagado | G107: la redencion
B108: 85240 | E108: pagado | G108: distib LJ
B109: 51464.77 | G109: la serenisima
F110: 10000 | G110: brie
A117: SAB 11 | B117: 264682 | E117: pagado | G117: marilu | H117: 270
A132: LU 13 | F132: 4752 | G132: LIMON | H132: 230
B133: 19364.94 | G133: la serenisima
A143: MA 14 | F143: 2359 | G143: crema | H143: 212
F144: 7864.56 | G144: limon
B145: 57000 | G145: huevo
B146: 117500 | E146: si | G146: edu
B147: 46600 | E147: pagado | G147: manteca
D148: 101631.16 | E148: pagado | G148: semas (quesos)
B149: 69490 | G149: choco alpino
B150: 18126 | G150: colorante rojo
B151: 70664 | E151: si | G151: wraps
B152: 370804.5 | E152: si | G152: motofeca
A158: MIE 15 | B158: 44500 | E158: pagado | G158: edu | H158: 295
B159: 54648.53 | G159: la serenisima
B160: 176461.44 | E160: ´pagado | G160: gonzanio
B161: 58445.95 | G161: milkaut
B162: 253391.16 | E162: pagado | G162: Ormazabal VTO 30/1
F163: 2000 | G163: curitas
A174: JUE 16 | F174: 4917.65 | G174: fp | H174: 180 | I174: 50 USO CECI
B175: 30000 | G175: harina
B176: 163904.33 | E176: si | G176: quintela VTO 15/2
B177: 10000 | G177: hielo
G178: tutto farra
G179: vitalcer
F180: =3639+1000 -> 4639 | G180: lima
F181: 4900 | G181: limon
A189: VIE 17 | B189: 112500 | E189: si | G189: edu | H189: =118+70 -> 188 | I189: 200 SE USO PARA LUCHO
F190: 2850 | G190: breik
B191: 51464.77 | G191: la serenisima
B192: 71910 | E192: pagado | G192: la redencion
A201: SAB 18 | H201: =145+80 -> 225
I202: se uso 80 pri y 20 rodri
A216: LU 20 | B216: =93000 -> 93000 | E216: si | G216: EDU | H216: 468
B217: 57000 | G217: huevo
B218: 19364.94 | G218: la serenisima
B219: 79203.8 | E219: pagado | G219: Semas VTO 27/1 lunes
F220: =16031.35+7374.51 -> 23405.86 | G220: fp
F221: 8600 | G221: leche en polvo
A230: MA 21 | F230: 5548 | G230: fp | H230: 360
B231: 55600 | E231: pagado | G231: aceite freidora
B232: 20726 | G232: tenedores
A245: MIE 22 | B245: =58500-13000 -> 45500 | E245: si | G245: edu (se devolvio la espinaca) | H245: 32 | I245: 100 uso h y 100 uso c
B246: 462401.5 | E246: si | G246: motofeca
B247: 207858.83 | E247: pagado | G247: marilu
F248: 1620 | G248: fp
B249: 59266 | G249: coffler
B250: 69490 | G250: choco alpino
A258: JUE 23 | F258: 1620 | G258: espinaca | H258: =140+170 -> 310
B259: 30000 | G259: HARINA
B260: =189067.46+108280.35 -> 297347.81 | E260: si | G260: quintela VTO 23/2
F261: 7000 | G261: syrups envio
B262: 50000 | G262: syrups
F263: 8000 | G263: tuttofarra
A274: VIE 24 | B274: 204600 | E274: si | G274: manteca | H274: 110 | I274: se uso todo para alq
B275: 55000 | E275: si | G275: edu
B276: =38272.43+38729.87 -> 77002.3 | G276: la serenisima (2 boletas)
A289: SAB 25 | H289: 242 | I289: se uso todo para alq
A304: LU 27 | B304: 95000 | E304: si | G304: edu | H304: 130 | I304: 160 se uso para alquiler
B305: 55043.3 | E305: pagado | G305: Distrib Semas
F306: 10000 | G306: hielo
B307: 38729.87 | G307: la serenisima
B308: 20400 | G308: breik
B309: 1300 | G309: tutto farra
B310: 24785 | G310: uriburu harina de almendras
A318: MA 28 | B318: 135839 | E318: si | G318: marilu | H318: 190 | I318: se uso 90 para alq
B319: 52198.42 | G319: milkaut
...

Sheet FEBRERO 2025
B1: MP | C1: CHEQUE | D1: TRANSFERENCIA | E1: ADEUDA | F1: GASTOS EN EFT | H1: RETIROS
A2: SAB 1 | H2: 283 | I2: se deposito
A3: LU 3 | D3: 103679.22 | E3: pagado | G3: SEMAS | H3: 204 | I3: se deposito
B4: 143500 | E4: si | G4: EDU
B5: 10809 | G5: colorante rojo
B17: 90718 | F17: 44000 | G17: milkaut | H17: 130 | I17: 15hs se deposito
B18: 34900 | E18: pagado | G18: feras | H18: 110 | I18: restante
A19: MA 4 | F19: 7400 | G19: tutto farra
D20: 25000 | G20: dia camila
A29: MIE 5 | B29: 50000 | E29: pagado | G29: edu | H29: 259
B30: 119615.72 | E30: si | G30: Ormazabal VTO 19/2
F31: 5640 | G31: breik
B32: 108000 | E32: Pagado | G32: huevo
B33: 161823 | G33: la serenisima 3 facturas
B34: 265042.5 | E34: si | G34: motofeca VTO 5/3
B35: 63890 | G35: choco alpino
F36: 10000 | G36: camila
A43: JUE 6 | B43: 155410.95 | E43: si | G43: quintela VTO 6/3 | H43: 270
F44: 5000 | G44: hielo
F45: 28000 | G45: camila
A55: VIE 7 | B55: 19848.77 | G55: la serenisima | H55: 340
B56: 205399.64 | E56: si | G56: marilu
B57: 47500 | E57: pagado | G57: edu
A71: SAB 8 | B71: 20991 | G71: colorante rojo
A85: LU 10 | B85: 95500 | E85: si | G85: edu | H85: 180
B86: 32583.67 | G86: la serenisima
A103: MA 11 | H103: 260
F106: 5000 | G106: HIELO
A118: mie 12 | F118: 1200 | G118: TUTTO FARRA | H118: 360
B119: 24600 | G119: CHINO
B120: 3400 | G120: COSTA
A133: JUE 13 | F133: 11842.74 | G133: fp | H133: 186
F134: 11100 | G134: brie | H134: -100 | I134: h
F135: 7000 | G135: envio syrup
H136: 86
A144: VIE 14 | F144: 3800 | G144: tutto farra | H144: 450
B145: 1900 | G145: tutto farra
B146: 1660 | G146: breik
B147: 22000 | G147: syrup messian
F148: 20000 | G148: cami
F149: 30000 | G149: adelanto chris
B150: 5000 | G150: palta fp
A159: SAB 15 | F159: 8500 | G159: Cami | H159: 270
A175: LU 17 | F175: 3222 | G175: fp espinaca | H175: 340
A190: MA 18 | B190: 58000 | G190: aceite freidora | H190: 250
F191: 9640 | G191: brie
F192: 7353 | G192: fp
B193: 33500 | G193: Colorante
A202: MIE 19 | F202: 3108 | G202: carrefour | H202: 210
A217: JUE 20 | F217: 15000 | G217: brie | H217: 360
A231: VIE 21 | B231: 48600 | G231: feras frutos rojos | H231: =110+50 -> 160
F232: 10000 | G232: hielo
A246: SAB 22 | B246: 63890 | G246: chocolate | H246: 190
B247: 61000 | G247: huevo
A259: LU 24 | F259: 5748.43 | G259: brocoli | H259: =60+300+100+8 -> 468
A275: MA 25 | H275: =100+400+30 -> 530
A290: MIE 26 | H290: =100+30+200 -> 330 | I290: 20 ceci
A305: JUE 27 | F305: 5821 | G305: fp | H305: =50+160+80 -> 290
A319: VIE 28 | B319: 61000 | G319: huevo | H319: 95
F320: 225000 | G320: mary
A385: GASTOS FIJOS | D385: 70000 | G385: EDESUR | H385: 45691 | I385: anticipo plan de pagos 12 cuotas | J385: Galcia | K385: ok
B386: 329687.38 | G386: EDESUR | H386: 45714
B387: 167716.75 | G387: METROGAS (DEUDA) | H387: 45714 | I387: plan de pagos | J387: Galicia | K387: ok
D388: 123280.4 | G388: FLOW | H388: 45708 | I388: GALICIA
G389: AYSA | J389: Galicia | K389: ok
D390: 318000 | G390: Gonzalo cuota heladera
D391: 363000 | G391: ALQUILER A | H391: 45717
F392: 600000 | G392: ALQUILER B
G393: EXPENSAS
D394: 130000 | G394: CONTADORA | H394: 45693
D396: 70864.64 | G396: METROTEL(Cps) | H396: 45708 | I396: pagamos del galicia | J396: Falta ad deb
D397: 57732.36 | G397: VERISURE | I397: link de mp | J397: Falta ad deb | K397: se pagaron 2 facturas x mp
D398: 113167.71 | G398: MAXIREST | I398: DEBITO AUTOM | J398: esta dado de alta en nuevo cbu
D399: 84785.15 | G399: MAPFRE | I399: DEBITO AUTOM
D400: 46630 | G400: AUTONOMOS VEP | H400: 45691
D401: 107822.49 | G401: ART VEP (periodo inicial)
D402: 14425.21 | G402: ART VEP (periodo inicial) INTERESES
G403: CARGAS SOCIALES VEP
G404: uthgra seg vida
G405: uthgra convenio
G406: uthgra cuota sindical
G407: IVA | I407: IVA DE noviemBRE QUE VENCIA EN febrero
D408: 142499.15 | G408: UVA CIUDAD | H408: 45698 | I408: A mano | J408: Galicia | K408: Hay que programarla
G411: MARTIN REDES
B414: =SUM(B385:B413) -> 497404.13 | D414: =SUM(D385:D413) -> 1642207.1 | F414: =SUM(F385:F413) -> 600000

Sheet MARZO 2025
B1: MP | C1: CHEQUE | D1: TRANSFERENCIA | E1: ADEUDA | F1: GASTOS EN EFT | H1: RETIROS
A2: SAB 1 | H2: 269 | I2: se uso 100 para priscila
I3: se uso para alquiler
A5: LU 3 | H5: 140 | I5: se uso para alquiler
H19: 200 | I19: se uso para alquiler
A21: MA 4
A31: MIE 5 | H31: 340
A45: JUE 6 | F45: 10000 | G45: hielo | H45: 303
F46: =3600+1560 -> 5160 | G46: verdu
F47: 7710 | G47: moto contadora
A57: VIE 7 | B57: 49700 | G57: feras frutos rojos | H57: 370
F58: 1242 | G58: rucula
F59: 6700 | G59: Lechuga francesa
I60: hernan uso 50k nafta y 100k el galicia
A73: SAB 8 | F73: 6713.55 | G73: fp | H73: 300
A87: LU 10 | B87: 61000 | G87: huevo | H87: 280
A105: MA 11 | H105: 340
A120: mie 12 | F120: 14100 | G120: verdu pago cami ya se lo devolvi en ef | H120: 390
F121: 5000 | G121: hielo
A135: JUE 13 | B135: 27114 | G135: harina almendra y az impalpable | H135: 300
F136: 6000 | G136: verdu
B137: 29230 | G137: la botica del pastelero
A146: VIE 14 | F146: 1490 | G146: limpieza | H146: 160
A161: SAB 15 | H161: 476 | I161: use 300 para sueldo mary asique queda 176
A177: LU 17 | F177: 3271.32 | G177: FP | H177: =220+270 -> 490
F178: 3680 | G178: CARREFOUR
A192: MA 18 | F192: 2300 | G192: breik | H192: =170+100 -> 270
A204: MIE 19 | H204: =200+170 -> 370
A219: JUE 20 | H219: 290
I221: 350k uso Hernan para patente auto
I222: 50 k H transfierio a su cuenta nacion
I223: los 50k estan compensados con ceci
A233: VIE 21 | B233: 34000 | G233: naranjas frutas premium | H233: =270+140 -> 410
A248: SAB 22/DOM 23 | F248: 5490 | G248: BOLSAS | H248: 290 | I248: SAB
H250: 210 | I250: DOM
A261: LU 24 | H261: 390
A277: MA 25 | B277: 6330 | G277: fp | I277: 430 se deposito
B278: 63000 | G278: tutto farra chocolate
F279: 2339 | G279: lavandina
A292: MIE 26 | H292: 49 | I292: 100 uso h
I293: ya compensado con ceci
A307: JUE 27 | H307: 410
A321: VIE 28 | H321: =110+200 -> 310 | I321: se repartio
A339: SAB 29 DOM 30 | H339: 190 | I339: SAB se uso para alquiler
H344: 220 | I344: DOM se uso para alquiler
A351: LU 31 | B351: 63000 | G351: tutto farra | H351: =240+40 -> 280 | I351: se uso para alquiler
A387: GASTOS FIJOS | J387: Galcia | K387: ok
G388: EDESUR
C389: 136330 | E389: 45728 | G389: METROGAS (DEUDA) | I389: plan de pagos | J389: Galicia | K389: ok
D390: 122753.85 | G390: FLOW | H390: 45742 | I390: GALICIA
G391: AYSA | J391: Galicia | K391: ok
D392: 318000 | G392: Gonzalo cuota heladera | H392: 45738
D393: 363000 | G393: ALQUILER A | H393: 45736
F394: 690000 | G394: ALQUILER B (con 90 de punitorios) | H394: 45751
G395: EXPENSAS
D396: 130000 | G396: CONTADORA | H396: 45734
D398: 72423.77 | G398: METROTEL(Cps) | H398: 45742 | I398: pagamos de mp | J398: Falta ad deb da rechazado todos los meses
D399: 53263 | G399: VERISURE | I399: link de mp | J399: Falta ad deb | K399: se pagaron 2 facturas x mp
D400: 124484.47 | G400: MAXIREST | H400: 45727 | I400: DEBITO AUTOM | J400: esta dado de alta en nuevo cbu
D401: 84785.15 | G401: MAPFRE | I401: DEBITO AUTOM
D402: 46630 | G402: AUTONOMOS VEP
D403: 107822.49 | G403: ART VEP (periodo inicial)
D404: 14425.21 | G404: ART VEP (periodo inicial) INTERESES
G405: CARGAS SOCIALES VEP
G406: uthgra seg vida
G407: uthgra convenio
G408: uthgra cuota sindical
G409: IVA | I409: IVA DE noviemBRE QUE VENCIA EN febrero
D410: 142499.15 | G410: UVA CIUDAD | H410: 45726 | I410: A mano | J410: Galicia | K410: Hay que programarla
G413: MARTIN REDES
B416: =SUM(B387:B415) -> 0 | D416: =SUM(D387:D415) -> 1580087.1 | F416: =SUM(F387:F415) -> 690000

Sheet ABRIL 2025
A1: ABRIL | B1: MP | C1: CHEQUE | D1: TRANSFERENCIA | E1: ADEUDA | F1: GASTOS EN EFT | H1: RETIROS
A2: MA 1 | H2: 310 | I2: -293 mary
A16: MIE 2 | H16: 350
A30: JUE 3 | H30: 320
A42: VIE 4 | H42: 320
A58: SAB 5 | H58: 30 | I58: SAB
I59: ceci 220
I60: compensado
I62: DOM
I63: hernan gasto 170
I64: compensado
A72: LU 7 | I72: hernan gasto 130
I73: ceci gasto 120
I74: compensado
A90: MA 8 | B90: 63000 | G90: chocolate tutto farra | H90: 300 | I90: 100 se llevo hernan
I91: compensado
A105: mie 9 | F105: 30 | G105: seba | H105: 300 | I105: ceci gasto 60
I106: compensado
I119: habia 440
A120: JUE 10 | H120: 134 | I120: -270 mary
I121: - 20 uber agus
I122: -16 uber leo
A131: VIE 11 | B131: 6700 | G131: tutto farra (cortantes pascua) | H131: 430 | I131: 100 gasto h del galicia
B132: 17000 | G132: fp | I132: compensado
A146: SAB 12 | I146: SAB
I147: 150 se repartio
I148: 80 retiro h
I149: compensado
H152: 90 | I152: DOM
A162: LU 14 | H162: =350+60 -> 410
A177: MA 15 | B177: 24400 | G177: vitalcer h de alm | H177: 110 | I177: h retira 300
I178: compensado
A189: MIE 16 | F189: 16800 | G189: panisi bebidas vidrio (se pago con ef del sab) | H189: =220+150 -> 370
A204: JUE 17 | H204: =230+90 -> 320 | I204: h transfiriio 40k
I205: compensado
A218: VIE 18 | H218: 290
A233: SAB 19/DOM 20 | I233: 120 turno mañana (se repartio)
H234: 240 | I234: SAB
H239: 130 | I239: DOM
I241: 100K SE LLEVO H
A246: LU 21 | B246: 43400 | G246: tutto farra choco | H246: 350
A262: MA 22 | H262: =300+60 -> 360
A277: MIE 23 | B277: 24400 | G277: vitalcer | H277: 190
I278: 124029 USO H FILTROS
A292: JUE 24 | H292: 300
A306: VIE 25 | H306: =200+170 -> 370
A324: SAB 26 DOM 27 | H324: 170 | I324: SAB
H329: 120 | I329: DOM
A336: LU 28 | B336: 76200 | G336: tutto farra chocolate | H336: 40
B337: 13778 | G337: carrefour leche
A348: MA 29 | H348: 140
A359: MIE 30 | H359: =160+230 -> 390
A372: GASTOS FIJOS | J372: Galcia | K372: ok
G373: EDESUR
B374: 306851 | G374: METROGAS (DEUDA) | H374: 45752 | I374: plan de pagos | J374: Galicia | K374: ok
D375: 122753.85 | G375: FLOW | I375: GALICIA
G376: AYSA | J376: Galicia | K376: ok
D377: 318000 | G377: Gonzalo cuota heladera
D378: 720000 | G378: ALQUILER A
F379: 700000 | G379: ALQUILER B
G380: EXPENSAS
D381: 136000 | G381: CONTADORA | H381: 45751 | I381: galicia pagado
D382: 50137 | G382: AUTONOMOS VEP (perido 03) | H382: 45752
D383: 72423.77 | G383: METROTEL(Cps) | H383: 45777 | I383: pagamos de mp | J383: Falta ad deb da rechazado todos los meses
D384: 173197 | G384: VERISURE | I384: se pago feb/mar/abril | J384: Falta ad deb
D385: 124484.47 | G385: MAXIREST | H385: 45755 | I385: DEBITO AUTOM
D386: 84785.15 | G386: MAPFRE | I386: DEBITO AUTOM
D387: 50137.39 | G387: AUTONOMOS VEP | H387: 45752
D388: 323159.6 | G388: ART VEP | H388: 45757
G390: CARGAS SOCIALES VEP
G391: uthgra seg vida
G392: uthgra convenio
G393: uthgra cuota sindical
G394: IVA
D395: 142499.15 | G395: UVA CIUDAD | H395: 45756 | I395: A mano | J395: Galicia | K395: Hay que programarla
G398: MARTIN REDES
B401: =SUM(B372:B400) -> 306851 | D401: =SUM(D372:D400) -> 2317577.4 | F401: =SUM(F372:F400) -> 700000

Sheet MAYO 25
A1: MAYO | B1: GASTOS MP | C1: GASTOS TRANSFER | D1: GASTOS EFT | E1: OBSERVACIONES Y NOTAS | F1: RETIROS DE CAJA | G1: NOTAS | H1: RETIROS HERNAN | I1: RETIROS CECI
A2: VIE 2 | F2: 160 | G2: puso hernan para alquiler | H2: =720000 -> 720000
H3: -150000
G4: debito de mp | H4: -267572
G5: fac carne | H5: -231918
G6: compras desde el galicia | H6: -72000
H7: =SUM(H2:H6) -> -1490
A8: SAB 3/DOM 4 | F8: 80 | G8: SAB
G9: Se repartio 120 + sueldo juan
F11: 10 | G11: DOM
G12: habia 280 se uso 270 mary sueldo
A15: LU 5 | F15: 250
A21: MA 6 | B21: 27200 | E21: 2k chocolate tutto farra | F21: =350+140 -> 490 | I21: 70
A27: MIE 7 | F27: 370
A33: JUE 8 | F33: 390
A39: VIE 9 | B39: 8700 | E39: chino | F39: =80+300 -> 380
B40: 17100 | E40: cartas breik
A45: SAB 10/DOM 11 | D45: 1958 | E45: levadura | G45: 60 se uso para rodri y fabri
D46: 9000 | E46: bolsas? | G46: 250 se uso para mary
F48: 270 | G48: DOM
A51: LU 12 | F51: =140+360 -> 500
A57: MA 13 | F57: =90+200 -> 290
A63: MIE 14 | F63: 350
A69: JUE 15 | B69: 21549 | E69: colorantes | F69: =230+50 -> 280
A75: VIE 16 | B75: 39600 | E75: chocolate tutto farra | F75: 300
A81: SAB 1 /DOM 18 | F81: 500
A87: LU 19 | F87: 350 | H87: 50
A93: MA 20 | F93: 60 | G93: pague sueldo de mary de aca
G94: habia 330
A99: MIE 21 | E99: nueo emporio | F99: =90+250 -> 340
A105: JUE 22 | F105: =150+250 -> 400
A111: VIE 23 | B111: 33900 | E111: fumigador | F111: =250+130 -> 380 | H111: 150
A117: SAB 24/ DOM 25 | F117: =140+150 -> 290 | G117: se uso alq
F120: 180 | G120: se uso alq | H120: =SUM(H87:H119) -> 200 | I120: 230 | J120: totales
A123: LU 26 | B123: 23400 | E123: vitalcer | F123: =200+50 -> 250 | G123: 200 ceci 50 alq | H123: 200 | I123: 200 | J123: compensado
A129: MA 27 | F129: =120+150 -> 270 | H129: 50 | J129: EF
I130: 20
A135: MIE 28 | F135: 170 | G135: 270 sueldo mary, habia 440
A141: JUE 29 | B141: 46200 | E141: choco alpino | F141: =100+60+400 -> 560 | H141: 30 | I141: 30
H142: 20
A147: VIE 30 | F147: =70+260 -> 330 | H147: 80 | J147: galcia
B148: 48800 | E148: harina almendra
A153: SAB 31 | F153: 70 | G153: habia 350
G154: 150sueldo chris 130laura | I154: 130
H155: =SUM(H129:H154) -> 180 | I155: =SUM(I129:I154) -> 180 | J155: total
A159: GASTOS FIJOS | H159: Galcia | I159: ok
E160: EDESUR
B161: 306851 | E161: METROGAS (DEUDA) | G161: plan de pagos | H161: Galicia | I161: ok
C162: 122753.85 | E162: FLOW | G162: GALICIA
E163: AYSA | H163: Galicia | I163: ok
C164: 318000 | E164: Gonzalo cuota heladera
C165: 720000 | E165: ALQUILER A
D166: 700000 | E166: ALQUILER B
E167: EXPENSAS
C168: 136000 | E168: CONTADORA | G168: galicia pagado
C169: 50137 | E169: AUTONOMOS VEP (perido 03)
C170: 72423.77 | E170: METROTEL(Cps) | G170: pagamos de mp | H170: Falta ad deb da rechazado todos los meses
C171: 173197 | E171: VERISURE | G171: se pago feb/mar/abril | H171: Falta ad deb
C172: 124484.47 | E172: MAXIREST | G172: DEBITO AUTOM
C173: 84785.15 | E173: MAPFRE | G173: DEBITO AUTOM
C174: 50137.39 | E174: AUTONOMOS VEP
C175: 323159.6 | E175: ART VEP
E177: CARGAS SOCIALES VEP
E178: uthgra seg vida
E179: uthgra convenio
E180: uthgra cuota sindical
E181: IVA
C182: 142499.15 | E182: UVA CIUDAD | G182: A mano | H182: Galicia | I182: Hay que programarla
B188: =SUM(B159:B187) -> 306851 | C188: =SUM(C159:C187) -> 2317577.4 | D188: =SUM(D159:D187) -> 700000

Sheet JUNIO 25
B1: GASTOS MP | C1: GASTOS TRANSFER | D1: GASTOS EFT | E1: OBSERVACIONES Y NOTAS | F1: RETIROS DE CAJA | G1: NOTAS | H1: RETIROS HERNAN | I1: RETIROS CECI
A2: LU 2 | B2: 88200 | E2: CHOCO ALPINO | F2: 220 | G2: DOM | H2: 700 | J2: puso p alq
H3: -280 | J3: retiro del galicia
F4: =190+170 -> 360 | G4: LU | H4: 500 | J4: puso para iva
H5: -113 | J5: aysa
H6: -50 | J6: a mp personal de hernan
H7: -35 | J7: a mp personal de hernan
A8: MA 3 | F8: 120 | G8: habia 390 se uso 270 sueldo mary | H8: -100 | J8: ef
H9: -110 | J9: cafe
H10: -100 | J10: transfer del galicia 11/6
H11: -100 | J11: ef 11/6
H12: -281.4 | J12: deuda mp11/6
H13: -150 | J13: transfer del galicia 12/6
H14: -76 | J14: transfer del galicia 13/6
A15: MIE 4 | B15: 38050 | E15: cucharitas | F15: =240+100 -> 340 | I15: -240 | J15: retiro ceci en ef
B16: 30400 | E16: vasitos | H16: -30 | J16: transfer del galicia 13/6
B17: 21200 | E17: breik | H17: -128.8 | J17: transfer galicia asado
H18: -64 | J18: farma costa
H19: -24 | J19: frutilla
I20: -200 | J20: ef sab 14
A21: JUE 5 | F21: =200+100 -> 300
A27: VIE 6 | B27: 16000 | E27: Tonner | F27: =240+150 -> 390
A33: SAB 7 / DOM 8 | F33: 230 | G33: sab | H33: =SUM(H2:H32) -> -442.2 | I33: =SUM(I15:I32) -> -440 | J33: total
G34: 200 se uso para sueldo chris | J34: compensado hasta el 14/6
H35: -100 | J35: transfer galicia 15/6
F36: 150 | G36: dom | H36: -81.4 | J36: mp 16/6
I37: -60 | J37: mp 15/6
I38: -26 | J38: mp 14/6
A39: LU 9 | F39: =250+160 -> 410 | H39: =680 -> 680 | J39: deposito en galicia 17/6
H40: -26 | J40: galicia 22/6
H41: -200 | J41: galicia 26/6
H42: -70 | J42: efectivo caja 25/6
H43: -100 | J43: galicia 27/6
A45: MA10 | B45: 3200 | E45: tapas tarta | F45: =180+70 -> 250
A51: MIE 11 | B51: 33400 | E51: choco tutto farra | F51: =200+200 -> 400 | G51: Habia 100 mas q se llevo hernan
A57: JUE 12 | F57: =200+240-270 -> 170 | G57: use 270 para sueldo mary
A63: VIE 13 | F63: 150 | G63: 240 retiro ceci
A69: SAB 14 / DOM 15 | F69: 340 | G69: SAB | H69: =SUM(H35:H68) -> 102.6 | I69: =SUM(I37:I68) -> -86 | J69: total
G70: 200 Laura
F72: 260 | G72: DOM
A75: LU 16 | F75: 300
A81: MA 17 | F81: =280 -> 280
A87: MIE 18 | B87: 48800 | E87: harina de almendras | F87: =150+160 -> 310
B88: 81600 | E88: tutto farra chocolate
A93: JUE 19 | B93: 39500 | E93: pasta fabrica | F93: =140+390 -> 530
A99: VIE 20 | F99: 70
G100: se uso 292 sueldo mary
A105: SAB 21/ DOM 22 | F105: =156 -> 156 | G105: SAB ok
G106: se uso 234 sueldo chris
F108: 100 | G108: DOM
G109: ok
A111: LU 23 | F111: =220+240 -> 460 | G111: ok
A117: MA 24 | F117: =220+130 -> 350 | G117: ok
A123: MIE 25 | B123: 54000 | E123: tutto farra chocolate | F123: =400+90 -> 490 | G123: tt dice 160 y el sobre tiene 90
A129: JUE 26 | F129: =140+260 -> 400 | G129: ok
A135: VIE 27 | F135: =100+250 -> 350 | G135: habia TM 370 se uso 270 sueldo mary
G136: ok
A141: SAB 28/ DOM 29 | F141: =29+130 -> 159 | G141: SAB TM HABIA 270 SE USO 215 CHRIS
G142: Y 30 SEBA
F144: 230 | G144: DOM
A147: LU 30 | F147: =330+180 -> 510

Sheet JULIO 25
B1: GASTOS MP | C1: GASTOS TRANSFER | D1: GASTOS EFT | E1: OBSERVACIONES Y NOTAS | F1: RETIROS DE CAJA | G1: NOTAS | H1: RETIROS HERNAN | I1: RETIROS CECI
A2: MA 1 | F2: =140+200 -> 340
A8: MIE 2 | B8: 39600 | E8: choco tutto farra | F8: =300+230-270+50 -> 310 | G8: habia 530 -270 sueldo mary
A15: JUE 3 | B15: 8130 | E15: caja tortas tutto farra | F15: =260+250 -> 510
A21: VIE 4 | F21: =120+170 -> 290
A27: SAB 5 / DOM 6 | G27: tm 170, se uso p sueldo seba
G28: tt se uso p sueldo chris no se cuanto habia
F30: 350 | G30: Dom
G31: ok
A33: LU 7 | B33: 54050 | E33: harina almendras vitalcer | F33: 300 | G33: tm ok
F34: 130 | G34: tt ok
H35: -100 | J35: transfer galicia 15/6
H36: -81.4 | J36: mp 16/6
I37: -60 | J37: mp 15/6
I38: -26 | J38: mp 14/6
A39: MA 8 | B39: 20200 | E39: choco tutto farra | F39: 350 | G39: tm ok | H39: =680 -> 680 | J39: deposito en galicia 17/6
H40: -128.7 | J40: galicia 17/6
B41: 12700 | E41: crema | F41: 130 | G41: tt ok | H41: -26 | J41: galicia 22/6
H42: -200 | J42: galicia 26/6
H43: -70 | J43: efectivo caja 25/6
H44: -100 | J44: galicia 27/6
H45: -64.9 | J45: 2/7 mp
H46: -50 | J46: galicia 4/7
I47: -39 | J47: mp 4/7
A48: MIE 9 FERIADO | G48: tm y tt | H48: -30 | J48: galicia 10/7
G49: habia 400 se uso para mary | H49: -268.5 | J49: deuda de mp que se debito
H50: -32 | J50: cafe margot galicia 12/7
H51: =-50-13 -> -63 | J51: galicia 13/7
I52: -51 | J52: mp rappi
H53: -150 | J53: mp 21/7
A54: JUE 10 | B54: 2300 | E54: glucosa tutto farra | F54: 320 | G54: tm ok | I54: -216 | J54: 27/7 mp
B55: 18145 | E55: BOLSAS DOYPACK CAFE | F55: 60 | G55: tt ok | H55: -100 | J55: 27/7 galicia
D56: 100000 | E56: marcelo | H56: -60 | J56: 27/7 galicia
H57: -10.6 | J57: 29/07/2025 mp
I58: -103 | J58: 31/7 mp
H59: =-95-14 -> -109 | J59: 1/8 galicia
H60: -50 | J60: 1/8 galicia
A61: VIE 11 | F61: 90 | G61: tm habia 250 se uso 160 mary | H61: -9.2 | J61: 3/08/2025 mp
H62: -296.2 | J62: 11/8 deuda de mp que se debito
F63: 250 | G63: tt | H63: -10.9 | J63: 15/8 mp
H64: -90 | J64: 18/8 galicia edesur
I65: -134.5 | J65: 23/8 reparacion auto
H66: -27.7 | J66: 25/08 galicia
H67: -87 | J67: 26/08/2025 galicia
I68: -96 | J68: del 18 al 23/8 mp
A69: SAB 12 / DOM 13 | G69: tm 272 se uso para sueldos | I69: -200 | J69: 45898
F70: 100 | G70: tt | H70: -470.3 | I70: -477.7 | J70: 04/09 compesacion
H71: 300
G72: dom | H72: -1000 | I72: -500 | J72: credito
I73: -500 | J73: 6/9 retiro de eft
I74: -430 | J74: 13/9 retiro eft
H75: =-(113.4+17.15) -> -130.55 | J75: 13/9 carne asado
H76: -250.5 | J76: 13/9deuda personal mp
I77: -400 | J77: 20/9 retiro eft
H79: =SUM(H35:H78) -> -3086.45 | I79: =SUM(I37:I78) -> -3098.7 | J79: total
A80: LU 14 | F80: 300 | G80: ok | H80: ok
B81: 88200 | E81: chocolate | F81: 120 | G81: tt
A86: MA 15 | G86: tm habia 270 se uso p/ sueldo mary aguinaldo
F87: 240 | G87: tt
A92: MIE 16 | F92: 170 | G92: tm
F93: 90 | G93: tt
A98: JUE 17 | F98: 200 | G98: tm
F99: 120 | G99: tt
A104: VIE 18 | F104: 180 | G104: tm
F105: 202 | G105: tt
A110: SAB 19 / DOM 20 | G110: el resto se uso p sueldo de chris, mat y seba
F111: - | G111: SAB 110 se uso p/mariana
F113: - | G113: DOM 340 se uso p/mariana
A116: LU 21 | B116: 22200 | E116: colorantes | G116: tm 370 se uso p/mariana
B117: 48800 | E117: harina de almendras 2k | F117: 160 | G117: tt
A122: MA 22 | B122: 58800 | E122: chocolate tutto farra | G122: tm 270 se uso p/mariana
F123: 260 | G123: tt
A128: MIE 23 | F128: 250 | G128: tm
F129: 300 | G129: tt
A134: JUE 24 | B134: 5000 | E134: mouse buganza | F134: 230 | G134: tm
G135: tt 230 se uso sueldo mary
A140: VIE 25 | F140: =160-50 -> 110 | G140: tm 50 se uso sueldo mary
F141: 220 | G141: tt
A146: SAB 26 / DOM 27 | G146: 200 se uso p/ sueldo de chris
G147: tt habia 350 se uso p sueldo mary
F149: 170 | G149: DOM
G150: habia 360-190 (mary) quedo170
A152: LU 28 | F152: 240 | G152: tm
F153: 260 | G153: tt
A158: MA 29 | F158: 270 | G158: tm
F159: 150 | G159: tt
A164: MIE 30 | F164: 190 | G164: tm
F165: 160 | G165: tt
A170: JUE 31 | F170: 260 | G170: tm
F171: 150 | G171: tt
A176: vie 1 | F176: 170 | G176: tm
F177: =130+80 -> 210 | G177: TT
A182: TOTAL OTROS GASTOS VARIOS
B184: =SUM(B8:B183) -> 378125

Sheet AGOSTO 25
B1: GASTOS MP | C1: GASTOS TRANSFER | D1: GASTOS EFT | E1: OBSERVACIONES Y NOTAS | F1: RETIROS DE CAJA | G1: NOTAS | H1: RETIROS HERNAN | I1: RETIROS CECI
A2: VIE 1
A8: SAB 2 / DOM 3 | F8: 20 | G8: SAB habia 290 se uso 270 para mary
G9: 400 TM se uso sueldo chris y mat
G10: TT
G11: DOM habia 270 se uso alquiler
A15: LU 4 | G15: tm habia 440 se uso alquiler
F17: 200 | G17: tt
A21: MA 5 | F21: 170 | G21: tm
F22: 140 | G22: tt
A27: MIE 6 | F27: 260 | G27: tm
F28: 140 | G28: tt
A33: JUE 7 | F33: 250 | G33: tm
F34: 310 | G34: tt
A39: VIE 8 | F39: 230 | G39: tm
F40: 230 | G40: TT
A45: SAB 9 / DOM 10 | B45: 15500 | E45: breik impresion de menu | F45: 70 | G45: TM habia 230 se uso 160 p sueldos ok
F46: 380 | G46: TT ok
F48: 440 | G48: DOM ok
A51: LU 11 | G51: tm habia 270 se uso para sueldo mary
F52: 280 | G52: tt ok
A57: MA 12 | F57: 550 | G57: tm y tt ok
A63: MIE 13 | F63: 370 | G63: tm ok
F64: 160 | G64: tt ok
A69: JUE 14 | B69: 4000 | E69: gas aerosol | F69: 400 | G69: tm ok | H69: =SUM(H35:H68) -> 0 | I69: =SUM(I37:I68) -> 0 | J69: total
G70: tt habia 160 lo retiro hernan
A75: VIE 15 | F75: 300 | G75: ok
A81: SAB 16/ DOM 17 | G81: tm y tt habia 430 se deposito todo en galicia para edesur
G84: dom habia 170 se uso para suss
A87: LU 18 | G87: habia 370 se uso para suss
A93: MA 19 | G93: tm se uso para suss
F94: 10 | G94: tt se uso 70 para mary
A99: MIE 20 | F99: 290 | G99: tm
G100: tt habia 200 se uso para mary
A105: JUE 21 | F105: 400 | G105: tm y tt
A111: VIE 22 | F111: 320 | G111: tm y tt
A117: SAB 23/ DOM 24 | F117: 250 | G117: tm ok
F118: 300 | G118: tt ok
F119: 110 | G119: sobrante de la semana ok
F120: 310 | G120: dom ok
A123: LU 25 | F123: 300 | G123: tm ok
F124: 100 | G124: tt ok
A129: MA 26 | F129: 300 | G129: tm y tt ok
A135: MIE 27 | B135: 9500 | E135: resma de hojas | F135: 180 | G135: tm ok
F136: 80 | G136: tt ok
A141: JUE 28 | F141: 400 | G141: tm y tt ok
A147: VIE 29 | F147: 300 | G147: tm
F148: 200 | G148: tt se uso p alquiler
A153: SAB 30 / DOM 31 | F153: 510 | G153: tm y tt
F156: 160 | G156: dom
B159: TOTAL GASTOS VARIOS
B160: =SUM(B2:B159) -> 29000
A165: vie 1

Sheet SEPTIEMBRE 25
B1: GASTOS MP | C1: GASTOS TRANSFER | D1: GASTOS EFT | E1: OBSERVACIONES Y NOTAS | F1: RETIROS DE CAJA | G1: NOTAS | H1: RETIROS HERNAN | I1: RETIROS CECI
A2: LU 1
F3: 280 | G3: tm y tt
A8: MA 2 | D8: 12582 | E8: fp | F8: 30 | G8: habia 500 (-270 mary -200 agus tm y tt)
D9: 4585 | E9: fp
D10: 12600 | E10: carrefour
D11: 1670 | E11: carrefour
D12: 1188 | E12: carrefour
D13: 12200 | E13: panceta
A15: MIE 3 | F15: 440 | G15: tm y tt
A21: JUE 4 | F21: 320 | G21: tm y tt
F22: 60 | G22: la serenisima no se uso
A27: VIE 5 | F27: 600 | G27: tm y tt
A33: SAB 6 /DOM 7 | D33: 3484.85 | E33: fp | F33: 540 | G33: tm y tt | H33: ok
F36: 240 | G36: dom | H36: ok
A39: LU 8 | F39: 540 | G39: tm y tt | H39: ok
A45: MA 9 | D45: 67721 | E45: NUEVO EMPORIO | F45: 300 | G45: tm y tt
D46: 19000 | E46: crema
A51: MIE 10 | F51: 300 | G51: tm y tt | H51: ,
A57: JUE 11 | D57: 4255 | E57: fp | F57: 450 | G57: tm
G58: habia 270 se uso p mary tt
A63: VIE 12 | F63: 460 | G63: TM Y TT | H63: ok
A69: SAB 13 DOM 14 | F69: 360 | G69: sab tm ok | H69: =SUM(H35:H68) -> 0 | I69: =SUM(I37:I68) -> 0 | J69: total
F70: 200 | G70: sab tt ok
F72: 200 | G72: dom ok
A75: LU 15 | B75: 4200 | E75: twin papelera | F75: 420 | G75: tm y tt ok
B76: 3600 | E76: twin papelera
A81: MA 16
F82: 320 | G82: tm y tt ok
A87: MIE 17 | F87: 330 | G87: tm y tt ok
A93: JUE 18 | F93: 400 | G93: tm y tt ok
A99: VIE 19 | F99: =160+90+120 -> 370 | G99: tm y tt
A105: SAB 20 DOM 21 | F105: =370+160 -> 530 | G105: Sab tm y tt se saco 150 p alquiler
G106: y 270 p sueldo mary (quedo110) ok
F108: 230 | G108: Dom ok
A111: LU 22 | D111: 3149 | E111: carrefour | F111: 170 | G111: tm ok
D112: 3646 | E112: carrefour | F112: 210 | G112: tt ok
A117: MA 23 | D117: 5700 | E117: libreria | F117: 120 | G117: se saco 100 para alquiler (quedo 20) ok
A123: MIE 24 | F123: 350 | G123: tm ok
F124: 160 | G124: tt ok
A129: JUE 25 | D129: 3000 | E129: Carrefour | F129: 520 | G129: tm y tt ok
C130: 7900 | E130: limpieza LJ
A135: VIE 26 | B135: 19310 | E135: colorante rojo | F135: 500 | G135: tm y tt ok
A141: SAB 27 DOM 28 | F141: 400 | G141: sab ok
F144: 140 | G144: dom ok
A147: LU 29 | F147: 200 | G147: tm ok
F148: 270 | G148: tt ok
A153: MA 30 | F153: 170 | G153: tm ok
F154: 150 | G154: tt ok
A165: vie 1

Sheet OCTUBRE 25
B1: GASTOS MP | C1: GASTOS TRANSFER | D1: GASTOS EFT | E1: OBSERVACIONES Y NOTAS | F1: RETIROS DE CAJA | G1: NOTAS | H1: RETIROS HERNAN | I1: RETIROS CECI
A2: MIE 1 | F2: 260 | G2: tm ok | H2: -100 | I2: -100 | J2: ef 1/10
F3: 330 | G3: tt (se uso 270 para mary) 60 quedo | H3: -180 | J3: transfer 1/10
I4: -180 | J4: eft 4/10
I6: -220 | J6: 8/10 galicia alquiler
H7: -135
A8: JUE 2 | F8: 250 | G8: tm ok | H8: -85 | J8: compensado con lau
F9: 60 | G9: tt ok | H9: -292.4 | J9: deuda personal mp 11/10
F10: 110 | G10: tt ok | H10: -100 | J10: ef sobre 13/10
I11: -59 | J11: edesur desde mp 17/10
H12: -19 | J12: seguro moto h
I13: -350 | J13: mastercard 17/10
A15: VIE 3 | F15: 220 | G15: tm ok | H15: =SUM(H2:H14) -> -911.4 | I15: =SUM(I2:I14) -> -909 | J15: Total
F16: 200 | G16: tt ok
H18: -69 | J18: 23/10 debito
H19: -30 | J19: super chino 21/10
A20: SAB 4 / DOM 5 | F20: 240 | G20: tm ok | I20: -27 | J20: rappi 22/10
G21: tt 130 habia se pago mat | I21: -37 | J21: claro 22/10
I22: -26 | J22: py 19/10
F23: 100 | G23: DOM ok | I23: -20 | J23: apple 18/10
I24: -17 | J24: apple 18/10
I25: -39 | J25: apple 18/10
A26: LU 6 | F26: 370 | G26: tm ok | H26: -18 | J26: 21/10 daniel eduardo gomez
F27: 170 | G27: tt ok | I27: -30 | J27: apple 20/10/2025
H28: =-28-34 -> -62 | J28: 22/10articulos tutto farra cami
H29: -30 | J29: adelanto juan
H30: -10 | J30: cajas cami figura en cierre 25/10
H31: -50 | J31: mp 27/10
I32: -34 | J32: rappi 29/10
H33: -100 | I33: -150 | J33: efectivo 29/10
H34: -250 | J34: ef 18/11
A35: MA 7 | F35: 210 | G35: tm ok | I35: -350 | J35: transfer tarjeta
F36: 160 | G36: tt ok | H36: -41.9 | J36: 28/11 pizzeria galicia
F37: 40 | G37: tt ok | H37: -20 | J37: bocanada 28/11 galicia
H38: -46 | J38: Cubetera 6/11
I39: -557 | J39: transfer lau 6/11
H40: -360 | J40: ef 8/11
A41: MIE 8 | F41: 260 | G41: tm ok | H41: -40 | J41: el deposito en galicia era de 360 pero se depositaron 320
F42: 100 | G42: tt ok | H42: -20 | J42: rh vie 8/11 en maxirest?
H43: -6 | J43: temple galicia 3/12
H44: -20 | J44: 2/12 gañicia x mp
H45: -10 | J45: 1/12 transf galicia a mp personal
H46: -19 | J46: seguro moto
A47: JUE 9 | F47: 200 | G47: tm ok | H47: -19 | J47: g suit
F48: 260 | G48: tt ok | H48: -31 | J48: 25/11 galicia
I49: -29 | J49: apple mp
H50: -81.3 | J50: 25/11 debin galicia?
H51: -100 | J51: 20/11 debin galicia?
H52: =199 -> 199 | J52: 6/12 pago metrogas de bbva
I53: -500 | J53: 6/12 ef
H54: -100 | J54: 12/12 ef
H55: -39 | J55: py 11/12
I56: -400 | J56: 10/12 transfer galicia
H57: -120 | J57: h se llevo 200 y yo 80, la dif es 120 13/12/2025
H58: -12.5 | J58: deuda mp hasta sab 20 10.29am
H59: -62.1 | J59: lengua y peceto 20/12
H60: -110 | J60: luz proyector 15/12 efete
H61: -160 | J61: retiro h 30/12
H62: -76 | J62: farma costa 2/1
H63: -50 | J63: retira cami 29/12 era para h
I64: -100 | J64: ef 3/1
H65: -22 | J65: 30/12 golosinas pan dulce
H66: -140 | J66: 20/1 galicia
H67: -250 | I67: -250 | J67: 21/1 MP AMBOS
H68: -60 | J68: galicia 21/1 y 22/1
H69: -44.5 | J69: galicia 23/1
H70: -26 | J70: galicia 23/1
H71: =-60-150 -> -210 | I71: -210 | J71: h uso 23/1 galicia y c compenso en ef
H72: -50 | J72: h ef 24/1
H73: -10 | J73: 26/1 galicia
A77: VIE 10 | F77: 340 | G77: tm y tt ok | H77: =SUM(H30:H76) -> -2567.3 | I77: =SUM(I30:I76) -> -2580
A83: SAB 11/ DOM 12 | F83: 270 | G83: tm se uso para mary
F84: 210 | G84: tt ok
F86: 370 | G86: DOM ok
A89: LU 13 | F89: 200 | G89: tm ok
F90: 200 | G90: tt OK se uso 100 hernan
A95: MA 14 | J95: total
B96: 150000 | E96: horno pauna service | F96: 330 | G96: tt OK
F97: 80 | G97: TT OK
A101: MIE 15 | F101: 230 | G101: tm OK
F102: 120 | G102: tt OK
A107: JUE 16 | F107: 200 | G107: tm OK
F108: 130 | G108: tt OK
A113: VIE 17 | F113: 230 | G113: tm ok
F114: 20 | G114: tt ok
A119: SAB 18/ DOM 19 | G119: tm se repartio el jueves 200
F120: 210 | G120: tt ok
F123: 130 | G123: dom ok
A125: LU 20 | F125: 400 | G125: tm ok
F126: 110 | G126: tt ok
F127: 30 | G127: tt ok
A131: MA 21 | B131: 10640.1 | E131: frutas premium | F131: 200 | G131: tm oki
F132: 70 | G132: tt ok
A137: MIE 22 | F137: 400 | G137: tm ok
F138: 60 | G138: tt ok
A143: JUE 23 | F143: 120 | G143: tt ok
F144: 200 | G144: tm ok
A149: VIE 24
F150: 130 | G150: tm ok
F151: 150 | G151: tt ok
...

Sheet NOVIEMBRE 25
B1: GASTOS MP | C1: GASTOS TRANSFER | D1: GASTOS EFT | E1: OBSERVACIONES Y NOTAS | F1: RETIROS DE CAJA | G1: NOTAS | H1: RETIROS HERNAN | I1: RETIROS CECI
A2: SAB 1 / DOM 2 | F2: 120 | G2: TM
F3: 110 | G3: TT
F5: 160 | G5: DOM
A8: LU 3 | F8: 200 | G8: TM
F9: 220 | G9: tt
A15: MA 4 | F15: 190 | G15: tm
F16: 200 | G16: tt
A20: MIE 5 | F20: 200 | G20: tm
F21: 180 | G21: tt
A26: JUE 6 | F26: 270 | G26: tt
F27: 200 | G27: tm
A35: VIE 7 | F35: 300 | G35: tm
G36: hasta aca quedo 490 en ef
F37: 230 | G37: tt
A41: SAB 8 /DOM9 | F41: 120 | G41: tm OK
F42: =260+90 -> 350 | G42: tt OK
F44: 210 | G44: dom OK
A47: lu 10 | F47: 400 | G47: tm OK
F48: 100 | G48: tt OK
A53: ma 11 | C53: harina de almendras | G53: transfer a Agustín 33660
F55: 180 | G55: tm OK
F56: 220 | G56: tt OK
A59: mie 12 | F59: 300 | G59: tm OK
F60: 200 | G60: TT OK
A65: jue 13 | F65: 370 | G65: tm OK
F66: 270 | G66: tt OK
A71: vie 14 | F71: 170 | G71: TM OK
F72: 60 | G72: tt OK se uso para sueldo milo
A77: sab 15/ dom 16 | F77: 230 | G77: sab ok habia 220 ok
F80: 210 | G80: dom ok
A83: LU 17 | F83: 240 | G83: tm ok
F84: 200 | G84: tt ok
A89: MA 18 | F89: 260 | G89: tm ok
F90: 80 | G90: tt ok
A95: MIE 19 | F95: 200 | G95: tm cami ok
F96: 150 | G96: tt OK
A101: JUE 20 | B101: 91301.76 | E101: pampa vida | F101: 170 | G101: tm ok
F102: 200 | G102: tt OK
A107: VIE 21 | F107: 360 | G107: tm y tt ok
A113: SAB 22 / DOM 23 | F113: 200 | G113: tm OK
F114: 90 | G114: tt OK
F116: 170 | G116: dom OK
A119: LU 24 | F119: 290 | G119: tm y tt OK
A125: MA 25 | F125: 200 | G125: tm OK
F126: 250 | G126: tt OK
A131: MIE 26 | F131: 220 | G131: tm OK
F132: 60 | G132: tt OK
A137: JUE 27 | F137: 170 | G137: tm OK
F138: 130 | G138: tt OK
A143: VIE 28 | F143: 200 | G143: tm
F144: 180 | G144: tt
D146: 43000 | E146: fumigador
A149: SAB 29/ DOM 30
A167: vie 1

Sheet DICIEMBRE 25
B1: GASTOS MP | C1: GASTOS TRANSFER | D1: GASTOS EFT | E1: OBSERVACIONES Y NOTAS | F1: RETIROS DE CAJA | G1: NOTAS | H1: RETIROS HERNAN | I1: RETIROS CECI
A8: LU 1 | B8: 30116 | E8: NUEVO EMPORIO | F8: 290 | G8: quedo descontando alquiler 700
A15: MA 2 | F15: 220 | G15: tm ok
F16: 120 | G16: tt ok
F17: 50 | G17: tt, se usaron?
A20: MIE 3 | C20: 121000 | E20: matafuegos | F20: 280 | G20: tm ok
F21: 150 | G21: tt ok
A26: JUE 4 | C26: 50000 | E26: fito maq cafe | F26: 200 | G26: tm ok
F27: 110 | G27: tt ok
A35: VIE 5 | F35: 100 | G35: tm ok
F36: 110 | G36: tt ok
A41: SAB 6 /DOM 7 | B41: 17000 | E41: breik | G41: 200 tm se uso milo y seba
F42: 130 | G42: tt
F44: 120 | G44: dom
A47: lu 8 | F47: 130 | G47: tm
F48: 240 | G48: tm?
A53: ma 9 | F53: 130 | G53: tm
F54: 220 | G54: tt
A59: mie 10 | F59: 300 | G59: tm (se uso 270 mary)
F60: 220 | G60: tt
A65: JUE 11 | F65: 200 | G65: TM
F66: 160 | G66: tt
B67: 21150 | E67: breik marcadores
A71: VIE 12 | F71: 120 | G71: tm
G72: retiro hernan 100 en ef
C73: 170000 | E73: cobo licuadora | F73: 190 | G73: TT
A77: SAB 13/ DOM14 | F77: 200 | G77: TM
F78: 150 | G78: tt OK
F80: 250 | G80: dom OK
A83: LU 15 | F83: 230 | G83: tm OK
F84: 110 | G84: tt
A89: MA 16 | F89: 200 | G89: tm OK
C90: 380000 | E90: damian heladera | F90: 340 | G90: tt OK
A95: MIE 17 | F95: 260 | G95: tm OK
B96: 13900 | E96: cacao vitalcer | F96: 360 | G96: tt se usó 200 para cafe OK
B97: 50000 | E97: cintas pablo bustamante
A101: JUE 18 | F101: 300 | G101: tm
F102: 110 | G102: tt OK
A107: VIE 19 | F107: 290 | G107: tm OK
F108: 130 | G108: tt OK
A113: SAB 20 / DOM 21 | F113: 230 | G113: tm OK se uso sueldos
F114: 150 | G114: tt
F115: 110 | G115: dom
A119: LU 22 | F119: 280 | G119: tm
F120: 400 | G120: tt
A125: MA 23 | F125: 170 | G125: tm
F126: 170 | G126: tt
A131: MIE 24 | F131: 160 | G131: tm y tt
A137: JUE 25 | G137: feriado
A143: VIE 26 | F143: 200 | G143: tm y tt
A149: SAB 27/ DOM 28 | F149: 200 | G149: tm ok
F150: 340 | G150: tt alq
F152: 130 | G152: dom ok
A155: LU 29 | F155: 110 | G155: tm ok
B156: 91301.76 | E156: pampa vida | F156: 130 | G156: tt ok
A161: MA 30 | F161: 100 | G161: tm alq
F162: 220 | G162: tt ok
A167: MIE 31 | F167: 100 | G167: tm y tt ok
A173: vie 2 | F173: 270 | G173: tm ok se uso para mary
A179: sab 3/dom4 | F179: 160 | G179: tm
G180: 50 se uso para milo
G181: tt
G182: dom
B188: =SUM(B2:B187) -> 223467.76 | C188: =SUM(C20:C187) -> 721000

Sheet CIERRE 2026
A1: < | B1: FECHA | C1: VENTA DIARIA | D1: ZETA | E1: CAJA | F1: CAMBIO | G1: TARJETAS | H1: RAPPI PAGO-ONLINE | I1: PEDIDOSYA PAGO-ONLINE | J1: CTA CTE | K1: MERCADO | L1: EFECTIVO DEL DIA | M1: RETIROS | N1: CAJA
A2: LUNES | B2: 45292
A3: MARTES | B3: 45293 | C3: 566040 | D3: 358700 | E3: 3900 | F3: 7500 | G3: =8400+186800 -> 195200 | H3: 132856 | J3: 33700 | K3: 61300 | L3: 163640
A4: MIERCOLES | B4: 45294 | C4: 531340 | D4: 408580 | E4: 3900 | F4: 10400 | G4: =135000+7000 -> 142000 | H4: 152707 | K4: 122080 | L4: 124160
A5: JUEVES | B5: 45295 | C5: =1193100-396200 -> 796900 | D5: 549460 | E5: =600+1500+2200+250+500+800+240 -> 6090 | F5: =10400 -> 10400 | G5: =9500+247550 -> 257050 | H5: 129775 | J5: =465500-396200 -> 69300 | K5: 149610 | L5: 187490
A6: VIERNES | B6: 45296 | C6: =1639650-796900-396200 -> 446550 | D6: 296500 | E6: 7800 | F6: 10300 | G6: 179800 | H6: 92371 | J6: 31400 | K6: =212610-K5 -> 63000 | L6: =249340-L5 -> 61850
A7: SABADO | B7: 45297 | C7: 511010 | D7: 414500 | E7: =700+2100+500+500+800+280 -> 4880 | F7: 4400 | G7: =238000+24700 -> 262700 | H7: 69621 | K7: 95700 | L7: 85110
A8: DOMINGO
A9: LUNES | B9: 45299 | C9: 500720 | D9: 350950 | E9: 4800 | F9: 4400 | G9: 155100 | H9: 69936 | K9: 116800 | L9: 155370
A10: MARTES | B10: 45300 | C10: 527390 | D10: 368840 | E10: =1000+400+750+500+840+240 -> 3730 | F10: =4400 -> 4400 | G10: =123810+6200 -> 130010 | H10: 173866.5 | K10: 62600 | L10: 157750
A11: MIERCOLES | B11: 45301 | C11: 670100 | D11: 495650 | E11: =2000+1000+1200+300+500+840+250 -> 6090 | F11: 4400 | G11: =211000+23700 -> 234700 | H11: 111871 | J11: 26800 | K11: 132200 | L11: 148750
A12: JUEVES | B12: 45302 | C12: 732930 | D12: 647150 | E12: =800+2500+700+550+500+880+220 -> 6150 | F12: =4400 -> 4400 | G12: =162600+106000 -> 268600 | H12: 207310.5 | K12: 138700 | L12: 94280
A13: VIERNES | B13: 45303 | C13: 549550 | D13: 450950 | E13: 1000 | F13: 4400 | G13: =228270+6800 -> 235070 | H13: 86871 | K13: 131000 | L13: 98600
A14: SABADO | B14: 45304 | C14: 548110 | D14: 456960 | E14: 1800 | F14: 2400 | G14: =218760+69900 -> 288660 | H14: 88886 | K14: 79500 | L14: 91150
A15: DOMINGO
A16: LUNES | B16: 45306 | C16: 630080 | D16: 480860 | E16: 3500 | F16: 1400 | G16: =200500+49300+11400 -> 261200 | H16: 95947 | J16: 24200 | K16: 131960 | L16: 124120
A17: MARTES | B17: 45307 | C17: 549500 | D17: 438150 | E17: 5300 | F17: 4400 | G17: =212000+6500 -> 218500 | H17: 115901 | K17: 92750 | L17: 122350
A18: MIERCOLES | B18: 45308 | C18: 714720 | D18: 568600 | E18: 4500 | F18: 7400 | G18: =174600+65400 -> 240000 | H18: 156310 | K18: 139000 | L18: 130220
A19: JUEVES | B19: 45309 | C19: 750160 | D19: 592160 | E19: =1200+1200+900+500+820+250 -> 4870 | F19: 7400 | G19: =11000+248500 -> 259500 | H19: 195000 | J19: 24700 | K19: 154160 | L19: 138900
A20: VIERNES | B20: 45310 | C20: 606205 | D20: 479460 | E20: =1000+1400+950+500+800+250 -> 4900 | F20: 10400 | G20: =5200+261400 -> 266600 | H20: 92811 | K20: 89960 | L20: 126745
A21: SABADO | B21: 45311 | C21: 432800 | D21: 270730 | E21: =1000+900+900+500+820+240 -> 4360 | F21: 6400 | G21: =159500+3000 -> 162500 | H21: 60951 | K21: 58130 | L21: 159970
A22: DOMINGO
A23: LUNES | B23: 45313 | C23: 447650 | D23: 287450 | E23: 8000 | F23: 14400 | G23: 166100 | H23: 38980 | K23: 105200 | L23: 145700
A24: MARTES | B24: 45314 | C24: 776700 | D24: 619600 | E24: 5000 | F24: 4400 | G24: =159000+71000 -> 230000 | H24: 202181 | K24: 167900 | L24: 166200
A25: MIERCOLES | B25: 45315 | C25: 507630 | D25: 396210 | G25: 83350 | H25: 83510 | K25: 95800 | L25: 127480
A26: JUEVES | B26: 45316 | C26: =831440-210100 -> 621340 | D26: 689410 | G26: 119200 | H26: 102901 | K26: 76600 | L26: 139630
A27: VIERNES | B27: 45317 | C27: 552470 | D27: 431850 | E27: 6500 | F27: 6600 | G27: =190100+14000 -> 204100 | H27: 125551 | K27: 140200 | L27: 124920
A28: SABADO | B28: 45318 | C28: 446070 | D28: 322740 | E28: 4500 | F28: 6500 | G28: 144340 | H28: 97156 | K28: 76600 | L28: 128730
A29: DOMINGO
A30: LUNES | B30: 45320 | C30: 604740 | D30: 431040 | E30: 2600 | F30: =1600+3000+2000 -> 6600 | G30: =192800+1100 -> 193900 | H30: 127400 | K30: 118700 | L30: 160100
A31: Martes | B31: 45321 | C31: 495230 | D31: 386430 | E31: =500+1900+750+200+160+300 -> 3810 | F31: 4600 | G31: =6500+187030 -> 193530 | H31: 77500 | K31: 142100 | L31: 87000
A32: Miercoles | B32: 45322 | C32: 518050 | D32: 423980 | E32: 3200 | F32: 4600 | G32: 155400 | H32: 115510 | K32: 184680 | L32: 70770
A33: TOTAL | C33: =SUM(C2:C32) -> 15033985
A34: JUEVES | B34: 45323 | C34: 552340 | D34: 441800 | F34: 3600 | G34: 229500 | H34: 94400 | K34: 123900 | L34: 81540
A35: VIERNES | B35: 45324 | C35: 552810 | D35: 383410 | F35: 11600 | G35: 123600 | H35: 92456 | K35: 134210 | L35: 165400
A36: SABADO | B36: 45325 | C36: 432660 | D36: 344900 | E36: =1500+1500+700+400+310 -> 4410 | F36: =2000+1000+6000 -> 9000 | G36: =14900+223100 -> 238000 | H36: 36600 | K36: 56600 | L36: 87760
A37: DOMINGO
A38: LUNES | B38: 45327 | C38: 649730 | D38: 501120 | E38: 3000 | F38: 7500 | G38: 233740 | H38: 137261 | K38: 118500 | L38: 168390
A39: MARTES | B39: 45328 | C39: 659570 | D39: 478990 | E39: 3000 | F39: 3500 | G39: 230810 | H39: 135871 | K39: 128880 | L39: 168080
A40: MIERCOLES | B40: 45329 | C40: 710220 | D40: 526620 | E40: 3500 | F40: 3500 | G40: =250570+21600 -> 272170 | H40: 138610 | K40: 118700 | L40: 189200
A41: JUEVES | B41: 45330 | C41: 693630 | D41: 458600 | E41: 3500 | F41: 3500 | G41: 296450 | H41: 40483 | K41: 165530 | L41: 170730
A42: VIERNES | B42: 45331 | C42: 460060 | D42: 355300 | E42: 5730 | F42: 3500 | G42: 184200 | H42: 79800 | K42: 65490 | L42: 137720
A43: SABADO | B43: 45332 | C43: 622970 | D43: 451280 | F43: 11500 | G43: 163900 | H43: 81611 | K43: 119680 | L43: 161690
A44: DOMINGO
A45: LUNES | B45: 45334 | C45: 534760 | D45: 418560 | E45: 5000 | F45: 9500 | G45: 145500 | H45: 34771 | K45: 110140 | L45: 122500
A46: MARTES | B46: 45335 | C46: 523205 | D46: 428605 | E46: 5400 | F46: 9500 | G46: 286900 | H46: 182000 | K46: 159005 | L46: 116000
A47: MIERCOLES | B47: 45336 | C47: 838350 | D47: 608400 | E47: 500 | F47: 9500 | G47: 178320 | H47: 141900 | K47: 216000 | L47: 222000
A48: JUEVES | B48: 45337 | C48: 799600 | D48: 660680 | G48: 352500 | H48: 189800 | K48: 324000 | L48: 387850
A49: VIERNES | B49: 45338 | C49: 609960 | D49: 500700 | G49: 223900 | H49: 110446 | K49: 182000 | L49: 103660
A50: SABADO | B50: 45339 | C50: 599610 | D50: 435250 | E50: 3000 | F50: =3600+8000 -> 11600 | G50: 286850 | H50: 12700 | K50: 159500 | L50: 164360
A51: DOMINGO
A52: LUNES | B52: 45341 | C52: 595240 | D52: 446920 | G52: 277300 | H52: 79750 | K52: 121820 | L52: 147920
A53: MARTES | B53: 45342 | C53: 662170 | D53: 500410 | E53: =2000+3400+1400+200+600+200+250 -> 8050 | F53: =1000+1000+1000+500 -> 3500 | G53: =254200+28400 -> 282600 | H53: 108150 | K53: 95060 | L53: 159660
A54: MIERCOLES | B54: 45343 | C54: 661440 | D54: 474300 | E54: 6000 | F54: 3500 | G54: 235200 | H54: 156600 | K54: 70600 | L54: 193340
A55: JUEVES | B55: 45344 | C55: 696780 | D55: 587780 | E55: 6000 | F55: 3500 | G55: =231800+7600 -> 239400 | H55: 134055 | K55: 181200 | L55: 109000
A56: VIERNES | B56: 45345 | C56: 562300 | D56: 451400 | E56: 6000 | F56: 3500 | G56: 233700 | H56: 72255 | K56: 181500 | L56: 106100
A57: SABADO | B57: 45346 | C57: 773900 | D57: 567100 | E57: 6000 | F57: 11500 | G57: 359470 | H57: 70200 | K57: 119330 | L57: 238400
A58: DOMINGO
A59: LUNES | B59: 45348 | C59: 653040 | D59: 537640 | E59: =600+1500+1900+1550+200+740+200+200 -> 6890 | F59: 11500 | G59: =90500+103900 -> 194400 | H59: 110231 | K59: 231740 | L59: 106300
A60: Martes | B60: 45349 | C60: 588360 | D60: 449620 | G60: 255580 | H60: 90900 | K60: 104340 | L60: 138540
A61: MIERCOLES | B61: 45350 | C61: 685580 | D61: 489000 | F61: 3500 | G61: 250700 | H61: 109626 | K61: 146500 | L61: 202080
A62: Jueves | B62: 45351 | C62: 1338120 | D62: 1188960 | F62: 3500 | G62: 731800 | H62: 201311 | K62: 226860 | L62: 181160
A63: TOTAL | C63: =SUM(C34:C62) -> 16456405
A64: VIERNES | B64: 45352 | C64: 765740 | D64: 627400 | F64: 2500 | G64: 312700 | H64: 144381 | K64: 178800 | L64: 141740
A65: SÁBADO | B65: 45353 | C65: 605600 | D65: 492000 | G65: 213900 | H65: 81505 | K65: 102700 | L65: 113600
A66: DOMINGO | B66: 45354
A67: LUNES | B67: 45355 | C67: 534500 | D67: 459100 | F67: 2500 | G67: 126300 | H67: 138666 | K67: 127600 | L67: 75400
A68: MARTES | B68: 45356 | C68: 850260 | D68: 716700 | G68: 349400 | H68: 19115 | K68: 174900 | L68: 143460
A69: MIÉRCOLES | B69: 45357 | C69: 686210 | D69: 559100 | G69: 361200 | H69: 66215 | K69: 110500 | L69: 140110
A70: JUEVES | B70: 45358 | C70: 876350 | D70: 733560 | G70: 354300 | H70: 183315 | K70: 99380 | L70: 172890
A71: VIERNES | B71: 45359 | C71: 630640 | D71: 492840 | F71: 2500 | G71: 278900 | H71: 72105 | K71: 168540 | L71: 126500
A72: SÁBADO | B72: 45360 | C72: 697970 | D72: 556580 | F72: 2500 | G72: 299700 | H72: 165100 | K72: 165100 | L72: 139190
A73: DOMINGO | B73: 45361
A74: LUNES | B74: 45362 | C74: 461400 | D74: 337560 | F74: 2500 | G74: 146000 | H74: 68700 | K74: 112060 | L74: 111440
A75: MARTES | B75: 45363 | C75: 561770 | D75: 402790 | F75: 2500 | G75: 200130 | H75: 51700 | K75: 144750 | L75: 188780
A76: MIÉRCOLES | B76: 45364 | C76: 549780 | D76: 430960 | F76: 2500 | G76: 158800 | H76: 122900 | K76: 149660 | L76: 122320
A77: JUEVES | B77: 45365 | C77: 809220 | D77: 685500 | F77: 2500 | G77: 391900 | H77: 102110 | K77: 174700 | L77: 137720
A78: VIERNES | B78: 45366 | C78: =1528640-C77 -> 719420 | D78: 585770 | H78: 143121 | K78: =300870-K77 -> 126170 | L78: =293970-L77 -> 156250
A79: SÁBADO | B79: 45367 | C79: 545560 | D79: 429750 | F79: 2500 | G79: 228000 | H79: 64155 | K79: 155600 | L79: 115810
A80: DOMINGO | B80: 45368
A81: LUNES | B81: 45369 | C81: 615660 | D81: 461160 | G81: =44600+14600+198700 -> 257900 | H81: 65915 | K81: 124260 | L81: 177800
A82: MARTES | B82: 45370 | C82: 658390 | D82: 514780 | F82: 2500 | G82: 194800 | H82: 202959 | K82: 97180 | L82: 154710
A83: MIÉRCOLES | B83: 45371 | C83: 560030 | D83: 414960 | F83: 2500 | G83: 163300 | H83: 160250 | K83: 103010 | L83: 143370
A84: JUEVES | B84: 45372 | C84: =1726560-C83-C82 -> 508140 | D84: =857550-D83 -> 442590 | F84: 2500 | G84: =482900-G83 -> 319600 | H84: =482900-H83-H83 -> 162400 | K84: =482900-K83-K82 -> 282710 | L84: =421550-L83-L82 -> 123470
A85: VIERNES | B85: 45373 | C85: 635530 | D85: 558060 | F85: 2500 | G85: 263300 | H85: 110351 | K85: 195700 | L85: 69870
A86: SÁBADO | B86: 45374 | C86: 747520 | D86: 568280 | F86: 2500 | G86: 347600 | H86: 124721 | L86: 147040
A87: DOMINGO | B87: 45375
A88: LUNES | B88: 45376 | C88: 784860 | D88: 646500 | F88: 2500 | G88: 361100 | H88: 79200 | K88: 196400 | L88: 181160
A89: MARTES | B89: 45377 | C89: 926250 | D89: 776700 | F89: 2500 | G89: 391800 | H89: 130500 | K89: 261800 | L89: 161850
A90: MIÉRCOLES | B90: 45378 | C90: 884120 | D90: 766180 | F90: 2500 | G90: 327200 | H90: 102600 | K90: 293480 | L90: 140340
A91: JUEVES | B91: 45379 | C91: 712350 | D91: 620460 | F91: 2500 | G91: 365240 | H91: 63300 | K91: 185120 | L91: 88190
A92: VIERNES | B92: 45380 | C92: 662760 | D92: 485840 | F92: 2500 | G92: 275900 | H92: 140011 | K92: 78540 | L92: 188220
A93: SÁBADO | B93: 45381 | C93: 450230 | D93: 353060 | F93: 2500 | G93: 175300 | H93: 58600 | K93: 128610 | L93: 97170
A94: DOMINGO | B94: 45382
A95: TOTAL | C95: =SUM(C66:C94) -> 16068920
A96: LUNES | B96: 45383
A97: MARTES | B97: 45384 | C97: 740780 | D97: 658980 | F97: 2500 | G97: 297240 | H97: 128300 | K97: 249280 | L97: 73800
A98: MIÉRCOLES | B98: 45385 | C98: 539350 | D98: 439220 | F98: 2000 | H98: 100526 | K98: 71140 | L98: 90530
A99: JUEVES | B99: 45386 | C99: 1084390 | D99: 896260 | F99: 2000 | G99: 443400 | H99: 287600 | L99: 181930
A100: VIERNES | B100: 45387 | C100: 716170 | D100: 561090 | F100: 2000 | G100: 249750 | H100: 124800 | K100: 161200 | L100: 175180
...

Sheet ENERO 26
B1: GASTOS MP | C1: GASTOS TRANSFER | D1: GASTOS EFT | E1: OBSERVACIONES Y NOTAS | F1: RETIROS DE CAJA | G1: NOTAS | H1: RETIROS HERNAN | I1: RETIROS CECI
A2: VIE 2
A8: SAB 3 / DOM 4 | G8: TM, 50 se uso para milo 160 mary
F9: 180 | G9: TT ok
F11: 200 | G11: DOM ok
G12: habia 160 se uso para pagar cafe
A15: LU 5 | F15: 400 | G15: TM ok
F16: 210 | G16: TT ok
A20: MA 6 | B20: 99888 | E20: NUEVO EMPORIO | F20: 170 | G20: TM ok
F21: 150 | G21: TT ok
A26: MIE 7 | G26: 380 TM se uso todo p mary
F27: 170 | G27: TTok
A35: JUE 8 | B35: 242000 | E35: limpieza campana, debe certif | F35: 180 | G35: TM ok
F36: 110 | G36: TT ok
A41: VIE 9 | F41: 180 | G41: TM ok
F42: 150 | G42: TT ok
A47: SAB 10 / DOM 11 | F47: 220 | G47: TM
F48: =260-140 -> 120 | G48: TT habia 260 se uso 140 cafe OK
F50: 240 | G50: DOM OK
A53: LU12 | B53: 20560 | E53: colorante rojo | F53: 180 | G53: TM OK
F54: 100 | G54: TT OK
A59: MA 13 | F59: 230 | G59: TM OK
F60: 230 | G60: TT OK
A65: MIE 14 | G65: TM habia 270 se uso mary
F66: 120 | G66: TT habia 200 se uso 80 cafe OK
A71: JUE 15 | F71: 150 | G71: TM OK
F72: 200 | G72: TT OK
A77: VIE 16 | F77: 200 | G77: TM OK
F78: 200 | G78: TT OK
A83: SAB 17 / DOM 18 | F83: 100 | G83: SAB TM habia 140, 40 se uso para milo ok
F84: 100 | G84: SAB TT ok
F86: 160 | G86: DOM ok
A89: LU 19 | F89: 250 | G89: TM ok
F90: 300 | G90: TT ok
A95: MA 20 | F95: 300 | G95: TM ok
F96: 250 | G96: TT ok
A101: MIE 21 | B101: 157598 | E101: PAPELERA SAN CRISTOBAL | F101: 60 | G101: TM habia 140, 80 se uso para cafe ok
F102: 140 | G102: TT ok
A107: JUE 22 | G107: TM habia 200 uso h100 y c 100
F108: 200 | G108: TT ok
A113: VIE 23 | F113: 170 | G113: TM habia 212 se uso 42 la sere ok
F114: 100 | G114: TT ok
A119: SAB 24 | G119: TM habia 160 se uso sueldo pris
G120: TT habia 190 se uso 113 milkaut y 70 sueldo cami
A125: LU 26 | D125: 6900 | E125: brie | F125: 180 | G125: TM
F126: 130 | G126: TT
A131: MA 27 | D131: 9400 | E131: brie | F131: 280 | G131: TM
D132: 7200 | E132: mayonesa | F132: 20 | G132: habia 90, se uso 70 semas
A137: MIE 28 | F137: 230 | G137: TM
F138: 250 | G138: TT
A143: JUE 29 | F143: 250 | G143: TM
F144: 200 | G144: TT | H144: -80 | I144: -80 | J144: Ef 27/1 ambos
H145: -50 | J145: Mp 29/1
H146: -90 | J146: Galicia 29/1
I147: 1420000 | J147: 29/1 tome credito de mp para pagar abl y expensas
H148: =2000000 -> 2000000 | J148: 19/2 hernan puso para pagar suss e iva
A149: VIE 30 | F149: 200 | G149: TM
F150: 110 | G150: TT
A155: SAB 31 | F155: 150 | G155: TM
F156: 130 | G156: TT
A161: MA 30
A167: MIE 31
A173: vie 2
A179: sab 3/dom4

Sheet FEBRERO 26
B1: GASTOS MP | C1: GASTOS TRANSFER | D1: GASTOS EFT | E1: OBSERVACIONES Y NOTAS | F1: RETIROS DE CAJA | G1: NOTAS | H1: RETIROS HERNAN | I1: RETIROS CECI
A2: LU 2 | F2: 220 | G2: TM (habia 210) OK
F3: 90 | G3: TT habia 200 se uso 110 agunaldo pris OK
A8: MA 3 | B8: 35900 | E8: queso parmesano | F8: 100 | G8: TM habia 200, 100 retiro lau OK
B9: 15100 | E9: ensaladeras breik | G9: TT habia 70 se uso sueldo mary
A15: MIE 4 | F15: 380 | G15: TM OK
F16: 100 | G16: TT OK
A20: JUE 5 | G20: TM habia 400 se uso 200 agui cami 200 sueldo mary
F21: 60 | G21: TT OK
A26: VIE 6 | F26: 500 | G26: TM y TT (habia 490) OK
A35: SAB 7 | G35: TM habia 150se uso sueldos
G36: TT habia 300 se uso alquiler
A41: LU 9 | G41: TM habia 260 se uso alquiler
F42: 200 | G42: TT ok
G43: Hernan puso 140k para alq hacer transfer
A47: MA 10 | F47: 200 | G47: TM ok
F48: 250 | G48: TT ok
F49: 30 | G49: TT ok
A53: MIE 11 | B53: 19800 | E53: papelera san cristobal | G53: TM habia 250 se uso sueldo mary
F54: 30 | G54: TT habia 170, se uso 140 cafe
A59: JUE 12 | F59: 100 | G59: TM ok
G60: TT habia 220 se uso sueldo mary 20 h 100 y c 100
A65: VIE 13 | B65: 27720 | E65: papelera san cristobal | F65: 150 | G65: TM ok
F66: 220 | G66: TT ok
A71: SAB 14 | F71: 100 | G71: TM ok
G73: 1280 hasta aca
G74: 120 se uso priscila TT
F75: 150 | G75: TT
A77: LU 16
A83: MA 17 | F83: 290 | G83: TM y TT
A89: MIE 18 | F89: 230 | G89: TM
F90: 130 | G90: TT
A95: JUE 19 | F95: 210 | G95: TM y TT
A101: VIE 20 | F101: 150 | G101: TM
F102: 250 | G102: TT
A107: SAB 21 | F107: 240 | G107: TM Y TT
A113: LU 23 | G113: TM 340 iva
F114: 200 | G114: TT
A119: MA 24 | C119: 175450 | E119: wraps | G119: TM habia 220 se uso para el cafe
C120: 80000 | E120: marcelo reparacion aire | F120: 100 | G120: TT habia 150 se uso50k la sere
A125: MIE 25 | G125: TM habia 300 se uso 210 semas
G126: 90 iva
G127: TT 200 se uso iva
A131: JUE 26 | F131: 250 | G131: TM
G132: TT 200 habia se uso pagos milk y la sere
A137: VIE 27 | F137: 170 | G137: TM
F138: 200 | G138: TT
A143: SAB 28 | F143: 180 | G143: cierre parcial 13:40hs
F144: 90 | H144: -80 | I144: -80 | J144: Ef 27/1 ambos
F145: 110 | G145: se uso milkaut | H145: -50 | J145: Mp 29/1
H146: -90 | J146: Galicia 29/1
I147: 1420000 | J147: 29/1 tome credito de mp para pagar abl y expensas
A161: MA 30
A167: MIE 31
A173: vie 2
A179: sab 3/dom4

Sheet MARZO 26
B1: GASTOS MP | C1: GASTOS TRANSFER | D1: GASTOS EFT | E1: OBSERVACIONES Y NOTAS | F1: RETIROS DE CAJA | G1: NOTAS | H1: RETIROS HERNAN | I1: RETIROS CECI
A2: LU 2 | G2: TM habia 180 se uso pris
G3: TT habia 220 se uso herrero y bebida
D4: 120 | E4: HERRERO
A8: MA 3 | G8: TM habia 350 se uso mary
F9: 200 | G9: TT ok
A15: MIE 4 | G15: TM habia 200 se uso mary
F16: 110 | G16: TT habia 180 -70 cafe
A20: JUE 5 | D20: 8910 | E20: vitalcer sal en escamas | F20: 180 | G20: TM
F21: 150 | G21: TT habia 200, se pago serenisima 50 ok
A26: VIE 6 | F26: 150 | G26: TM ok
F27: 200 | G27: TT ok
A35: SAB 7 | F35: 290 | G35: TM 14:20hs se uso sueldos
F36: 130 | G36: habia 230se uso 100 alquiler
A41: LU 9 | F41: 150 | G41: TM
F42: 190 | G42: TT
A47: MA 10 | F47: 60 | G47: habia 300 se uso 140 y 100 en bebidas y semas
A53: MIE 11 | F53: 350 | G53: TM
G54: TT falta el sobre
A59: JUE 12 | G59: TM habia 250 se uso sueldo mary
F60: 300 | G60: TT
A65: VIE 13 | F65: 200 | G65: TM
F66: 200 | G66: TT habia 250 se uso 52 huevos
A71: SAB 14 | F71: 250 | G71: TM se uso sueldos
F72: 130 | G72: TT se uso 70 milkaut quedo 60 ok
A77: LU 16 | F77: 270 | G77: TM se usó sueldo mary
A83: MA 17 | G83: 200 habia se uso para priscila
F84: 110 | G84: TT ok
A89: MIE 18 | F89: 300 | G89: TM ok
G90: TT habia 110 se uso cafe ok
A95: JUE 19 | F95: 210 | G95: TM se uso 170 mary quedo 40 ok
F96: 220 | G96: TT se uso 20 hielo quedo 200 ok
A101: VIE 20 | F101: 200 | G101: TM ok
F102: 280 | G102: TT ok
A107: SAB 21 | F107: 250 | G107: TM se uso sueldo
F108: 70 | G108: TT habia 120 se uso 50 pri ok
A113: LU 23
F114: 100 | G114: TM y TT habia 300, se uso 200 leo ok
A119: MA 24 | F119: 310 | G119: TM yTT ok
A125: MIE 25 | G125: 230 se uso 100 alq y 130pri
F126: 100 | G126: TT ok
A131: JUE 26 | F131: 200 | G131: habia 600 TM y TT se uso 140 cafe y 270 mary ok
A137: VIE 27 | G137: TM habia 120 retiro h
F138: 70000 | G138: TT ok
A143: SAB 28 | F143: 230 | G143: TM ok
F144: 220 | G144: TT ok | H144: -80 | I144: -80 | J144: Ef 27/1 ambos
H145: -50 | J145: Mp 29/1
H146: -90 | J146: Galicia 29/1
I147: 1420000 | J147: 29/1 tome credito de mp para pagar abl y expensas
A149: LU 30 | F149: 180 | G149: TM ok
F150: 90 | G150: TT ok
A155: MA 31 | F155: 400 | G155: TM Y TT ok
A161: vie 2
A167: sab 3/dom4

Sheet ABRIL26
B1: GASTOS MP | C1: GASTOS TRANSFER | D1: GASTOS EFT | E1: OBSERVACIONES Y NOTAS | F1: RETIROS DE CAJA | G1: NOTAS | H1: RETIROS HERNAN | I1: RETIROS CECI
A2: MIE1 | F2: 400 | G2: TM y TT ok
A8: JUE 2 | F8: 120 | G8: TM yTT ok
A15: VIE 3 | F15: 170 | G15: TM y TT ok
A20: SAB 4 | F20: 140 | G20: TM ok
F21: 220 | G21: TT
A26: LU 6 | F26: =230-230 -> 0
A35: MA 7 | F35: 150
F36: =260-150 -> 110
A41: MIE 8 | F41: 300
F42: 160
A47: JUE 9 | F47: 330
F48: 310
A53: VIE 10 | F53: =220-200 -> 20
F54: 140 | G54: tt
A59: SAB 11 | F59: 250
F60: 120 | G60: TT OK
A65: LUN 13 | F65: =300-270 -> 30 | G65: 270 MARY OK
F66: 110 | G66: 110 LA SERENISIMA OK
A71: MA 14 | F71: =200-148 -> 52 | G71: 144 CAFE OK
F72: 0 | G72: 80 LEO 200 JUAN OK
A77: MIER 15 | F77: 30 | G77: 240 BEBIDA 30 MARY OK
F78: =130-130 -> 0 | G78: 130 LEO OK
A83: JUE 16 | F83: 320 | G83: TM OK
F84: 120 | G84: TT OK
A89: VIE 17 | F89: 0 | G89: 240 MARY OK
F90: 70 | G90: TT
A95: SAB 18 | F95: 180 | G95: TM
F96: =200-200 -> 0 | G96: TT ALQ B
A101: LUN 2O | F101: =270-270 -> 0 | G101: TM y TT ALQ B
A107: 46102 | F107: 120 | G107: TM
F108: 140 | G108: TT
A113: MIE 22 | F113: 200 | G113: TM
F114: =210-110 -> 100 | G114: TT -110 CAFE
A119: JUE 23 | F119: 290 | G119: TM
F120: 300 | G120: TT
A125: VIE 24
A131: SAB 25
A137: LUN 27 | F137: 400
A143: 46109 | F143: 200
F144: 0 | G144: 100 DEPBCO mary | J144: Ef 27/1 ambos
J145: Mp 29/1
J146: Galicia 29/1
J147: 29/1 tome credito de mp para pagar abl y expensas
A149: MIER 29 | F149: 260
F150: 0 | G150: 110 cafe + 130 mary
A155: JUE 30 | F155: 0 | G155: 200 j + 50 M
F156: 160
A161: VIE 1 | F161: 400
A167: SAB 2 | F167: 190
A173: vie 2

Sheet MAYO26
B1: GASTOS MP | C1: GASTOS TRANSFER | D1: GASTOS EFT | E1: OBSERVACIONES Y NOTAS | F1: RETIROS DE CAJA | G1: NOTAS | H1: RETIROS HERNAN | I1: RETIROS CECI
A2: SAB 2 | F2: 70
A8: Lun 4 | F8: 120
A15: 46086 | F15: 200
A20: Mier 6 | F20: 400
F21: =210-110-100 -> 0 | G21: Cafe y Mary
A26: Jue 7 | F26: 200
F27: 110
A32: Vier 8 | F32: 200
F33: 200
A38: SAB 9 | F38: 140
F39: 90
A44: JUE 9
A50: VIE 10
A56: SAB 11
A62: LUN 13
A68: MA 14
A74: MIER 15
A80: JUE 16
A86: VIE 17
A92: SAB 18
A98: LUN 2O
A104: 46102
A110: MIE 22
A116: JUE 23
A122: VIE 24
A128: SAB 25
A134: LUN 27
A140: 46109
J141: Ef 27/1 ambos
J142: Mp 29/1
J143: Galicia 29/1
J144: 29/1 tome credito de mp para pagar abl y expensas
A146: MIER 29
A152: JUE 30
A158: VIE 1
A164: SAB 2
A170: vie 2

Sheet GASTOS FIJOS 2025
A1: MAYO
A2: ESTADO DE CUENTA: SERVICIOS Y GASTOS FIJOS
A3: SERVICIO | B3: 1ER VTO | C3: 2DO VTO | D3: MONTO | E3: ESTADO DE PAGO | G3: MODO DE PAGO | H3: ESTADO DE VTO | I3: DIAS DDE VTO | J3: DEBITO AUTOMATICO
A4: EDESUR del mes | D4: 647683.57 | E4: TRUE | F4: =IF(E4,"PAGADO","ADEUDA") -> PAGADO | G4: mercado pago | H4: =IF(C4<TODAY(),"VENCIDA",IF(C4=TODAY(),"VENCE HOY",IF(C4>TODAY(),"VIGENTE"))) -> VENCIDA | I4: =TODAY()-C4 -> 46167 | J4: FALSE
A5: EDESUR adeudado | B5: 45782 | D5: 506809.15 | E5: TRUE | F5: =IF(E5,"PAGADO","ADEUDA") -> PAGADO | G5: transferencia | H5: =IF(C5<TODAY(),"VENCIDA",IF(C5=TODAY(),"VENCE HOY",IF(C5>TODAY(),"VIGENTE"))) -> VENCIDA | I5: =TODAY()-B5 -> 385 | J5: FALSE | K5: se pago el 2/6
A6: METROGAS del mes 4 | B6: 45782 | D6: 180334.64 | E6: FALSE | F6: =IF(E6,"PAGADO","ADEUDA") -> ADEUDA | G6: transferencia | H6: =IF(C6<TODAY(),"VENCIDA",IF(C6=TODAY(),"VENCE HOY",IF(C6>TODAY(),"VIGENTE"))) -> VENCIDA | I6: =TODAY()-B6 -> 385 | J6: FALSE
